Workbook

Sheet JOURNAL
B1: JOURNAL 2025-2026
B2: Bénéfice/Perte | C2: =LOOKUP(9^9,Q:Q)-P4 -> #N/A
B3: Compte | C3: N° | D3: Date | E3: Montant | F3: En faveur de | G3: Libellé | H3: Entré par | I3: Coffre/Banque | J3: Centre de coûts | K3: N°Référence | L3: Solde Compte Courant | M3: Solde Coffre | N3: Solde Compte Epargne | O3: Solde Compte MyPos | P3: Total | V3: Abréviations comptables
C4: 0 | D4: 45866 | G4: solde compte initial | L4: 4619.01 | M4: 1995.65 | N4: 42.64 | O4: =IF(B4="","",IF(I4="CompteMyPos",IF(IF(ISNA(VLOOKUP(B4,DATA!$A$1:$A$15,1,0)),"",VLOOKUP(B4,DATA!$A$1:$A$15,1,0))="",O3+E4,O3-E4),O3)) | P4: =IF(L4="", "", SUM(L4,M4,N4,O4)) -> 6657.3 | V4: MCA | W4: Manuel Cabras
B5: EVENTS / Produits | C5: =C4+1 -> 1 | D5: 45911 | E5: 24 | F5: BLV | G5: Entrée cash journéée d''accueil | H5: MCA | I5: Coffre | J5: JACC | L5: =IF(B5="","",IF(I5="CompteCourant",IF(IF(ISNA(VLOOKUP(B5,DATA!$A$1:$A$16,1,0)),"",VLOOKUP(B5,DATA!$A$1:$A$16,1,0))="",L4+E5,L4-E5),L4)) -> 4619.01 | M5: =IF(B5="","",IF(I5="Coffre",IF(IF(ISNA(VLOOKUP(B5,DATA!$A$1:$A$16,1,0)),"",VLOOKUP(B5,DATA!$A$1:$A$16,1,0))="",M4+E5,M4-E5),M4)) -> 2019.65 | N5: =IF(B5="","",IF(I5="CompteEpargne",IF(IF(ISNA(VLOOKUP(B5,DATA!$A$1:$A$16,1,0)),"",VLOOKUP(B5,DATA!$A$1:$A$16,1,0))="",N4+E5,N4-E5),N4)) -> 42.64 | O5: =IF(B5="","",IF(I5="CompteMyPos",IF(IF(ISNA(VLOOKUP(B5,DATA!$A$1:$A$15,1,0)),"",VLOOKUP(B5,DATA!$A$1:$A$15,1,0))="",O4+E5,O4-E5),O4)) | P5: =IF(L5="", "", SUM(L5,M5,N5,O5)) -> 6681.3
B6: EVENTS / Charges | C6: =C5+1 -> 2 | D6: 45912 | E6: 54 | F6: Landi | G6: JA : Charbon | H6: MCA | I6: CompteCourant | J6: JACC | L6: =IF(B6="","",IF(I6="CompteCourant",IF(IF(ISNA(VLOOKUP(B6,DATA!$A$1:$A$16,1,0)),"",VLOOKUP(B6,DATA!$A$1:$A$16,1,0))="",L5+E6,L5-E6),L5)) -> 4565.01 | M6: =IF(B6="","",IF(I6="Coffre",IF(IF(ISNA(VLOOKUP(B6,DATA!$A$1:$A$16,1,0)),"",VLOOKUP(B6,DATA!$A$1:$A$16,1,0))="",M5+E6,M5-E6),M5)) -> 2019.65 | N6: =IF(B6="","",IF(I6="CompteEpargne",IF(IF(ISNA(VLOOKUP(B6,DATA!$A$1:$A$16,1,0)),"",VLOOKUP(B6,DATA!$A$1:$A$16,1,0))="",N5+E6,N5-E6),N5)) -> 42.64 | O6: =IF(B6="","",IF(I6="CompteMyPos",IF(IF(ISNA(VLOOKUP(B6,DATA!$A$1:$A$15,1,0)),"",VLOOKUP(B6,DATA!$A$1:$A$15,1,0))="",O5+E6,O5-E6),O5)) | P6: =IF(L6="", "", SUM(L6,M6,N6,O6)) -> 6627.3
B7: EVENTS / Charges | C7: =C6+1 -> 3 | D7: 46279 | E7: 175.5 | F7: Landi | G7: SG1 : Charbon | H7: MCA | I7: CompteCourant | J7: SEGRILL1 | L7: =IF(B7="","",IF(I7="CompteCourant",IF(IF(ISNA(VLOOKUP(B7,DATA!$A$1:$A$16,1,0)),"",VLOOKUP(B7,DATA!$A$1:$A$16,1,0))="",L6+E7,L6-E7),L6)) -> 4389.51 | M7: =IF(B7="","",IF(I7="Coffre",IF(IF(ISNA(VLOOKUP(B7,DATA!$A$1:$A$16,1,0)),"",VLOOKUP(B7,DATA!$A$1:$A$16,1,0))="",M6+E7,M6-E7),M6)) -> 2019.65 | N7: =IF(B7="","",IF(I7="CompteEpargne",IF(IF(ISNA(VLOOKUP(B7,DATA!$A$1:$A$16,1,0)),"",VLOOKUP(B7,DATA!$A$1:$A$16,1,0))="",N6+E7,N6-E7),N6)) -> 42.64 | O7: =IF(B7="","",IF(I7="CompteMyPos",IF(IF(ISNA(VLOOKUP(B7,DATA!$A$1:$A$15,1,0)),"",VLOOKUP(B7,DATA!$A$1:$A$15,1,0))="",O6+E7,O6-E7),O6)) | P7: =IF(L7="", "", SUM(L7,M7,N7,O7)) -> 6451.8
B8: DIVERS / Charges | C8: =C7+1 -> 4 | D8: 46279 | E8: 10.8 | F8: Landi | G8: Bière pour local | H8: MCA | I8: CompteCourant | J8: AFTER | L8: =IF(B8="","",IF(I8="CompteCourant",IF(IF(ISNA(VLOOKUP(B8,DATA!$A$1:$A$16,1,0)),"",VLOOKUP(B8,DATA!$A$1:$A$16,1,0))="",L7+E8,L7-E8),L7)) -> 4378.71 | M8: =IF(B8="","",IF(I8="Coffre",IF(IF(ISNA(VLOOKUP(B8,DATA!$A$1:$A$16,1,0)),"",VLOOKUP(B8,DATA!$A$1:$A$16,1,0))="",M7+E8,M7-E8),M7)) -> 2019.65 | N8: =IF(B8="","",IF(I8="CompteEpargne",IF(IF(ISNA(VLOOKUP(B8,DATA!$A$1:$A$16,1,0)),"",VLOOKUP(B8,DATA!$A$1:$A$16,1,0))="",N7+E8,N7-E8),N7)) -> 42.64 | O8: =IF(B8="","",IF(I8="CompteMyPos",IF(IF(ISNA(VLOOKUP(B8,DATA!$A$1:$A$15,1,0)),"",VLOOKUP(B8,DATA!$A$1:$A$15,1,0))="",O7+E8,O7-E8),O7)) | P8: =IF(L8="", "", SUM(L8,M8,N8,O8)) -> 6441
B9: EVENTS / Produits | C9: =C8+1 -> 5 | D9: 45915 | E9: 60 | F9: BLV | G9: SG1 15.09 : Recette lundi midi CASH | H9: MCA | I9: Coffre | J9: SEGRILL1 | L9: =IF(B9="","",IF(I9="CompteCourant",IF(IF(ISNA(VLOOKUP(B9,DATA!$A$1:$A$16,1,0)),"",VLOOKUP(B9,DATA!$A$1:$A$16,1,0))="",L8+E9,L8-E9),L8)) -> 4378.71 | M9: =IF(B9="","",IF(I9="Coffre",IF(IF(ISNA(VLOOKUP(B9,DATA!$A$1:$A$16,1,0)),"",VLOOKUP(B9,DATA!$A$1:$A$16,1,0))="",M8+E9,M8-E9),M8)) -> 2079.65 | N9: =IF(B9="","",IF(I9="CompteEpargne",IF(IF(ISNA(VLOOKUP(B9,DATA!$A$1:$A$16,1,0)),"",VLOOKUP(B9,DATA!$A$1:$A$16,1,0))="",N8+E9,N8-E9),N8)) -> 42.64 | O9: =IF(B9="","",IF(I9="CompteMyPos",IF(IF(ISNA(VLOOKUP(B9,DATA!$A$1:$A$15,1,0)),"",VLOOKUP(B9,DATA!$A$1:$A$15,1,0))="",O8+E9,O8-E9),O8)) | P9: =IF(L9="", "", SUM(L9,M9,N9,O9)) -> 6501
B10: EVENTS / Produits | C10: =C9+1 -> 6 | D10: 45915 | E10: 38 | F10: BLV | G10: SG1 15.09 : Recette lundi après-midi CASH | H10: MCA | I10: Coffre | J10: SEGRILL1 | L10: =IF(B10="","",IF(I10="CompteCourant",IF(IF(ISNA(VLOOKUP(B10,DATA!$A$1:$A$16,1,0)),"",VLOOKUP(B10,DATA!$A$1:$A$16,1,0))="",L9+E10,L9-E10),L9)) -> 4378.71 | M10: =IF(B10="","",IF(I10="Coffre",IF(IF(ISNA(VLOOKUP(B10,DATA!$A$1:$A$16,1,0)),"",VLOOKUP(B10,DATA!$A$1:$A$16,1,0))="",M9+E10,M9-E10),M9)) -> 2117.65 | N10: =IF(B10="","",IF(I10="CompteEpargne",IF(IF(ISNA(VLOOKUP(B10,DATA!$A$1:$A$16,1,0)),"",VLOOKUP(B10,DATA!$A$1:$A$16,1,0))="",N9+E10,N9-E10),N9)) -> 42.64 | O10: =IF(B10="","",IF(I10="CompteMyPos",IF(IF(ISNA(VLOOKUP(B10,DATA!$A$1:$A$15,1,0)),"",VLOOKUP(B10,DATA!$A$1:$A$15,1,0))="",O9+E10,O9-E10),O9)) | P10: =IF(L10="", "", SUM(L10,M10,N10,O10)) -> 6539 | V10: Abréviations libellés
B11: EVENTS / Produits | C11: =C10+1 -> 7 | D11: 45916 | E11: 101.85 | F11: BLV | G11: AL : Entrées au 16.09 (beer money) | H11: MCA | I11: Coffre | J11: AFTER | L11: =IF(B11="","",IF(I11="CompteCourant",IF(IF(ISNA(VLOOKUP(B11,DATA!$A$1:$A$16,1,0)),"",VLOOKUP(B11,DATA!$A$1:$A$16,1,0))="",L10+E11,L10-E11),L10)) -> 4378.71 | M11: =IF(B11="","",IF(I11="Coffre",IF(IF(ISNA(VLOOKUP(B11,DATA!$A$1:$A$16,1,0)),"",VLOOKUP(B11,DATA!$A$1:$A$16,1,0))="",M10+E11,M10-E11),M10)) -> 2219.5 | N11: =IF(B11="","",IF(I11="CompteEpargne",IF(IF(ISNA(VLOOKUP(B11,DATA!$A$1:$A$16,1,0)),"",VLOOKUP(B11,DATA!$A$1:$A$16,1,0))="",N10+E11,N10-E11),N10)) -> 42.64 | O11: =IF(B11="","",IF(I11="CompteMyPos",IF(IF(ISNA(VLOOKUP(B11,DATA!$A$1:$A$15,1,0)),"",VLOOKUP(B11,DATA!$A$1:$A$15,1,0))="",O10+E11,O10-E11),O10)) | P11: =IF(L11="", "", SUM(L11,M11,N11,O11)) -> 6640.85 | V11: AB | W11: After Baleinev
B12: EVENTS / Produits | C12: =C11+1 -> 8 | D12: 45916 | E12: 23 | F12: BLV | G12: SG1 16.09 : Recette CASH | H12: MCA | I12: Coffre | J12: SEGRILL1 | L12: =IF(B12="","",IF(I12="CompteCourant",IF(IF(ISNA(VLOOKUP(B12,DATA!$A$1:$A$16,1,0)),"",VLOOKUP(B12,DATA!$A$1:$A$16,1,0))="",L11+E12,L11-E12),L11)) -> 4378.71 | M12: =IF(B12="","",IF(I12="Coffre",IF(IF(ISNA(VLOOKUP(B12,DATA!$A$1:$A$16,1,0)),"",VLOOKUP(B12,DATA!$A$1:$A$16,1,0))="",M11+E12,M11-E12),M11)) -> 2242.5 | N12: =IF(B12="","",IF(I12="CompteEpargne",IF(IF(ISNA(VLOOKUP(B12,DATA!$A$1:$A$16,1,0)),"",VLOOKUP(B12,DATA!$A$1:$A$16,1,0))="",N11+E12,N11-E12),N11)) -> 42.64 | O12: =IF(B12="","",IF(I12="CompteMyPos",IF(IF(ISNA(VLOOKUP(B12,DATA!$A$1:$A$15,1,0)),"",VLOOKUP(B12,DATA!$A$1:$A$15,1,0))="",O11+E12,O11-E12),O11)) | P12: =IF(L12="", "", SUM(L12,M12,N12,O12)) -> 6663.85 | V12: AGE | W12: Événements AGE
B13: EVENTS / Produits | C13: =C12+1 -> 9 | D13: 45912 | E13: 178.64 | F13: BLV | G13: AL du 10.09 | H13: MCA | I13: CompteCourant | J13: AFTER | L13: =IF(B13="","",IF(I13="CompteCourant",IF(IF(ISNA(VLOOKUP(B13,DATA!$A$1:$A$16,1,0)),"",VLOOKUP(B13,DATA!$A$1:$A$16,1,0))="",L12+E13,L12-E13),L12)) -> 4557.35 | M13: =IF(B13="","",IF(I13="Coffre",IF(IF(ISNA(VLOOKUP(B13,DATA!$A$1:$A$16,1,0)),"",VLOOKUP(B13,DATA!$A$1:$A$16,1,0))="",M12+E13,M12-E13),M12)) -> 2242.5 | N13: =IF(B13="","",IF(I13="CompteEpargne",IF(IF(ISNA(VLOOKUP(B13,DATA!$A$1:$A$16,1,0)),"",VLOOKUP(B13,DATA!$A$1:$A$16,1,0))="",N12+E13,N12-E13),N12)) -> 42.64 | O13: =IF(B13="","",IF(I13="CompteMyPos",IF(IF(ISNA(VLOOKUP(B13,DATA!$A$1:$A$15,1,0)),"",VLOOKUP(B13,DATA!$A$1:$A$15,1,0))="",O12+E13,O12-E13),O12)) | P13: =IF(L13="", "", SUM(L13,M13,N13,O13)) -> 6842.49 | V13: Am | W13: Amalgame
B14: EVENTS / Produits | C14: =C13+1 -> 10 | D14: 45915 | E14: 143.09 | F14: BLV | G14: JA 11.09 : Recette TWINT | H14: MCA | I14: CompteCourant | J14: JACC | L14: =IF(B14="","",IF(I14="CompteCourant",IF(IF(ISNA(VLOOKUP(B14,DATA!$A$1:$A$16,1,0)),"",VLOOKUP(B14,DATA!$A$1:$A$16,1,0))="",L13+E14,L13-E14),L13)) -> 4700.44 | M14: =IF(B14="","",IF(I14="Coffre",IF(IF(ISNA(VLOOKUP(B14,DATA!$A$1:$A$16,1,0)),"",VLOOKUP(B14,DATA!$A$1:$A$16,1,0))="",M13+E14,M13-E14),M13)) -> 2242.5 | N14: =IF(B14="","",IF(I14="CompteEpargne",IF(IF(ISNA(VLOOKUP(B14,DATA!$A$1:$A$16,1,0)),"",VLOOKUP(B14,DATA!$A$1:$A$16,1,0))="",N13+E14,N13-E14),N13)) -> 42.64 | O14: =IF(B14="","",IF(I14="CompteMyPos",IF(IF(ISNA(VLOOKUP(B14,DATA!$A$1:$A$15,1,0)),"",VLOOKUP(B14,DATA!$A$1:$A$15,1,0))="",O13+E14,O13-E14),O13)) | P14: =IF(L14="", "", SUM(L14,M14,N14,O14)) -> 6985.58 | V14: BF22 | W14: Baleinev Festival 2022
B15: EVENTS / Produits | C15: =C14+1 -> 11 | D15: 45917 | E15: 146.03 | F15: BLV | G15: SG1 15.09 : Recette TWINT | H15: MCA | I15: CompteCourant | J15: SEGRILL1 | L15: =IF(B15="","",IF(I15="CompteCourant",IF(IF(ISNA(VLOOKUP(B15,DATA!$A$1:$A$16,1,0)),"",VLOOKUP(B15,DATA!$A$1:$A$16,1,0))="",L14+E15,L14-E15),L14)) -> 4846.47 | M15: =IF(B15="","",IF(I15="Coffre",IF(IF(ISNA(VLOOKUP(B15,DATA!$A$1:$A$16,1,0)),"",VLOOKUP(B15,DATA!$A$1:$A$16,1,0))="",M14+E15,M14-E15),M14)) -> 2242.5 | N15: =IF(B15="","",IF(I15="CompteEpargne",IF(IF(ISNA(VLOOKUP(B15,DATA!$A$1:$A$16,1,0)),"",VLOOKUP(B15,DATA!$A$1:$A$16,1,0))="",N14+E15,N14-E15),N14)) -> 42.64 | O15: =IF(B15="","",IF(I15="CompteMyPos",IF(IF(ISNA(VLOOKUP(B15,DATA!$A$1:$A$15,1,0)),"",VLOOKUP(B15,DATA!$A$1:$A$15,1,0))="",O14+E15,O14-E15),O14)) | P15: =IF(L15="", "", SUM(L15,M15,N15,O15)) -> 7131.61 | V15: BF23 | W15: Baleinev Festival 2023
B16: EVENTS / Produits | C16: =C15+1 -> 12 | D16: 45916 | E16: 153.93 | F16: BLV | G16: SG1 16.09 : Recette TWINT | H16: MCA | I16: CompteCourant | J16: SEGRILL1 | L16: =IF(B16="","",IF(I16="CompteCourant",IF(IF(ISNA(VLOOKUP(B16,DATA!$A$1:$A$16,1,0)),"",VLOOKUP(B16,DATA!$A$1:$A$16,1,0))="",L15+E16,L15-E16),L15)) -> 5000.4 | M16: =IF(B16="","",IF(I16="Coffre",IF(IF(ISNA(VLOOKUP(B16,DATA!$A$1:$A$16,1,0)),"",VLOOKUP(B16,DATA!$A$1:$A$16,1,0))="",M15+E16,M15-E16),M15)) -> 2242.5 | N16: =IF(B16="","",IF(I16="CompteEpargne",IF(IF(ISNA(VLOOKUP(B16,DATA!$A$1:$A$16,1,0)),"",VLOOKUP(B16,DATA!$A$1:$A$16,1,0))="",N15+E16,N15-E16),N15)) -> 42.64 | O16: =IF(B16="","",IF(I16="CompteMyPos",IF(IF(ISNA(VLOOKUP(B16,DATA!$A$1:$A$15,1,0)),"",VLOOKUP(B16,DATA!$A$1:$A$15,1,0))="",O15+E16,O15-E16),O15)) | P16: =IF(L16="", "", SUM(L16,M16,N16,O16)) -> 7285.54 | V16: BS | W16: Baleiski
B17: EVENTS / Produits | C17: =C16+1 -> 13 | D17: 45918 | E17: 236.84 | F17: BLV | G17: SG1 17.09 : Recette TWINT | H17: MCA | I17: CompteCourant | J17: SEGRILL1 | L17: =IF(B17="","",IF(I17="CompteCourant",IF(IF(ISNA(VLOOKUP(B17,DATA!$A$1:$A$16,1,0)),"",VLOOKUP(B17,DATA!$A$1:$A$16,1,0))="",L16+E17,L16-E17),L16)) -> 5237.24 | M17: =IF(B17="","",IF(I17="Coffre",IF(IF(ISNA(VLOOKUP(B17,DATA!$A$1:$A$16,1,0)),"",VLOOKUP(B17,DATA!$A$1:$A$16,1,0))="",M16+E17,M16-E17),M16)) -> 2242.5 | N17: =IF(B17="","",IF(I17="CompteEpargne",IF(IF(ISNA(VLOOKUP(B17,DATA!$A$1:$A$16,1,0)),"",VLOOKUP(B17,DATA!$A$1:$A$16,1,0))="",N16+E17,N16-E17),N16)) -> 42.64 | O17: =IF(B17="","",IF(I17="CompteMyPos",IF(IF(ISNA(VLOOKUP(B17,DATA!$A$1:$A$15,1,0)),"",VLOOKUP(B17,DATA!$A$1:$A$15,1,0))="",O16+E17,O16-E17),O16)) | P17: =IF(L17="", "", SUM(L17,M17,N17,O17)) -> 7522.38 | V17: Div | W17: Divers
B18: EVENTS / Produits | C18: =C17+1 -> 14 | D18: 45919 | E18: 1016.6 | F18: BLV | G18: SG1 18.09 : Recette TWINT | H18: MCA | I18: CompteCourant | J18: SEGRILL1 | L18: =IF(B18="","",IF(I18="CompteCourant",IF(IF(ISNA(VLOOKUP(B18,DATA!$A$1:$A$16,1,0)),"",VLOOKUP(B18,DATA!$A$1:$A$16,1,0))="",L17+E18,L17-E18),L17)) -> 6253.84 | M18: =IF(B18="","",IF(I18="Coffre",IF(IF(ISNA(VLOOKUP(B18,DATA!$A$1:$A$16,1,0)),"",VLOOKUP(B18,DATA!$A$1:$A$16,1,0))="",M17+E18,M17-E18),M17)) -> 2242.5 | N18: =IF(B18="","",IF(I18="CompteEpargne",IF(IF(ISNA(VLOOKUP(B18,DATA!$A$1:$A$16,1,0)),"",VLOOKUP(B18,DATA!$A$1:$A$16,1,0))="",N17+E18,N17-E18),N17)) -> 42.64 | O18: =IF(B18="","",IF(I18="CompteMyPos",IF(IF(ISNA(VLOOKUP(B18,DATA!$A$1:$A$15,1,0)),"",VLOOKUP(B18,DATA!$A$1:$A$15,1,0))="",O17+E18,O17-E18),O17)) | P18: =IF(L18="", "", SUM(L18,M18,N18,O18)) -> 8538.98 | V18: FG | W18: Frais généraux
B19: EVENTS / Produits | C19: =C18+1 -> 15 | D19: 45919 | E19: =646.21+84.87 -> 731.08 | F19: BLV | G19: AL 18.09 : Recette TWINT | H19: MCA | I19: CompteCourant | J19: AFTER | L19: =IF(B19="","",IF(I19="CompteCourant",IF(IF(ISNA(VLOOKUP(B19,DATA!$A$1:$A$16,1,0)),"",VLOOKUP(B19,DATA!$A$1:$A$16,1,0))="",L18+E19,L18-E19),L18)) -> 6984.92 | M19: =IF(B19="","",IF(I19="Coffre",IF(IF(ISNA(VLOOKUP(B19,DATA!$A$1:$A$16,1,0)),"",VLOOKUP(B19,DATA!$A$1:$A$16,1,0))="",M18+E19,M18-E19),M18)) -> 2242.5 | N19: =IF(B19="","",IF(I19="CompteEpargne",IF(IF(ISNA(VLOOKUP(B19,DATA!$A$1:$A$16,1,0)),"",VLOOKUP(B19,DATA!$A$1:$A$16,1,0))="",N18+E19,N18-E19),N18)) -> 42.64 | O19: =IF(B19="","",IF(I19="CompteMyPos",IF(IF(ISNA(VLOOKUP(B19,DATA!$A$1:$A$15,1,0)),"",VLOOKUP(B19,DATA!$A$1:$A$15,1,0))="",O18+E19,O18-E19),O18)) | P19: =IF(L19="", "", SUM(L19,M19,N19,O19)) -> 9270.06 | V19: GM | W19: Grosse murge
B20: EVENTS / Produits | C20: =C19+1 -> 16 | D20: 45920 | E20: 134.48 | F20: BLV | G20: SG 19.09 : Recette TWINT | H20: MCA | I20: CompteCourant | J20: SEGRILL1 | L20: =IF(B20="","",IF(I20="CompteCourant",IF(IF(ISNA(VLOOKUP(B20,DATA!$A$1:$A$16,1,0)),"",VLOOKUP(B20,DATA!$A$1:$A$16,1,0))="",L19+E20,L19-E20),L19)) -> 7119.4 | M20: =IF(B20="","",IF(I20="Coffre",IF(IF(ISNA(VLOOKUP(B20,DATA!$A$1:$A$16,1,0)),"",VLOOKUP(B20,DATA!$A$1:$A$16,1,0))="",M19+#REF!,M19-#REF!),M19)) -> 2242.5 | N20: =IF(B20="","",IF(I20="CompteEpargne",IF(IF(ISNA(VLOOKUP(B20,DATA!$A$1:$A$16,1,0)),"",VLOOKUP(B20,DATA!$A$1:$A$16,1,0))="",N19+#REF!,N19-#REF!),N19)) -> 42.64 | O20: =IF(B20="","",IF(I20="CompteMyPos",IF(IF(ISNA(VLOOKUP(B20,DATA!$A$1:$A$15,1,0)),"",VLOOKUP(B20,DATA!$A$1:$A$15,1,0))="",O19+#REF!,O19-#REF!),O19)) | P20: =IF(L20="", "", SUM(L20,M20,N20,O20)) -> 9404.54 | V20: LB | W20: Local Baleinev
B21: EVENTS / Produits | C21: =C20+1 -> 17 | D21: 45916 | E21: 23 | F21: BLV | G21: SG 16.09 : Recette CASH | H21: MCA | I21: Coffre | J21: SEGRILL1 | L21: =IF(B21="","",IF(I21="CompteCourant",IF(IF(ISNA(VLOOKUP(B21,DATA!$A$1:$A$16,1,0)),"",VLOOKUP(B21,DATA!$A$1:$A$16,1,0))="",L20+E21,L20-E21),L20)) -> 7119.4 | M21: =IF(B21="","",IF(I21="Coffre",IF(IF(ISNA(VLOOKUP(B21,DATA!$A$1:$A$16,1,0)),"",VLOOKUP(B21,DATA!$A$1:$A$16,1,0))="",M20+E20,M20-E20),M20)) -> 2376.98 | N21: =IF(B21="","",IF(I21="CompteEpargne",IF(IF(ISNA(VLOOKUP(B21,DATA!$A$1:$A$16,1,0)),"",VLOOKUP(B21,DATA!$A$1:$A$16,1,0))="",N20+E20,N20-E20),N20)) -> 42.64 | O21: =IF(B21="","",IF(I21="CompteMyPos",IF(IF(ISNA(VLOOKUP(B21,DATA!$A$1:$A$15,1,0)),"",VLOOKUP(B21,DATA!$A$1:$A$15,1,0))="",O20+E20,O20-E20),O20)) | P21: =IF(L21="", "", SUM(L21,M21,N21,O21)) -> 9539.02 | V21: Pa | W21: Passation
B22: EVENTS / Produits | C22: =C21+1 -> 18 | D22: 45918 | E22: 104 | F22: BLV | G22: AL 18.09 : Recette CASH | H22: MCA | I22: Coffre | J22: AFTER | L22: =IF(B22="","",IF(I22="CompteCourant",IF(IF(ISNA(VLOOKUP(B22,DATA!$A$1:$A$16,1,0)),"",VLOOKUP(B22,DATA!$A$1:$A$16,1,0))="",L21+E22,L21-E22),L21)) -> 7119.4 | M22: =IF(B22="","",IF(I22="Coffre",IF(IF(ISNA(VLOOKUP(B22,DATA!$A$1:$A$16,1,0)),"",VLOOKUP(B22,DATA!$A$1:$A$16,1,0))="",M21+E22,M21-E22),M21)) -> 2480.98 | N22: =IF(B22="","",IF(I22="CompteEpargne",IF(IF(ISNA(VLOOKUP(B22,DATA!$A$1:$A$16,1,0)),"",VLOOKUP(B22,DATA!$A$1:$A$16,1,0))="",N21+E22,N21-E22),N21)) -> 42.64 | O22: =IF(B22="","",IF(I22="CompteMyPos",IF(IF(ISNA(VLOOKUP(B22,DATA!$A$1:$A$15,1,0)),"",VLOOKUP(B22,DATA!$A$1:$A$15,1,0))="",O21+E22,O21-E22),O21)) | P22: =IF(L22="", "", SUM(L22,M22,N22,O22)) -> 9643.02 | V22: PO | W22: Portes ouvertes
B23: EVENTS / Produits | C23: =C22+1 -> 19 | D23: 45919 | E23: 3 | F23: BLV | G23: SG 19.09 : Recette CASH | H23: MCA | I23: Coffre | J23: SEGRILL1 | L23: =IF(B23="","",IF(I23="CompteCourant",IF(IF(ISNA(VLOOKUP(B23,DATA!$A$1:$A$16,1,0)),"",VLOOKUP(B23,DATA!$A$1:$A$16,1,0))="",L22+E23,L22-E23),L22)) -> 7119.4 | M23: =IF(B23="","",IF(I23="Coffre",IF(IF(ISNA(VLOOKUP(B23,DATA!$A$1:$A$16,1,0)),"",VLOOKUP(B23,DATA!$A$1:$A$16,1,0))="",M22+E23,M22-E23),M22)) -> 2483.98 | N23: =IF(B23="","",IF(I23="CompteEpargne",IF(IF(ISNA(VLOOKUP(B23,DATA!$A$1:$A$16,1,0)),"",VLOOKUP(B23,DATA!$A$1:$A$16,1,0))="",N22+E23,N22-E23),N22)) -> 42.64 | O23: =IF(B23="","",IF(I23="CompteMyPos",IF(IF(ISNA(VLOOKUP(B23,DATA!$A$1:$A$15,1,0)),"",VLOOKUP(B23,DATA!$A$1:$A$15,1,0))="",O22+E23,O22-E23),O22)) | P23: =IF(L23="", "", SUM(L23,M23,N23,O23)) -> 9646.02 | V23: RI | W23: Raclette Interrassociation
B24: DIVERS / Charges | C24: =C23+1 -> 20 | D24: 45911 | E24: 23.4 | F24: Landi | G24: AG : Achat bières | H24: MCA | I24: CompteCourant | J24: INTERNE | L24: =IF(B24="","",IF(I24="CompteCourant",IF(IF(ISNA(VLOOKUP(B24,DATA!$A$1:$A$16,1,0)),"",VLOOKUP(B24,DATA!$A$1:$A$16,1,0))="",L23+E24,L23-E24),L23)) -> 7096 | M24: =IF(B24="","",IF(I24="Coffre",IF(IF(ISNA(VLOOKUP(B24,DATA!$A$1:$A$16,1,0)),"",VLOOKUP(B24,DATA!$A$1:$A$16,1,0))="",M23+E24,M23-E24),M23)) -> 2483.98 | N24: =IF(B24="","",IF(I24="CompteEpargne",IF(IF(ISNA(VLOOKUP(B24,DATA!$A$1:$A$16,1,0)),"",VLOOKUP(B24,DATA!$A$1:$A$16,1,0))="",N23+E24,N23-E24),N23)) -> 42.64 | P24: =IF(L24="", "", SUM(L24,M24,N24,O24)) -> 9622.62 | V24: ROA | W24: Rock Oz Arène
B25: EVENTS / Charges | C25: =C24+1 -> 21 | D25: 45911 | E25: 10.5 | F25: Denner | G25: JA : Bonbons | H25: MCA | I25: CompteCourant | J25: JACC | L25: =IF(B25="","",IF(I25="CompteCourant",IF(IF(ISNA(VLOOKUP(B25,DATA!$A$1:$A$16,1,0)),"",VLOOKUP(B25,DATA!$A$1:$A$16,1,0))="",L24+E25,L24-E25),L24)) -> 7085.5 | M25: =IF(B25="","",IF(I25="Coffre",IF(IF(ISNA(VLOOKUP(B25,DATA!$A$1:$A$16,1,0)),"",VLOOKUP(B25,DATA!$A$1:$A$16,1,0))="",M24+E25,M24-E25),M24)) -> 2483.98 | N25: =IF(B25="","",IF(I25="CompteEpargne",IF(IF(ISNA(VLOOKUP(B25,DATA!$A$1:$A$16,1,0)),"",VLOOKUP(B25,DATA!$A$1:$A$16,1,0))="",N24+E25,N24-E25),N24)) -> 42.64 | P25: =IF(L25="", "", SUM(L25,M25,N25,O25)) -> 9612.12 | V25: SE | W25: Sans effet
B26: EVENTS / Charges | C26: =C25+1 -> 22 | D26: 45911 | E26: 15 | F26: Landi | G26: JA : Softs | H26: MCA | I26: CompteCourant | J26: JACC | L26: =IF(B26="","",IF(I26="CompteCourant",IF(IF(ISNA(VLOOKUP(B26,DATA!$A$1:$A$16,1,0)),"",VLOOKUP(B26,DATA!$A$1:$A$16,1,0))="",L25+E26,L25-E26),L25)) -> 7070.5 | M26: =IF(B26="","",IF(I26="Coffre",IF(IF(ISNA(VLOOKUP(B26,DATA!$A$1:$A$16,1,0)),"",VLOOKUP(B26,DATA!$A$1:$A$16,1,0))="",M25+E26,M25-E26),M25)) -> 2483.98 | N26: =IF(B26="","",IF(I26="CompteEpargne",IF(IF(ISNA(VLOOKUP(B26,DATA!$A$1:$A$16,1,0)),"",VLOOKUP(B26,DATA!$A$1:$A$16,1,0))="",N25+E26,N25-E26),N25)) -> 42.64 | P26: =IF(L26="", "", SUM(L26,M26,N26,O26)) -> 9597.12 | V26: SG1 | W26: Semaine grillade n°1
B27: SANS EFFET / Produits | C27: =C26+1 -> 23 | D27: 45914 | E27: 334 | F27: BLV | G27: UNILIVE : DEMANDER MAX | H27: MCA | I27: CompteCourant | J27: INTERNE | L27: =IF(B27="","",IF(I27="CompteCourant",IF(IF(ISNA(VLOOKUP(B27,DATA!$A$1:$A$16,1,0)),"",VLOOKUP(B27,DATA!$A$1:$A$16,1,0))="",L26+E27,L26-E27),L26)) -> 7404.5 | M27: =IF(B27="","",IF(I27="Coffre",IF(IF(ISNA(VLOOKUP(B27,DATA!$A$1:$A$16,1,0)),"",VLOOKUP(B27,DATA!$A$1:$A$16,1,0))="",M26+E27,M26-E27),M26)) -> 2483.98 | N27: =IF(B27="","",IF(I27="CompteEpargne",IF(IF(ISNA(VLOOKUP(B27,DATA!$A$1:$A$16,1,0)),"",VLOOKUP(B27,DATA!$A$1:$A$16,1,0))="",N26+E27,N26-E27),N26)) -> 42.64 | P27: =IF(L27="", "", SUM(L27,M27,N27,O27)) -> 9931.12 | V27: SG2 | W27: Semaine grillade n°2
B28: EVENTS / Charges | C28: =C27+1 -> 24 | D28: 45917 | E28: 500 | F28: Commune de Cheseaux | G28: Caution GM | H28: MCA | I28: CompteCourant | J28: GM | L28: =IF(B28="","",IF(I28="CompteCourant",IF(IF(ISNA(VLOOKUP(B28,DATA!$A$1:$A$16,1,0)),"",VLOOKUP(B28,DATA!$A$1:$A$16,1,0))="",L27+E28,L27-E28),L27)) -> 6904.5 | M28: =IF(B28="","",IF(I28="Coffre",IF(IF(ISNA(VLOOKUP(B28,DATA!$A$1:$A$16,1,0)),"",VLOOKUP(B28,DATA!$A$1:$A$16,1,0))="",M27+E28,M27-E28),M27)) -> 2483.98 | N28: =IF(B28="","",IF(I28="CompteEpargne",IF(IF(ISNA(VLOOKUP(B28,DATA!$A$1:$A$16,1,0)),"",VLOOKUP(B28,DATA!$A$1:$A$16,1,0))="",N27+E28,N27-E28),N27)) -> 42.64 | P28: =IF(L28="", "", SUM(L28,M28,N28,O28)) -> 9431.12 | V28: Spo | W28: Sponsoring
B29: EVENTS / Charges | C29: =C28+1 -> 25 | D29: 45918 | E29: 20.5 | F29: Thomas Brêchet | G29: SG1 : Courses Hot Dogs | H29: MCA | I29: Coffre | J29: SEGRILL1 | L29: =IF(B29="","",IF(I29="CompteCourant",IF(IF(ISNA(VLOOKUP(B29,DATA!$A$1:$A$16,1,0)),"",VLOOKUP(B29,DATA!$A$1:$A$16,1,0))="",L28+E29,L28-E29),L28)) -> 6904.5 | M29: =IF(B29="","",IF(I29="Coffre",IF(IF(ISNA(VLOOKUP(B29,DATA!$A$1:$A$16,1,0)),"",VLOOKUP(B29,DATA!$A$1:$A$16,1,0))="",M28+E29,M28-E29),M28)) -> 2463.48 | N29: =IF(B29="","",IF(I29="CompteEpargne",IF(IF(ISNA(VLOOKUP(B29,DATA!$A$1:$A$16,1,0)),"",VLOOKUP(B29,DATA!$A$1:$A$16,1,0))="",N28+E29,N28-E29),N28)) -> 42.64 | O29: =IF(B29="","",IF(J29="CompteEpargne",IF(IF(ISNA(VLOOKUP(B29,DATA!$A$1:$A$16,1,0)),"",VLOOKUP(B29,DATA!$A$1:$A$16,1,0))="",N23+E29,N23-E29),N23)) -> 42.64 | P29: =IF(L29="", "", SUM(L29,M29,N29,O29)) -> 9453.26 | V29: SVC | W29: Semain vin chaud
B30: EVENTS / Charges | C30: =C29+1 -> 26 | D30: 45918 | E30: 47.25 | F30: Thomas Brêchet | G30: SG1 : Courses Hot Dogs | H30: MCA | I30: Coffre | J30: SEGRILL1 | L30: =IF(B30="","",IF(I30="CompteCourant",IF(IF(ISNA(VLOOKUP(B30,DATA!$A$1:$A$16,1,0)),"",VLOOKUP(B30,DATA!$A$1:$A$16,1,0))="",L29+E30,L29-E30),L29)) -> 6904.5 | M30: =IF(B30="","",IF(I30="Coffre",IF(IF(ISNA(VLOOKUP(B30,DATA!$A$1:$A$16,1,0)),"",VLOOKUP(B30,DATA!$A$1:$A$16,1,0))="",M29+E30,M29-E30),M29)) -> 2416.23 | N30: =IF(B30="","",IF(I30="CompteEpargne",IF(IF(ISNA(VLOOKUP(B30,DATA!$A$1:$A$16,1,0)),"",VLOOKUP(B30,DATA!$A$1:$A$16,1,0))="",N29+E30,N29-E30),N29)) -> 42.64 | O30: =IF(B30="","",IF(J30="CompteEpargne",IF(IF(ISNA(VLOOKUP(B30,DATA!$A$1:$A$16,1,0)),"",VLOOKUP(B30,DATA!$A$1:$A$16,1,0))="",O29+E30,O29-E30),O29)) -> 42.64 | P30: =IF(L30="", "", SUM(L30,M30,N30,O30)) -> 9406.01 | V30: SR | W30: stand rentrée
B31: EVENTS / Charges | C31: =C30+1 -> 27 | D31: 45919 | E31: 21.6 | F31: Landi | G31: SG1 : Courses after (softs) | H31: MCA | I31: CompteCourant | J31: SEGRILL1 | L31: =IF(B31="","",IF(I31="CompteCourant",IF(IF(ISNA(VLOOKUP(B31,DATA!$A$1:$A$16,1,0)),"",VLOOKUP(B31,DATA!$A$1:$A$16,1,0))="",L30+E31,L30-E31),L30)) -> 6882.9 | M31: =IF(B31="","",IF(I31="Coffre",IF(IF(ISNA(VLOOKUP(B31,DATA!$A$1:$A$16,1,0)),"",VLOOKUP(B31,DATA!$A$1:$A$16,1,0))="",M30+E31,M30-E31),M30)) -> 2416.23 | N31: =IF(B31="","",IF(I31="CompteEpargne",IF(IF(ISNA(VLOOKUP(B31,DATA!$A$1:$A$16,1,0)),"",VLOOKUP(B31,DATA!$A$1:$A$16,1,0))="",N30+E31,N30-E31),N30)) -> 42.64 | O31: =IF(B31="","",IF(J31="CompteEpargne",IF(IF(ISNA(VLOOKUP(B31,DATA!$A$1:$A$16,1,0)),"",VLOOKUP(B31,DATA!$A$1:$A$16,1,0))="",O30+E31,O30-E31),O30)) -> 42.64 | P31: =IF(L31="", "", SUM(L31,M31,N31,O31)) -> 9384.41 | V31: AL | W31: after local
B32: EVENTS / Produits | C32: =C31+1 -> 28 | D32: 45925 | E32: 700 | F32: BLV | G32: Mobilière : Remboursement incident POS | H32: MCA | I32: CompteCourant | J32: INTERNE | L32: =IF(B32="","",IF(I32="CompteCourant",IF(IF(ISNA(VLOOKUP(B32,DATA!$A$1:$A$16,1,0)),"",VLOOKUP(B32,DATA!$A$1:$A$16,1,0))="",L31+E32,L31-E32),L31)) -> 7582.9 | M32: =IF(B32="","",IF(I32="Coffre",IF(IF(ISNA(VLOOKUP(B32,DATA!$A$1:$A$16,1,0)),"",VLOOKUP(B32,DATA!$A$1:$A$16,1,0))="",M31+E32,M31-E32),M31)) -> 2416.23 | N32: =IF(B32="","",IF(I32="CompteEpargne",IF(IF(ISNA(VLOOKUP(B32,DATA!$A$1:$A$16,1,0)),"",VLOOKUP(B32,DATA!$A$1:$A$16,1,0))="",N31+E32,N31-E32),N31)) -> 42.64 | O32: =IF(B32="","",IF(J32="CompteEpargne",IF(IF(ISNA(VLOOKUP(B32,DATA!$A$1:$A$16,1,0)),"",VLOOKUP(B32,DATA!$A$1:$A$16,1,0))="",O31+E32,O31-E32),O31)) -> 42.64 | P32: =IF(L32="", "", SUM(L32,M32,N32,O32)) -> 10084.41 | V32: AS | W32: apéro de soutien
B33: ADMINISTRATION / Charges | C33: =C32+1 -> 29 | D33: 45930 | E33: 25.2 | F33: BCV | G33: Frais périodiques | H33: MCA | I33: CompteCourant | J33: INTERNE | L33: =IF(B33="","",IF(I33="CompteCourant",IF(IF(ISNA(VLOOKUP(B33,DATA!$A$1:$A$16,1,0)),"",VLOOKUP(B33,DATA!$A$1:$A$16,1,0))="",L32+E33,L32-E33),L32)) -> 7557.7 | M33: =IF(B33="","",IF(I33="Coffre",IF(IF(ISNA(VLOOKUP(B33,DATA!$A$1:$A$16,1,0)),"",VLOOKUP(B33,DATA!$A$1:$A$16,1,0))="",M32+E33,M32-E33),M32)) -> 2416.23 | N33: =IF(B33="","",IF(I33="CompteEpargne",IF(IF(ISNA(VLOOKUP(B33,DATA!$A$1:$A$16,1,0)),"",VLOOKUP(B33,DATA!$A$1:$A$16,1,0))="",N32+E33,N32-E33),N32)) -> 42.64 | O33: =IF(B33="","",IF(J33="CompteEpargne",IF(IF(ISNA(VLOOKUP(B33,DATA!$A$1:$A$16,1,0)),"",VLOOKUP(B33,DATA!$A$1:$A$16,1,0))="",O32+E33,O32-E33),O32)) -> 42.64 | P33: =IF(L33="", "", SUM(L33,M33,N33,O33)) -> 10059.21 | V33: MdN | W33: Marché de Noël
B34: ADMINISTRATION / Charges | C34: =C33+1 -> 30 | D34: 45932 | E34: 120 | F34: Le Csarda | G34: SG : Pizza | H34: MCA | I34: CompteCourant | J34: INTERNE | L34: =IF(B34="","",IF(I34="CompteCourant",IF(IF(ISNA(VLOOKUP(B34,DATA!$A$1:$A$16,1,0)),"",VLOOKUP(B34,DATA!$A$1:$A$16,1,0))="",L33+E34,L33-E34),L33)) -> 7437.7 | M34: =IF(B34="","",IF(I34="Coffre",IF(IF(ISNA(VLOOKUP(B34,DATA!$A$1:$A$16,1,0)),"",VLOOKUP(B34,DATA!$A$1:$A$16,1,0))="",M33+E34,M33-E34),M33)) -> 2416.23 | N34: =IF(B34="","",IF(I34="CompteEpargne",IF(IF(ISNA(VLOOKUP(B34,DATA!$A$1:$A$16,1,0)),"",VLOOKUP(B34,DATA!$A$1:$A$16,1,0))="",N33+E34,N33-E34),N33)) -> 42.64 | O34: =IF(B34="","",IF(J34="CompteEpargne",IF(IF(ISNA(VLOOKUP(B34,DATA!$A$1:$A$16,1,0)),"",VLOOKUP(B34,DATA!$A$1:$A$16,1,0))="",O33+E34,O33-E34),O33)) -> 42.64 | P34: =IF(L34="", "", SUM(L34,M34,N34,O34)) -> 9939.21 | V34: SeM | W34: Semaine de montage
B35: ADMINISTRATION / Produits | C35: =C34+1 -> 31 | D35: 45932 | E35: 156.9 | F35: BLV | G35: SG : Pizzas + boissons | H35: MCA | I35: CompteCourant | J35: INTERNE | L35: =IF(B35="","",IF(I35="CompteCourant",IF(IF(ISNA(VLOOKUP(B35,DATA!$A$1:$A$16,1,0)),"",VLOOKUP(B35,DATA!$A$1:$A$16,1,0))="",L34+E35,L34-E35),L34)) -> 7594.6 | M35: =IF(B35="","",IF(I35="Coffre",IF(IF(ISNA(VLOOKUP(B35,DATA!$A$1:$A$16,1,0)),"",VLOOKUP(B35,DATA!$A$1:$A$16,1,0))="",M34+E35,M34-E35),M34)) -> 2416.23 | N35: =IF(B35="","",IF(I35="CompteEpargne",IF(IF(ISNA(VLOOKUP(B35,DATA!$A$1:$A$16,1,0)),"",VLOOKUP(B35,DATA!$A$1:$A$16,1,0))="",N34+E35,N34-E35),N34)) -> 42.64 | O35: =IF(B35="","",IF(J35="CompteEpargne",IF(IF(ISNA(VLOOKUP(B35,DATA!$A$1:$A$16,1,0)),"",VLOOKUP(B35,DATA!$A$1:$A$16,1,0))="",O34+E35,O34-E35),O34)) -> 42.64 | P35: =IF(L35="", "", SUM(L35,M35,N35,O35)) -> 10096.11 | V35: JA | W35: Journée d'accueil
B36: ADMINISTRATION / Charges | C36: =C35+1 -> 32 | D36: 45957 | E36: 36.75 | F36: Maxime Magnenat | G36: Renouvellement Infomaniak | H36: MCA | I36: CompteCourant | J36: INTERNE | L36: =IF(B36="","",IF(I36="CompteCourant",IF(IF(ISNA(VLOOKUP(B36,DATA!$A$1:$A$16,1,0)),"",VLOOKUP(B36,DATA!$A$1:$A$16,1,0))="",L35+E36,L35-E36),L35)) -> 7557.85 | M36: =IF(B36="","",IF(I36="Coffre",IF(IF(ISNA(VLOOKUP(B36,DATA!$A$1:$A$16,1,0)),"",VLOOKUP(B36,DATA!$A$1:$A$16,1,0))="",M35+E36,M35-E36),M35)) -> 2416.23 | N36: =IF(B36="","",IF(I36="CompteEpargne",IF(IF(ISNA(VLOOKUP(B36,DATA!$A$1:$A$16,1,0)),"",VLOOKUP(B36,DATA!$A$1:$A$16,1,0))="",N35+E36,N35-E36),N35)) -> 42.64 | O36: =IF(B36="","",IF(J36="CompteEpargne",IF(IF(ISNA(VLOOKUP(B36,DATA!$A$1:$A$16,1,0)),"",VLOOKUP(B36,DATA!$A$1:$A$16,1,0))="",O35+E36,O35-E36),O35)) -> 42.64 | P36: =IF(L36="", "", SUM(L36,M36,N36,O36)) -> 10059.36
B37: EVENTS / Charges | C37: =C36+1 -> 33 | D37: 45938 | E37: 47.05 | F37: Thomas Brêchet | G37: DrawOnMe : croques monsieur | H37: MCA | I37: Coffre | J37: EVTCHILL | L37: =IF(B37="","",IF(I37="CompteCourant",IF(IF(ISNA(VLOOKUP(B37,DATA!$A$1:$A$16,1,0)),"",VLOOKUP(B37,DATA!$A$1:$A$16,1,0))="",L36+E37,L36-E37),L36)) -> 7557.85 | M37: =IF(B37="","",IF(I37="Coffre",IF(IF(ISNA(VLOOKUP(B37,DATA!$A$1:$A$16,1,0)),"",VLOOKUP(B37,DATA!$A$1:$A$16,1,0))="",M36+E37,M36-E37),M36)) -> 2369.18 | N37: =IF(B37="","",IF(I37="CompteEpargne",IF(IF(ISNA(VLOOKUP(B37,DATA!$A$1:$A$16,1,0)),"",VLOOKUP(B37,DATA!$A$1:$A$16,1,0))="",N36+E37,N36-E37),N36)) -> 42.64 | O37: =IF(B37="","",IF(J37="CompteEpargne",IF(IF(ISNA(VLOOKUP(B37,DATA!$A$1:$A$16,1,0)),"",VLOOKUP(B37,DATA!$A$1:$A$16,1,0))="",O36+E37,O36-E37),O36)) -> 42.64 | P37: =IF(L37="", "", SUM(L37,M37,N37,O37)) -> 10012.31
B38: EVENTS / Charges | C38: =C37+1 -> 34 | D38: 45933 | E38: 0 | F38: Maxime Magnenat | G38: Courses GM - 26.85 possiblement pas remboursé | H38: MCA | I38: CompteCourant | J38: GM | L38: =IF(B38="","",IF(I38="CompteCourant",IF(IF(ISNA(VLOOKUP(B38,DATA!$A$1:$A$16,1,0)),"",VLOOKUP(B38,DATA!$A$1:$A$16,1,0))="",L37+E38,L37-E38),L37)) -> 7557.85 | M38: =IF(B38="","",IF(I38="Coffre",IF(IF(ISNA(VLOOKUP(B38,DATA!$A$1:$A$16,1,0)),"",VLOOKUP(B38,DATA!$A$1:$A$16,1,0))="",M37+E38,M37-E38),M37)) -> 2369.18 | N38: =IF(B38="","",IF(I38="CompteEpargne",IF(IF(ISNA(VLOOKUP(B38,DATA!$A$1:$A$16,1,0)),"",VLOOKUP(B38,DATA!$A$1:$A$16,1,0))="",N37+E38,N37-E38),N37)) -> 42.64 | O38: =IF(B38="","",IF(J38="CompteEpargne",IF(IF(ISNA(VLOOKUP(B38,DATA!$A$1:$A$16,1,0)),"",VLOOKUP(B38,DATA!$A$1:$A$16,1,0))="",O37+E38,O37-E38),O37)) -> 42.64 | P38: =IF(L38="", "", SUM(L38,M38,N38,O38)) -> 10012.31
B39: ADMINISTRATION / Charges | C39: =C38+1 -> 35 | D39: 45933 | E39: 172.6 | F39: Landi | G39: A COMPLETER | H39: MCA | I39: CompteCourant | L39: =IF(B39="","",IF(I39="CompteCourant",IF(IF(ISNA(VLOOKUP(B39,DATA!$A$1:$A$16,1,0)),"",VLOOKUP(B39,DATA!$A$1:$A$16,1,0))="",L38+E39,L38-E39),L38)) -> 7385.25 | M39: =IF(B39="","",IF(I39="Coffre",IF(IF(ISNA(VLOOKUP(B39,DATA!$A$1:$A$16,1,0)),"",VLOOKUP(B39,DATA!$A$1:$A$16,1,0))="",M38+E39,M38-E39),M38)) -> 2369.18 | N39: =IF(B39="","",IF(I39="CompteEpargne",IF(IF(ISNA(VLOOKUP(B39,DATA!$A$1:$A$16,1,0)),"",VLOOKUP(B39,DATA!$A$1:$A$16,1,0))="",N38+E39,N38-E39),N38)) -> 42.64 | O39: =IF(B39="","",IF(J39="CompteEpargne",IF(IF(ISNA(VLOOKUP(B39,DATA!$A$1:$A$16,1,0)),"",VLOOKUP(B39,DATA!$A$1:$A$16,1,0))="",O38+E39,O38-E39),O38)) -> 42.64 | P39: =IF(L39="", "", SUM(L39,M39,N39,O39)) -> 9839.71
B40: EVENTS / Charges | C40: =C39+1 -> 36 | D40: 45935 | E40: 150 | F40: Laiterie du Chateau | G40: Fromage GM | H40: MCA | I40: CompteCourant | J40: GM | L40: =IF(B40="","",IF(I40="CompteCourant",IF(IF(ISNA(VLOOKUP(B40,DATA!$A$1:$A$16,1,0)),"",VLOOKUP(B40,DATA!$A$1:$A$16,1,0))="",L39+E40,L39-E40),L39)) -> 7235.25 | M40: =IF(B40="","",IF(I40="Coffre",IF(IF(ISNA(VLOOKUP(B40,DATA!$A$1:$A$16,1,0)),"",VLOOKUP(B40,DATA!$A$1:$A$16,1,0))="",M39+E40,M39-E40),M39)) -> 2369.18 | N40: =IF(B40="","",IF(I40="CompteEpargne",IF(IF(ISNA(VLOOKUP(B40,DATA!$A$1:$A$16,1,0)),"",VLOOKUP(B40,DATA!$A$1:$A$16,1,0))="",N39+E40,N39-E40),N39)) -> 42.64 | O40: =IF(B40="","",IF(J40="CompteEpargne",IF(IF(ISNA(VLOOKUP(B40,DATA!$A$1:$A$16,1,0)),"",VLOOKUP(B40,DATA!$A$1:$A$16,1,0))="",O39+E40,O39-E40),O39)) -> 42.64 | P40: =IF(L40="", "", SUM(L40,M40,N40,O40)) -> 9689.71
B41: EVENTS / Charges | C41: =C40+1 -> 37 | D41: 45935 | E41: 91.8 | F41: Boulangerie du Chateau | G41: Pain GM | H41: MCA | I41: CompteCourant | J41: GM | L41: =IF(B41="","",IF(I41="CompteCourant",IF(IF(ISNA(VLOOKUP(B41,DATA!$A$1:$A$16,1,0)),"",VLOOKUP(B41,DATA!$A$1:$A$16,1,0))="",L40+E41,L40-E41),L40)) -> 7143.45 | M41: =IF(B41="","",IF(I41="Coffre",IF(IF(ISNA(VLOOKUP(B41,DATA!$A$1:$A$16,1,0)),"",VLOOKUP(B41,DATA!$A$1:$A$16,1,0))="",M40+E41,M40-E41),M40)) -> 2369.18 | N41: =IF(B41="","",IF(I41="CompteEpargne",IF(IF(ISNA(VLOOKUP(B41,DATA!$A$1:$A$16,1,0)),"",VLOOKUP(B41,DATA!$A$1:$A$16,1,0))="",N40+E41,N40-E41),N40)) -> 42.64 | O41: =IF(B41="","",IF(J41="CompteEpargne",IF(IF(ISNA(VLOOKUP(B41,DATA!$A$1:$A$16,1,0)),"",VLOOKUP(B41,DATA!$A$1:$A$16,1,0))="",O40+E41,O40-E41),O40)) -> 42.64 | P41: =IF(L41="", "", SUM(L41,M41,N41,O41)) -> 9597.91
B42: EVENTS / Charges | C42: =C41+1 -> 38 | D42: 45943 | E42: 968.48 | F42: Chopfab Boxer | G42: Bières SG1 et JACC | H42: MCA | I42: CompteCourant | J42: SEGRILL1 | L42: =IF(B42="","",IF(I42="CompteCourant",IF(IF(ISNA(VLOOKUP(B42,DATA!$A$1:$A$16,1,0)),"",VLOOKUP(B42,DATA!$A$1:$A$16,1,0))="",L41+E42,L41-E42),L41)) -> 6174.97 | M42: =IF(B42="","",IF(I42="Coffre",IF(IF(ISNA(VLOOKUP(B42,DATA!$A$1:$A$16,1,0)),"",VLOOKUP(B42,DATA!$A$1:$A$16,1,0))="",M41+E42,M41-E42),M41)) -> 2369.18 | N42: =IF(B42="","",IF(I42="CompteEpargne",IF(IF(ISNA(VLOOKUP(B42,DATA!$A$1:$A$16,1,0)),"",VLOOKUP(B42,DATA!$A$1:$A$16,1,0))="",N41+E42,N41-E42),N41)) -> 42.64 | O42: =IF(B42="","",IF(J42="CompteEpargne",IF(IF(ISNA(VLOOKUP(B42,DATA!$A$1:$A$16,1,0)),"",VLOOKUP(B42,DATA!$A$1:$A$16,1,0))="",O41+E42,O41-E42),O41)) -> 42.64 | P42: =IF(L42="", "", SUM(L42,M42,N42,O42)) -> 8629.43
B43: ADMINISTRATION / Produits | C43: =C42+1 -> 39 | D43: 45943 | E43: 192 | F43: BLV | G43: Remboursement caution GM | H43: MCA | I43: CompteCourant | J43: GM | L43: =IF(B43="","",IF(I43="CompteCourant",IF(IF(ISNA(VLOOKUP(B43,DATA!$A$1:$A$16,1,0)),"",VLOOKUP(B43,DATA!$A$1:$A$16,1,0))="",L42+E43,L42-E43),L42)) -> 6366.97 | M43: =IF(B43="","",IF(I43="Coffre",IF(IF(ISNA(VLOOKUP(B43,DATA!$A$1:$A$16,1,0)),"",VLOOKUP(B43,DATA!$A$1:$A$16,1,0))="",M42+E43,M42-E43),M42)) -> 2369.18 | N43: =IF(B43="","",IF(I43="CompteEpargne",IF(IF(ISNA(VLOOKUP(B43,DATA!$A$1:$A$16,1,0)),"",VLOOKUP(B43,DATA!$A$1:$A$16,1,0))="",N42+E43,N42-E43),N42)) -> 42.64 | O43: =IF(B43="","",IF(J43="CompteEpargne",IF(IF(ISNA(VLOOKUP(B43,DATA!$A$1:$A$16,1,0)),"",VLOOKUP(B43,DATA!$A$1:$A$16,1,0))="",O42+E43,O42-E43),O42)) -> 42.64 | P43: =IF(L43="", "", SUM(L43,M43,N43,O43)) -> 8821.43
B44: EVENTS / Charges | C44: =C43+1 -> 40 | D44: 45945 | E44: 200 | F44: Maxime Magnenat | G44: Boissons local | H44: MCA | I44: CompteCourant | J44: AFTER | L44: =IF(B44="","",IF(I44="CompteCourant",IF(IF(ISNA(VLOOKUP(B44,DATA!$A$1:$A$16,1,0)),"",VLOOKUP(B44,DATA!$A$1:$A$16,1,0))="",L43+E44,L43-E44),L43)) -> 6166.97 | M44: =IF(B44="","",IF(I44="Coffre",IF(IF(ISNA(VLOOKUP(B44,DATA!$A$1:$A$16,1,0)),"",VLOOKUP(B44,DATA!$A$1:$A$16,1,0))="",M43+E44,M43-E44),M43)) -> 2369.18 | N44: =IF(B44="","",IF(I44="CompteEpargne",IF(IF(ISNA(VLOOKUP(B44,DATA!$A$1:$A$16,1,0)),"",VLOOKUP(B44,DATA!$A$1:$A$16,1,0))="",N43+E44,N43-E44),N43)) -> 42.64 | O44: =IF(B44="","",IF(J44="CompteEpargne",IF(IF(ISNA(VLOOKUP(B44,DATA!$A$1:$A$16,1,0)),"",VLOOKUP(B44,DATA!$A$1:$A$16,1,0))="",O43+E44,O43-E44),O43)) -> 42.64 | P44: =IF(L44="", "", SUM(L44,M44,N44,O44)) -> 8621.43
B45: ADMINISTRATION / Produits | C45: =C44+1 -> 41 | D45: 45951 | E45: 67 | F45: BLV | G45: Provenance : Etu'sounds | H45: MCA | I45: CompteCourant | L45: =IF(B45="","",IF(I45="CompteCourant",IF(IF(ISNA(VLOOKUP(B45,DATA!$A$1:$A$16,1,0)),"",VLOOKUP(B45,DATA!$A$1:$A$16,1,0))="",L44+E45,L44-E45),L44)) -> 6233.97 | M45: =IF(B45="","",IF(I45="Coffre",IF(IF(ISNA(VLOOKUP(B45,DATA!$A$1:$A$16,1,0)),"",VLOOKUP(B45,DATA!$A$1:$A$16,1,0))="",M44+E45,M44-E45),M44)) -> 2369.18 | N45: =IF(B45="","",IF(I45="CompteEpargne",IF(IF(ISNA(VLOOKUP(B45,DATA!$A$1:$A$16,1,0)),"",VLOOKUP(B45,DATA!$A$1:$A$16,1,0))="",N44+E45,N44-E45),N44)) -> 42.64 | O45: =IF(B45="","",IF(J45="CompteEpargne",IF(IF(ISNA(VLOOKUP(B45,DATA!$A$1:$A$16,1,0)),"",VLOOKUP(B45,DATA!$A$1:$A$16,1,0))="",O44+E45,O44-E45),O44)) -> 42.64 | P45: =IF(L45="", "", SUM(L45,M45,N45,O45)) -> 8688.43
B46: ADMINISTRATION / Charges | C46: =C45+1 -> 42 | D46: 45952 | E46: 2977.65 | F46: Patrick Magnenat | G46: Achat nouvelle cuisine | H46: MCA | I46: CompteCourant | J46: INTERNE | L46: =IF(B46="","",IF(I46="CompteCourant",IF(IF(ISNA(VLOOKUP(B46,DATA!$A$1:$A$16,1,0)),"",VLOOKUP(B46,DATA!$A$1:$A$16,1,0))="",L45+E46,L45-E46),L45)) -> 3256.32 | M46: =IF(B46="","",IF(I46="Coffre",IF(IF(ISNA(VLOOKUP(B46,DATA!$A$1:$A$16,1,0)),"",VLOOKUP(B46,DATA!$A$1:$A$16,1,0))="",M45+E46,M45-E46),M45)) -> 2369.18 | N46: =IF(B46="","",IF(I46="CompteEpargne",IF(IF(ISNA(VLOOKUP(B46,DATA!$A$1:$A$16,1,0)),"",VLOOKUP(B46,DATA!$A$1:$A$16,1,0))="",N45+E46,N45-E46),N45)) -> 42.64 | O46: =IF(B46="","",IF(J46="CompteEpargne",IF(IF(ISNA(VLOOKUP(B46,DATA!$A$1:$A$16,1,0)),"",VLOOKUP(B46,DATA!$A$1:$A$16,1,0))="",O45+E46,O45-E46),O45)) -> 42.64 | P46: =IF(L46="", "", SUM(L46,M46,N46,O46)) -> 5710.78
B47: EVENTS / Produits | C47: =C46+1 -> 43 | D47: 45936 | E47: 171.73 | F47: BLV | G47: Revenus GM | H47: MCA | I47: CompteCourant | J47: GM | L47: =IF(B47="","",IF(I47="CompteCourant",IF(IF(ISNA(VLOOKUP(B47,DATA!$A$1:$A$16,1,0)),"",VLOOKUP(B47,DATA!$A$1:$A$16,1,0))="",L46+E47,L46-E47),L46)) -> 3428.05 | M47: =IF(B47="","",IF(I47="Coffre",IF(IF(ISNA(VLOOKUP(B47,DATA!$A$1:$A$16,1,0)),"",VLOOKUP(B47,DATA!$A$1:$A$16,1,0))="",M46+E47,M46-E47),M46)) -> 2369.18 | N47: =IF(B47="","",IF(I47="CompteEpargne",IF(IF(ISNA(VLOOKUP(B47,DATA!$A$1:$A$16,1,0)),"",VLOOKUP(B47,DATA!$A$1:$A$16,1,0))="",N46+E47,N46-E47),N46)) -> 42.64 | O47: =IF(B47="","",IF(J47="CompteEpargne",IF(IF(ISNA(VLOOKUP(B47,DATA!$A$1:$A$16,1,0)),"",VLOOKUP(B47,DATA!$A$1:$A$16,1,0))="",O46+E47,O46-E47),O46)) -> 42.64 | P47: =IF(L47="", "", SUM(L47,M47,N47,O47)) -> 5882.51
B48: EVENTS / Produits | C48: =C47+1 -> 44 | D48: 45937 | E48: 467.8 | F48: BLV | G48: Revenus GM | H48: MCA | I48: CompteCourant | J48: GM | L48: =IF(B48="","",IF(I48="CompteCourant",IF(IF(ISNA(VLOOKUP(B48,DATA!$A$1:$A$16,1,0)),"",VLOOKUP(B48,DATA!$A$1:$A$16,1,0))="",L47+E48,L47-E48),L47)) -> 3895.85 | M48: =IF(B48="","",IF(I48="Coffre",IF(IF(ISNA(VLOOKUP(B48,DATA!$A$1:$A$16,1,0)),"",VLOOKUP(B48,DATA!$A$1:$A$16,1,0))="",M47+E48,M47-E48),M47)) -> 2369.18 | N48: =IF(B48="","",IF(I48="CompteEpargne",IF(IF(ISNA(VLOOKUP(B48,DATA!$A$1:$A$16,1,0)),"",VLOOKUP(B48,DATA!$A$1:$A$16,1,0))="",N47+E48,N47-E48),N47)) -> 42.64 | O48: =IF(B48="","",IF(J48="CompteEpargne",IF(IF(ISNA(VLOOKUP(B48,DATA!$A$1:$A$16,1,0)),"",VLOOKUP(B48,DATA!$A$1:$A$16,1,0))="",O47+E48,O47-E48),O47)) -> 42.64 | P48: =IF(L48="", "", SUM(L48,M48,N48,O48)) -> 6350.31
B49: EVENTS / Produits | C49: =C48+1 -> 45 | D49: 45937 | E49: 25.66 | F49: BLV | G49: Revenus GM | H49: MCA | I49: CompteCourant | J49: GM | L49: =IF(B49="","",IF(I49="CompteCourant",IF(IF(ISNA(VLOOKUP(B49,DATA!$A$1:$A$16,1,0)),"",VLOOKUP(B49,DATA!$A$1:$A$16,1,0))="",L48+E49,L48-E49),L48)) -> 3921.51 | M49: =IF(B49="","",IF(I49="Coffre",IF(IF(ISNA(VLOOKUP(B49,DATA!$A$1:$A$16,1,0)),"",VLOOKUP(B49,DATA!$A$1:$A$16,1,0))="",M48+E49,M48-E49),M48)) -> 2369.18 | N49: =IF(B49="","",IF(I49="CompteEpargne",IF(IF(ISNA(VLOOKUP(B49,DATA!$A$1:$A$16,1,0)),"",VLOOKUP(B49,DATA!$A$1:$A$16,1,0))="",N48+E49,N48-E49),N48)) -> 42.64 | O49: =IF(B49="","",IF(J49="CompteEpargne",IF(IF(ISNA(VLOOKUP(B49,DATA!$A$1:$A$16,1,0)),"",VLOOKUP(B49,DATA!$A$1:$A$16,1,0))="",O48+E49,O48-E49),O48)) -> 42.64 | P49: =IF(L49="", "", SUM(L49,M49,N49,O49)) -> 6375.97
B50: EVENTS / Produits | C50: =C49+1 -> 46 | D50: 45940 | E50: 0.99 | F50: BLV | G50: Revenus GM | H50: MCA | I50: CompteCourant | J50: GM | L50: =IF(B50="","",IF(I50="CompteCourant",IF(IF(ISNA(VLOOKUP(B50,DATA!$A$1:$A$16,1,0)),"",VLOOKUP(B50,DATA!$A$1:$A$16,1,0))="",L49+E50,L49-E50),L49)) -> 3922.5 | M50: =IF(B50="","",IF(I50="Coffre",IF(IF(ISNA(VLOOKUP(B50,DATA!$A$1:$A$16,1,0)),"",VLOOKUP(B50,DATA!$A$1:$A$16,1,0))="",M49+E50,M49-E50),M49)) -> 2369.18 | N50: =IF(B50="","",IF(I50="CompteEpargne",IF(IF(ISNA(VLOOKUP(B50,DATA!$A$1:$A$16,1,0)),"",VLOOKUP(B50,DATA!$A$1:$A$16,1,0))="",N49+E50,N49-E50),N49)) -> 42.64 | O50: =IF(B50="","",IF(J50="CompteEpargne",IF(IF(ISNA(VLOOKUP(B50,DATA!$A$1:$A$16,1,0)),"",VLOOKUP(B50,DATA!$A$1:$A$16,1,0))="",O49+E50,O49-E50),O49)) -> 42.64 | P50: =IF(L50="", "", SUM(L50,M50,N50,O50)) -> 6376.96
B51: EVENTS / Produits | C51: =C50+1 -> 47 | D51: 45943 | E51: 379.92 | F51: BLV | G51: Revenus DrawOnMe + After | H51: MCA | I51: CompteCourant | J51: EVTCHILL | L51: =IF(B51="","",IF(I51="CompteCourant",IF(IF(ISNA(VLOOKUP(B51,DATA!$A$1:$A$16,1,0)),"",VLOOKUP(B51,DATA!$A$1:$A$16,1,0))="",L50+E51,L50-E51),L50)) -> 4302.42 | M51: =IF(B51="","",IF(I51="Coffre",IF(IF(ISNA(VLOOKUP(B51,DATA!$A$1:$A$16,1,0)),"",VLOOKUP(B51,DATA!$A$1:$A$16,1,0))="",M50+E51,M50-E51),M50)) -> 2369.18 | N51: =IF(B51="","",IF(I51="CompteEpargne",IF(IF(ISNA(VLOOKUP(B51,DATA!$A$1:$A$16,1,0)),"",VLOOKUP(B51,DATA!$A$1:$A$16,1,0))="",N50+E51,N50-E51),N50)) -> 42.64 | O51: =IF(B51="","",IF(J51="CompteEpargne",IF(IF(ISNA(VLOOKUP(B51,DATA!$A$1:$A$16,1,0)),"",VLOOKUP(B51,DATA!$A$1:$A$16,1,0))="",O50+E51,O50-E51),O50)) -> 42.64 | P51: =IF(L51="", "", SUM(L51,M51,N51,O51)) -> 6756.88
B52: EVENTS / Produits | C52: =C51+1 -> 48 | D52: 45950 | E52: 95.7 | F52: BLV | G52: Revenus Soirée fantaisie | H52: MCA | I52: CompteCourant | J52: EVTCHILL | L52: =IF(B52="","",IF(I52="CompteCourant",IF(IF(ISNA(VLOOKUP(B52,DATA!$A$1:$A$16,1,0)),"",VLOOKUP(B52,DATA!$A$1:$A$16,1,0))="",L51+E52,L51-E52),L51)) -> 4398.12 | M52: =IF(B52="","",IF(I52="Coffre",IF(IF(ISNA(VLOOKUP(B52,DATA!$A$1:$A$16,1,0)),"",VLOOKUP(B52,DATA!$A$1:$A$16,1,0))="",M51+E52,M51-E52),M51)) -> 2369.18 | N52: =IF(B52="","",IF(I52="CompteEpargne",IF(IF(ISNA(VLOOKUP(B52,DATA!$A$1:$A$16,1,0)),"",VLOOKUP(B52,DATA!$A$1:$A$16,1,0))="",N51+E52,N51-E52),N51)) -> 42.64 | O52: =IF(B52="","",IF(J52="CompteEpargne",IF(IF(ISNA(VLOOKUP(B52,DATA!$A$1:$A$16,1,0)),"",VLOOKUP(B52,DATA!$A$1:$A$16,1,0))="",O51+E52,O51-E52),O51)) -> 42.64 | P52: =IF(L52="", "", SUM(L52,M52,N52,O52)) -> 6852.58
B53: EVENTS / Produits | C53: =C52+1 -> 49 | D53: 45939 | E53: 166.6 | F53: BLV | G53: Revenus GM Cash | H53: MCA | I53: Coffre | J53: GM | L53: =IF(B53="","",IF(I53="CompteCourant",IF(IF(ISNA(VLOOKUP(B53,DATA!$A$1:$A$16,1,0)),"",VLOOKUP(B53,DATA!$A$1:$A$16,1,0))="",L52+E53,L52-E53),L52)) -> 4398.12 | M53: =IF(B53="","",IF(I53="Coffre",IF(IF(ISNA(VLOOKUP(B53,DATA!$A$1:$A$16,1,0)),"",VLOOKUP(B53,DATA!$A$1:$A$16,1,0))="",M52+E53,M52-E53),M52)) -> 2535.78 | N53: =IF(B53="","",IF(I53="CompteEpargne",IF(IF(ISNA(VLOOKUP(B53,DATA!$A$1:$A$16,1,0)),"",VLOOKUP(B53,DATA!$A$1:$A$16,1,0))="",N52+E53,N52-E53),N52)) -> 42.64 | O53: =IF(B53="","",IF(J53="CompteEpargne",IF(IF(ISNA(VLOOKUP(B53,DATA!$A$1:$A$16,1,0)),"",VLOOKUP(B53,DATA!$A$1:$A$16,1,0))="",O52+E53,O52-E53),O52)) -> 42.64 | P53: =IF(L53="", "", SUM(L53,M53,N53,O53)) -> 7019.18
B54: EVENTS / Produits | C54: =C53+1 -> 50 | D54: 45939 | E54: 120 | F54: BLV | G54: Revenu after 9.10 | H54: MCA | I54: Coffre | J54: AFTER | L54: =IF(B54="","",IF(I54="CompteCourant",IF(IF(ISNA(VLOOKUP(B54,DATA!$A$1:$A$16,1,0)),"",VLOOKUP(B54,DATA!$A$1:$A$16,1,0))="",L53+E54,L53-E54),L53)) -> 4398.12 | M54: =IF(B54="","",IF(I54="Coffre",IF(IF(ISNA(VLOOKUP(B54,DATA!$A$1:$A$16,1,0)),"",VLOOKUP(B54,DATA!$A$1:$A$16,1,0))="",M53+E54,M53-E54),M53)) -> 2655.78 | N54: =IF(B54="","",IF(I54="CompteEpargne",IF(IF(ISNA(VLOOKUP(B54,DATA!$A$1:$A$16,1,0)),"",VLOOKUP(B54,DATA!$A$1:$A$16,1,0))="",N53+E54,N53-E54),N53)) -> 42.64 | O54: =IF(B54="","",IF(J54="CompteEpargne",IF(IF(ISNA(VLOOKUP(B54,DATA!$A$1:$A$16,1,0)),"",VLOOKUP(B54,DATA!$A$1:$A$16,1,0))="",O53+E54,O53-E54),O53)) -> 42.64 | P54: =IF(L54="", "", SUM(L54,M54,N54,O54)) -> 7139.18
B55: EVENTS / Produits | C55: =C54+1 -> 51 | D55: 45939 | E55: 112.15 | F55: BLV | G55: Cash Courses event chillout | H55: MCA | I55: Coffre | J55: EVTCHILL | L55: =IF(B55="","",IF(I55="CompteCourant",IF(IF(ISNA(VLOOKUP(B55,DATA!$A$1:$A$16,1,0)),"",VLOOKUP(B55,DATA!$A$1:$A$16,1,0))="",L54+E55,L54-E55),L54)) -> 4398.12 | M55: =IF(B55="","",IF(I55="Coffre",IF(IF(ISNA(VLOOKUP(B55,DATA!$A$1:$A$16,1,0)),"",VLOOKUP(B55,DATA!$A$1:$A$16,1,0))="",M54+E55,M54-E55),M54)) -> 2767.93 | N55: =IF(B55="","",IF(I55="CompteEpargne",IF(IF(ISNA(VLOOKUP(B55,DATA!$A$1:$A$16,1,0)),"",VLOOKUP(B55,DATA!$A$1:$A$16,1,0))="",N54+E55,N54-E55),N54)) -> 42.64 | O55: =IF(B55="","",IF(J55="CompteEpargne",IF(IF(ISNA(VLOOKUP(B55,DATA!$A$1:$A$16,1,0)),"",VLOOKUP(B55,DATA!$A$1:$A$16,1,0))="",O54+E55,O54-E55),O54)) -> 42.64 | P55: =IF(L55="", "", SUM(L55,M55,N55,O55)) -> 7251.33
B56: ADMINISTRATION / Charges | C56: =C55+1 -> 52 | D56: 45925 | E56: 591.4 | F56: BLV | G56: Correction après comptage caisse | H56: MCA | I56: Coffre | J56: INTERNE | L56: =IF(B56="","",IF(I56="CompteCourant",IF(IF(ISNA(VLOOKUP(B56,DATA!$A$1:$A$16,1,0)),"",VLOOKUP(B56,DATA!$A$1:$A$16,1,0))="",L55+E56,L55-E56),L55)) -> 4398.12 | M56: =IF(B56="","",IF(I56="Coffre",IF(IF(ISNA(VLOOKUP(B56,DATA!$A$1:$A$16,1,0)),"",VLOOKUP(B56,DATA!$A$1:$A$16,1,0))="",M55+E56,M55-E56),M55)) -> 2176.53 | N56: =IF(B56="","",IF(I56="CompteEpargne",IF(IF(ISNA(VLOOKUP(B56,DATA!$A$1:$A$16,1,0)),"",VLOOKUP(B56,DATA!$A$1:$A$16,1,0))="",N55+E56,N55-E56),N55)) -> 42.64 | O56: =IF(B56="","",IF(J56="CompteEpargne",IF(IF(ISNA(VLOOKUP(B56,DATA!$A$1:$A$16,1,0)),"",VLOOKUP(B56,DATA!$A$1:$A$16,1,0))="",O55+E56,O55-E56),O55)) -> 42.64 | P56: =IF(L56="", "", SUM(L56,M56,N56,O56)) -> 6659.93
B57: EVENTS / Produits | C57: =C56+1 -> 53 | D57: 45986 | E57: 65.67 | F57: BLV | G57: Entrées afters | H57: MCA | I57: Coffre | J57: AFTER | L57: =IF(B57="","",IF(I57="CompteCourant",IF(IF(ISNA(VLOOKUP(B57,DATA!$A$1:$A$16,1,0)),"",VLOOKUP(B57,DATA!$A$1:$A$16,1,0))="",L56+E57,L56-E57),L56)) -> 4398.12 | M57: =IF(B57="","",IF(I57="Coffre",IF(IF(ISNA(VLOOKUP(B57,DATA!$A$1:$A$16,1,0)),"",VLOOKUP(B57,DATA!$A$1:$A$16,1,0))="",M56+E57,M56-E57),M56)) -> 2242.2 | N57: =IF(B57="","",IF(I57="CompteEpargne",IF(IF(ISNA(VLOOKUP(B57,DATA!$A$1:$A$16,1,0)),"",VLOOKUP(B57,DATA!$A$1:$A$16,1,0))="",N56+E57,N56-E57),N56)) -> 42.64 | O57: =IF(B57="","",IF(J57="CompteEpargne",IF(IF(ISNA(VLOOKUP(B57,DATA!$A$1:$A$16,1,0)),"",VLOOKUP(B57,DATA!$A$1:$A$16,1,0))="",O56+E57,O56-E57),O56)) -> 42.64 | P57: =IF(L57="", "", SUM(L57,M57,N57,O57)) -> 6725.6
B58: ADMINISTRATION / Charges | C58: =C57+1 -> 54 | D58: 45957 | E58: 26.85 | F58: Maxime Magnenat | G58: note de frais | H58: MCA | I58: CompteCourant | L58: =IF(B58="","",IF(I58="CompteCourant",IF(IF(ISNA(VLOOKUP(B58,DATA!$A$1:$A$16,1,0)),"",VLOOKUP(B58,DATA!$A$1:$A$16,1,0))="",L57+E58,L57-E58),L57)) -> 4371.27 | M58: =IF(B58="","",IF(I58="Coffre",IF(IF(ISNA(VLOOKUP(B58,DATA!$A$1:$A$16,1,0)),"",VLOOKUP(B58,DATA!$A$1:$A$16,1,0))="",M57+E58,M57-E58),M57)) -> 2242.2 | N58: =IF(B58="","",IF(I58="CompteEpargne",IF(IF(ISNA(VLOOKUP(B58,DATA!$A$1:$A$16,1,0)),"",VLOOKUP(B58,DATA!$A$1:$A$16,1,0))="",N57+E58,N57-E58),N57)) -> 42.64 | O58: =IF(B58="","",IF(J58="CompteEpargne",IF(IF(ISNA(VLOOKUP(B58,DATA!$A$1:$A$16,1,0)),"",VLOOKUP(B58,DATA!$A$1:$A$16,1,0))="",O57+E58,O57-E58),O57)) -> 42.64 | P58: =IF(L58="", "", SUM(L58,M58,N58,O58)) -> 6698.75
B59: ADMINISTRATION / Charges | C59: =C58+1 -> 55 | D59: 45957 | E59: 210 | F59: Manuel Cabras | G59: note de frais | H59: MCA | I59: CompteCourant | L59: =IF(B59="","",IF(I59="CompteCourant",IF(IF(ISNA(VLOOKUP(B59,DATA!$A$1:$A$16,1,0)),"",VLOOKUP(B59,DATA!$A$1:$A$16,1,0))="",L58+E59,L58-E59),L58)) -> 4161.27 | M59: =IF(B59="","",IF(I59="Coffre",IF(IF(ISNA(VLOOKUP(B59,DATA!$A$1:$A$16,1,0)),"",VLOOKUP(B59,DATA!$A$1:$A$16,1,0))="",M58+E59,M58-E59),M58)) -> 2242.2 | N59: =IF(B59="","",IF(I59="CompteEpargne",IF(IF(ISNA(VLOOKUP(B59,DATA!$A$1:$A$16,1,0)),"",VLOOKUP(B59,DATA!$A$1:$A$16,1,0))="",N58+E59,N58-E59),N58)) -> 42.64 | O59: =IF(B59="","",IF(J59="CompteEpargne",IF(IF(ISNA(VLOOKUP(B59,DATA!$A$1:$A$16,1,0)),"",VLOOKUP(B59,DATA!$A$1:$A$16,1,0))="",O58+E59,O58-E59),O58)) -> 42.64 | P59: =IF(L59="", "", SUM(L59,M59,N59,O59)) -> 6488.75
B60: EVENTS / Produits | C60: =C59+1 -> 56 | D60: 45960 | E60: 154.93 | F60: BLV | G60: Revenus Soirée Halloween twint soupe courge | H60: MCA | I60: CompteCourant | J60: EVTCHILL | L60: =IF(B60="","",IF(I60="CompteCourant",IF(IF(ISNA(VLOOKUP(B60,DATA!$A$1:$A$16,1,0)),"",VLOOKUP(B60,DATA!$A$1:$A$16,1,0))="",L59+E60,L59-E60),L59)) -> 4316.2 | M60: =IF(B60="","",IF(I60="Coffre",IF(IF(ISNA(VLOOKUP(B60,DATA!$A$1:$A$16,1,0)),"",VLOOKUP(B60,DATA!$A$1:$A$16,1,0))="",M59+E60,M59-E60),M59)) -> 2242.2 | N60: =IF(B60="","",IF(I60="CompteEpargne",IF(IF(ISNA(VLOOKUP(B60,DATA!$A$1:$A$16,1,0)),"",VLOOKUP(B60,DATA!$A$1:$A$16,1,0))="",N59+E60,N59-E60),N59)) -> 42.64 | O60: =IF(B60="","",IF(J60="CompteEpargne",IF(IF(ISNA(VLOOKUP(B60,DATA!$A$1:$A$16,1,0)),"",VLOOKUP(B60,DATA!$A$1:$A$16,1,0))="",O59+E60,O59-E60),O59)) -> 42.64 | P60: =IF(L60="", "", SUM(L60,M60,N60,O60)) -> 6643.68
B61: ADMINISTRATION / Charges | C61: =C60+1 -> 57 | D61: 45961 | E61: 107.6 | F61: Manuel Cabras | G61: note de frais | H61: MCA | I61: CompteCourant | L61: =IF(B61="","",IF(I61="CompteCourant",IF(IF(ISNA(VLOOKUP(B61,DATA!$A$1:$A$16,1,0)),"",VLOOKUP(B61,DATA!$A$1:$A$16,1,0))="",L60+E61,L60-E61),L60)) -> 4208.6 | M61: =IF(B61="","",IF(I61="Coffre",IF(IF(ISNA(VLOOKUP(B61,DATA!$A$1:$A$16,1,0)),"",VLOOKUP(B61,DATA!$A$1:$A$16,1,0))="",M60+E61,M60-E61),M60)) -> 2242.2 | N61: =IF(B61="","",IF(I61="CompteEpargne",IF(IF(ISNA(VLOOKUP(B61,DATA!$A$1:$A$16,1,0)),"",VLOOKUP(B61,DATA!$A$1:$A$16,1,0))="",N60+E61,N60-E61),N60)) -> 42.64 | O61: =IF(B61="","",IF(J61="CompteEpargne",IF(IF(ISNA(VLOOKUP(B61,DATA!$A$1:$A$16,1,0)),"",VLOOKUP(B61,DATA!$A$1:$A$16,1,0))="",O60+E61,O60-E61),O60)) -> 42.64 | P61: =IF(L61="", "", SUM(L61,M61,N61,O61)) -> 6536.08
B62: EVENTS / Produits | C62: =C61+1 -> 58 | D62: 45961 | E62: 10 | F62: BLV | G62: manu achat soupe courge | H62: MCA | I62: CompteCourant | J62: EVTCHILL | L62: =IF(B62="","",IF(I62="CompteCourant",IF(IF(ISNA(VLOOKUP(B62,DATA!$A$1:$A$16,1,0)),"",VLOOKUP(B62,DATA!$A$1:$A$16,1,0))="",L61+E62,L61-E62),L61)) -> 4218.6 | M62: =IF(B62="","",IF(I62="Coffre",IF(IF(ISNA(VLOOKUP(B62,DATA!$A$1:$A$16,1,0)),"",VLOOKUP(B62,DATA!$A$1:$A$16,1,0))="",M61+E62,M61-E62),M61)) -> 2242.2 | N62: =IF(B62="","",IF(I62="CompteEpargne",IF(IF(ISNA(VLOOKUP(B62,DATA!$A$1:$A$16,1,0)),"",VLOOKUP(B62,DATA!$A$1:$A$16,1,0))="",N61+E62,N61-E62),N61)) -> 42.64 | O62: =IF(B62="","",IF(J62="CompteEpargne",IF(IF(ISNA(VLOOKUP(B62,DATA!$A$1:$A$16,1,0)),"",VLOOKUP(B62,DATA!$A$1:$A$16,1,0))="",O61+E62,O61-E62),O61)) -> 42.64 | P62: =IF(L62="", "", SUM(L62,M62,N62,O62)) -> 6546.08
B63: EVENTS / Produits | C63: =C62+1 -> 59 | D63: 45961 | E63: 17.76 | F63: BLV | G63: entrées halloween twint | H63: MCA | I63: CompteCourant | J63: AFTER | L63: =IF(B63="","",IF(I63="CompteCourant",IF(IF(ISNA(VLOOKUP(B63,DATA!$A$1:$A$16,1,0)),"",VLOOKUP(B63,DATA!$A$1:$A$16,1,0))="",L62+E63,L62-E63),L62)) -> 4236.36 | M63: =IF(B63="","",IF(I63="Coffre",IF(IF(ISNA(VLOOKUP(B63,DATA!$A$1:$A$16,1,0)),"",VLOOKUP(B63,DATA!$A$1:$A$16,1,0))="",M62+E63,M62-E63),M62)) -> 2242.2 | N63: =IF(B63="","",IF(I63="CompteEpargne",IF(IF(ISNA(VLOOKUP(B63,DATA!$A$1:$A$16,1,0)),"",VLOOKUP(B63,DATA!$A$1:$A$16,1,0))="",N62+E63,N62-E63),N62)) -> 42.64 | O63: =IF(B63="","",IF(J63="CompteEpargne",IF(IF(ISNA(VLOOKUP(B63,DATA!$A$1:$A$16,1,0)),"",VLOOKUP(B63,DATA!$A$1:$A$16,1,0))="",O62+E63,O62-E63),O62)) -> 42.64 | P63: =IF(L63="", "", SUM(L63,M63,N63,O63)) -> 6563.84
B64: EVENTS / Produits | C64: =C63+1 -> 60 | D64: 45964 | E64: 218.1 | F64: BLV | G64: entrées halloween twint | H64: MCA | I64: CompteCourant | J64: AFTER | L64: =IF(B64="","",IF(I64="CompteCourant",IF(IF(ISNA(VLOOKUP(B64,DATA!$A$1:$A$16,1,0)),"",VLOOKUP(B64,DATA!$A$1:$A$16,1,0))="",L63+E64,L63-E64),L63)) -> 4454.46 | M64: =IF(B64="","",IF(I64="Coffre",IF(IF(ISNA(VLOOKUP(B64,DATA!$A$1:$A$16,1,0)),"",VLOOKUP(B64,DATA!$A$1:$A$16,1,0))="",M63+E64,M63-E64),M63)) -> 2242.2 | N64: =IF(B64="","",IF(I64="CompteEpargne",IF(IF(ISNA(VLOOKUP(B64,DATA!$A$1:$A$16,1,0)),"",VLOOKUP(B64,DATA!$A$1:$A$16,1,0))="",N63+E64,N63-E64),N63)) -> 42.64 | O64: =IF(B64="","",IF(J64="CompteEpargne",IF(IF(ISNA(VLOOKUP(B64,DATA!$A$1:$A$16,1,0)),"",VLOOKUP(B64,DATA!$A$1:$A$16,1,0))="",O63+E64,O63-E64),O63)) -> 42.64 | P64: =IF(L64="", "", SUM(L64,M64,N64,O64)) -> 6781.94
B65: SANS EFFET / Charges | C65: =C64+1 -> 61 | D65: 45965 | E65: 562 | F65: Digitec Galaxus | G65: Achat frigo | H65: MCA | I65: CompteCourant | L65: =IF(B65="","",IF(I65="CompteCourant",IF(IF(ISNA(VLOOKUP(B65,DATA!$A$1:$A$16,1,0)),"",VLOOKUP(B65,DATA!$A$1:$A$16,1,0))="",L64+E65,L64-E65),L64)) -> 3892.46 | M65: =IF(B65="","",IF(I65="Coffre",IF(IF(ISNA(VLOOKUP(B65,DATA!$A$1:$A$16,1,0)),"",VLOOKUP(B65,DATA!$A$1:$A$16,1,0))="",M64+E65,M64-E65),M64)) -> 2242.2 | N65: =IF(B65="","",IF(I65="CompteEpargne",IF(IF(ISNA(VLOOKUP(B65,DATA!$A$1:$A$16,1,0)),"",VLOOKUP(B65,DATA!$A$1:$A$16,1,0))="",N64+E65,N64-E65),N64)) -> 42.64 | O65: =IF(B65="","",IF(J65="CompteEpargne",IF(IF(ISNA(VLOOKUP(B65,DATA!$A$1:$A$16,1,0)),"",VLOOKUP(B65,DATA!$A$1:$A$16,1,0))="",O64+E65,O64-E65),O64)) -> 42.64 | P65: =IF(L65="", "", SUM(L65,M65,N65,O65)) -> 6219.94
B66: ADMINISTRATION / Produits | C66: =C65+1 -> 62 | D66: 45965 | E66: 8 | F66: BLV | G66: Depôt GM cheseaux pt 2 | H66: MCA | I66: CompteCourant | L66: =IF(B66="","",IF(I66="CompteCourant",IF(IF(ISNA(VLOOKUP(B66,DATA!$A$1:$A$16,1,0)),"",VLOOKUP(B66,DATA!$A$1:$A$16,1,0))="",L65+E66,L65-E66),L65)) -> 3900.46 | M66: =IF(B66="","",IF(I66="Coffre",IF(IF(ISNA(VLOOKUP(B66,DATA!$A$1:$A$16,1,0)),"",VLOOKUP(B66,DATA!$A$1:$A$16,1,0))="",M65+E66,M65-E66),M65)) -> 2242.2 | N66: =IF(B66="","",IF(I66="CompteEpargne",IF(IF(ISNA(VLOOKUP(B66,DATA!$A$1:$A$16,1,0)),"",VLOOKUP(B66,DATA!$A$1:$A$16,1,0))="",N65+E66,N65-E66),N65)) -> 42.64 | O66: =IF(B66="","",IF(J66="CompteEpargne",IF(IF(ISNA(VLOOKUP(B66,DATA!$A$1:$A$16,1,0)),"",VLOOKUP(B66,DATA!$A$1:$A$16,1,0))="",O65+E66,O65-E66),O65)) -> 42.64 | P66: =IF(L66="", "", SUM(L66,M66,N66,O66)) -> 6227.94
B67: EVENTS / Produits | C67: =C66+1 -> 63 | D67: 45965 | E67: 165.78 | F67: BLV | G67: Entrée after | H67: MCA | I67: CompteCourant | L67: =IF(B67="","",IF(I67="CompteCourant",IF(IF(ISNA(VLOOKUP(B67,DATA!$A$1:$A$16,1,0)),"",VLOOKUP(B67,DATA!$A$1:$A$16,1,0))="",L66+E67,L66-E67),L66)) -> 4066.24 | M67: =IF(B67="","",IF(I67="Coffre",IF(IF(ISNA(VLOOKUP(B67,DATA!$A$1:$A$16,1,0)),"",VLOOKUP(B67,DATA!$A$1:$A$16,1,0))="",M66+E67,M66-E67),M66)) -> 2242.2 | N67: =IF(B67="","",IF(I67="CompteEpargne",IF(IF(ISNA(VLOOKUP(B67,DATA!$A$1:$A$16,1,0)),"",VLOOKUP(B67,DATA!$A$1:$A$16,1,0))="",N66+E67,N66-E67),N66)) -> 42.64 | O67: =IF(B67="","",IF(J67="CompteEpargne",IF(IF(ISNA(VLOOKUP(B67,DATA!$A$1:$A$16,1,0)),"",VLOOKUP(B67,DATA!$A$1:$A$16,1,0))="",O66+E67,O66-E67),O66)) -> 42.64 | P67: =IF(L67="", "", SUM(L67,M67,N67,O67)) -> 6393.72
B68: ADMINISTRATION / Charges | C68: =C67+1 -> 64 | D68: 45972 | E68: 650 | F68: Entente intercomm. Crissier | G68: Dépôt chalet Baleiski | H68: MCA | I68: CompteCourant | L68: =IF(B68="","",IF(I68="CompteCourant",IF(IF(ISNA(VLOOKUP(B68,DATA!$A$1:$A$16,1,0)),"",VLOOKUP(B68,DATA!$A$1:$A$16,1,0))="",L67+E68,L67-E68),L67)) -> 3416.24 | M68: =IF(B68="","",IF(I68="Coffre",IF(IF(ISNA(VLOOKUP(B68,DATA!$A$1:$A$16,1,0)),"",VLOOKUP(B68,DATA!$A$1:$A$16,1,0))="",M67+E68,M67-E68),M67)) -> 2242.2 | N68: =IF(B68="","",IF(I68="CompteEpargne",IF(IF(ISNA(VLOOKUP(B68,DATA!$A$1:$A$16,1,0)),"",VLOOKUP(B68,DATA!$A$1:$A$16,1,0))="",N67+E68,N67-E68),N67)) -> 42.64 | O68: =IF(B68="","",IF(J68="CompteEpargne",IF(IF(ISNA(VLOOKUP(B68,DATA!$A$1:$A$16,1,0)),"",VLOOKUP(B68,DATA!$A$1:$A$16,1,0))="",O67+E68,O67-E68),O67)) -> 42.64 | P68: =IF(L68="", "", SUM(L68,M68,N68,O68)) -> 5743.72
B69: EVENTS / Produits | C69: =C68+1 -> 65 | D69: 45973 | E69: 19.74 | F69: BLV | G69: Entrée after | H69: MCA | I69: CompteCourant | L69: =IF(B69="","",IF(I69="CompteCourant",IF(IF(ISNA(VLOOKUP(B69,DATA!$A$1:$A$16,1,0)),"",VLOOKUP(B69,DATA!$A$1:$A$16,1,0))="",L68+E69,L68-E69),L68)) -> 3435.98 | M69: =IF(B69="","",IF(I69="Coffre",IF(IF(ISNA(VLOOKUP(B69,DATA!$A$1:$A$16,1,0)),"",VLOOKUP(B69,DATA!$A$1:$A$16,1,0))="",M68+E69,M68-E69),M68)) -> 2242.2 | N69: =IF(B69="","",IF(I69="CompteEpargne",IF(IF(ISNA(VLOOKUP(B69,DATA!$A$1:$A$16,1,0)),"",VLOOKUP(B69,DATA!$A$1:$A$16,1,0))="",N68+E69,N68-E69),N68)) -> 42.64 | O69: =IF(B69="","",IF(J69="CompteEpargne",IF(IF(ISNA(VLOOKUP(B69,DATA!$A$1:$A$16,1,0)),"",VLOOKUP(B69,DATA!$A$1:$A$16,1,0))="",O68+E69,O68-E69),O68)) -> 42.64 | P69: =IF(L69="", "", SUM(L69,M69,N69,O69)) -> 5763.46
B70: SANS EFFET / Charges | C70: =C69+1 -> 66 | D70: 45974 | E70: 74.1 | F70: Mobility | G70: Location remplacement cuisine | H70: MCA | I70: CompteCourant | L70: =IF(B70="","",IF(I70="CompteCourant",IF(IF(ISNA(VLOOKUP(B70,DATA!$A$1:$A$16,1,0)),"",VLOOKUP(B70,DATA!$A$1:$A$16,1,0))="",L69+E70,L69-E70),L69)) -> 3361.88 | M70: =IF(B70="","",IF(I70="Coffre",IF(IF(ISNA(VLOOKUP(B70,DATA!$A$1:$A$16,1,0)),"",VLOOKUP(B70,DATA!$A$1:$A$16,1,0))="",M69+E70,M69-E70),M69)) -> 2242.2 | N70: =IF(B70="","",IF(I70="CompteEpargne",IF(IF(ISNA(VLOOKUP(B70,DATA!$A$1:$A$16,1,0)),"",VLOOKUP(B70,DATA!$A$1:$A$16,1,0))="",N69+E70,N69-E70),N69)) -> 42.64 | O70: =IF(B70="","",IF(J70="CompteEpargne",IF(IF(ISNA(VLOOKUP(B70,DATA!$A$1:$A$16,1,0)),"",VLOOKUP(B70,DATA!$A$1:$A$16,1,0))="",O69+E70,O69-E70),O69)) -> 42.64 | P70: =IF(L70="", "", SUM(L70,M70,N70,O70)) -> 5689.36
B71: EVENTS / Charges | C71: =C70+1 -> 67 | D71: 45976 | E71: 18 | F71: Coop St. Blaise | G71: Achats MDN | H71: MCA | I71: CompteCourant | J71: MDN | L71: =IF(B71="","",IF(I71="CompteCourant",IF(IF(ISNA(VLOOKUP(B71,DATA!$A$1:$A$16,1,0)),"",VLOOKUP(B71,DATA!$A$1:$A$16,1,0))="",L70+E71,L70-E71),L70)) -> 3343.88 | M71: =IF(B71="","",IF(I71="Coffre",IF(IF(ISNA(VLOOKUP(B71,DATA!$A$1:$A$16,1,0)),"",VLOOKUP(B71,DATA!$A$1:$A$16,1,0))="",M70+E71,M70-E71),M70)) -> 2242.2 | N71: =IF(B71="","",IF(I71="CompteEpargne",IF(IF(ISNA(VLOOKUP(B71,DATA!$A$1:$A$16,1,0)),"",VLOOKUP(B71,DATA!$A$1:$A$16,1,0))="",N70+E71,N70-E71),N70)) -> 42.64 | O71: =IF(B71="","",IF(J71="CompteEpargne",IF(IF(ISNA(VLOOKUP(B71,DATA!$A$1:$A$16,1,0)),"",VLOOKUP(B71,DATA!$A$1:$A$16,1,0))="",O70+E71,O70-E71),O70)) -> 42.64 | P71: =IF(L71="", "", SUM(L71,M71,N71,O71)) -> 5671.36
B72: EVENTS / Charges | C72: =C71+1 -> 68 | D72: 45976 | E72: 740 | F72: Prodega | G72: Achats MDN | H72: MCA | I72: CompteCourant | L72: =IF(B72="","",IF(I72="CompteCourant",IF(IF(ISNA(VLOOKUP(B72,DATA!$A$1:$A$16,1,0)),"",VLOOKUP(B72,DATA!$A$1:$A$16,1,0))="",L71+E72,L71-E72),L71)) -> 2603.88 | M72: =IF(B72="","",IF(I72="Coffre",IF(IF(ISNA(VLOOKUP(B72,DATA!$A$1:$A$16,1,0)),"",VLOOKUP(B72,DATA!$A$1:$A$16,1,0))="",M71+E72,M71-E72),M71)) -> 2242.2 | N72: =IF(B72="","",IF(I72="CompteEpargne",IF(IF(ISNA(VLOOKUP(B72,DATA!$A$1:$A$16,1,0)),"",VLOOKUP(B72,DATA!$A$1:$A$16,1,0))="",N71+E72,N71-E72),N71)) -> 42.64 | O72: =IF(B72="","",IF(J72="CompteEpargne",IF(IF(ISNA(VLOOKUP(B72,DATA!$A$1:$A$16,1,0)),"",VLOOKUP(B72,DATA!$A$1:$A$16,1,0))="",O71+E72,O71-E72),O71)) -> 42.64 | P72: =IF(L72="", "", SUM(L72,M72,N72,O72)) -> 4931.36
B73: SANS EFFET / Charges | C73: =C72+1 -> 69 | D73: 45978 | E73: 305.8 | F73: IKEA (CembraPay) | G73: Mobilier divers | H73: MCA | I73: CompteCourant | L73: =IF(B73="","",IF(I73="CompteCourant",IF(IF(ISNA(VLOOKUP(B73,DATA!$A$1:$A$16,1,0)),"",VLOOKUP(B73,DATA!$A$1:$A$16,1,0))="",L72+E73,L72-E73),L72)) -> 2298.08 | M73: =IF(B73="","",IF(I73="Coffre",IF(IF(ISNA(VLOOKUP(B73,DATA!$A$1:$A$16,1,0)),"",VLOOKUP(B73,DATA!$A$1:$A$16,1,0))="",M72+E73,M72-E73),M72)) -> 2242.2 | N73: =IF(B73="","",IF(I73="CompteEpargne",IF(IF(ISNA(VLOOKUP(B73,DATA!$A$1:$A$16,1,0)),"",VLOOKUP(B73,DATA!$A$1:$A$16,1,0))="",N72+E73,N72-E73),N72)) -> 42.64 | O73: =IF(B73="","",IF(J73="CompteEpargne",IF(IF(ISNA(VLOOKUP(B73,DATA!$A$1:$A$16,1,0)),"",VLOOKUP(B73,DATA!$A$1:$A$16,1,0))="",O72+E73,O72-E73),O72)) -> 42.64 | P73: =IF(L73="", "", SUM(L73,M73,N73,O73)) -> 4625.56
B74: DÉCORATION / Charges | C74: =C73+1 -> 70 | D74: 45978 | E74: 114.8 | F74: Cécile Cabaret | G74: note de frais deco | H74: MCA | I74: CompteCourant | L74: =IF(B74="","",IF(I74="CompteCourant",IF(IF(ISNA(VLOOKUP(B74,DATA!$A$1:$A$16,1,0)),"",VLOOKUP(B74,DATA!$A$1:$A$16,1,0))="",L73+E74,L73-E74),L73)) -> 2183.28 | M74: =IF(B74="","",IF(I74="Coffre",IF(IF(ISNA(VLOOKUP(B74,DATA!$A$1:$A$16,1,0)),"",VLOOKUP(B74,DATA!$A$1:$A$16,1,0))="",M73+E74,M73-E74),M73)) -> 2242.2 | N74: =IF(B74="","",IF(I74="CompteEpargne",IF(IF(ISNA(VLOOKUP(B74,DATA!$A$1:$A$16,1,0)),"",VLOOKUP(B74,DATA!$A$1:$A$16,1,0))="",N73+E74,N73-E74),N73)) -> 42.64 | O74: =IF(B74="","",IF(J74="CompteEpargne",IF(IF(ISNA(VLOOKUP(B74,DATA!$A$1:$A$16,1,0)),"",VLOOKUP(B74,DATA!$A$1:$A$16,1,0))="",O73+E74,O73-E74),O73)) -> 42.64 | P74: =IF(L74="", "", SUM(L74,M74,N74,O74)) -> 4510.76
B75: ADMINISTRATION / Charges | C75: =C74+1 -> 71 | D75: 45978 | E75: 51.5 | F75: Gilles Rothermund | G75: note de frais | H75: MCA | I75: CompteCourant | L75: =IF(B75="","",IF(I75="CompteCourant",IF(IF(ISNA(VLOOKUP(B75,DATA!$A$1:$A$16,1,0)),"",VLOOKUP(B75,DATA!$A$1:$A$16,1,0))="",L74+E75,L74-E75),L74)) -> 2131.78 | M75: =IF(B75="","",IF(I75="Coffre",IF(IF(ISNA(VLOOKUP(B75,DATA!$A$1:$A$16,1,0)),"",VLOOKUP(B75,DATA!$A$1:$A$16,1,0))="",M74+E75,M74-E75),M74)) -> 2242.2 | N75: =IF(B75="","",IF(I75="CompteEpargne",IF(IF(ISNA(VLOOKUP(B75,DATA!$A$1:$A$16,1,0)),"",VLOOKUP(B75,DATA!$A$1:$A$16,1,0))="",N74+E75,N74-E75),N74)) -> 42.64 | O75: =IF(B75="","",IF(J75="CompteEpargne",IF(IF(ISNA(VLOOKUP(B75,DATA!$A$1:$A$16,1,0)),"",VLOOKUP(B75,DATA!$A$1:$A$16,1,0))="",O74+E75,O74-E75),O74)) -> 42.64 | P75: =IF(L75="", "", SUM(L75,M75,N75,O75)) -> 4459.26
B76: ADMINISTRATION / Charges | C76: =C75+1 -> 72 | D76: 45978 | E76: 45 | F76: Sarah Mallet | G76: note de frais | H76: MCA | I76: CompteCourant | L76: =IF(B76="","",IF(I76="CompteCourant",IF(IF(ISNA(VLOOKUP(B76,DATA!$A$1:$A$16,1,0)),"",VLOOKUP(B76,DATA!$A$1:$A$16,1,0))="",L75+E76,L75-E76),L75)) -> 2086.78 | M76: =IF(B76="","",IF(I76="Coffre",IF(IF(ISNA(VLOOKUP(B76,DATA!$A$1:$A$16,1,0)),"",VLOOKUP(B76,DATA!$A$1:$A$16,1,0))="",M75+E76,M75-E76),M75)) -> 2242.2 | N76: =IF(B76="","",IF(I76="CompteEpargne",IF(IF(ISNA(VLOOKUP(B76,DATA!$A$1:$A$16,1,0)),"",VLOOKUP(B76,DATA!$A$1:$A$16,1,0))="",N75+E76,N75-E76),N75)) -> 42.64 | O76: =IF(B76="","",IF(J76="CompteEpargne",IF(IF(ISNA(VLOOKUP(B76,DATA!$A$1:$A$16,1,0)),"",VLOOKUP(B76,DATA!$A$1:$A$16,1,0))="",O75+E76,O75-E76),O75)) -> 42.64 | P76: =IF(L76="", "", SUM(L76,M76,N76,O76)) -> 4414.26
B77: EVENTS / Produits | C77: =C76+1 -> 73 | D77: 45978 | E77: 19.73 | F77: BLV | G77: Event XXX | H77: MCA | I77: CompteCourant | L77: =IF(B77="","",IF(I77="CompteCourant",IF(IF(ISNA(VLOOKUP(B77,DATA!$A$1:$A$16,1,0)),"",VLOOKUP(B77,DATA!$A$1:$A$16,1,0))="",L76+E77,L76-E77),L76)) -> 2106.51 | M77: =IF(B77="","",IF(I77="Coffre",IF(IF(ISNA(VLOOKUP(B77,DATA!$A$1:$A$16,1,0)),"",VLOOKUP(B77,DATA!$A$1:$A$16,1,0))="",M76+E77,M76-E77),M76)) -> 2242.2 | N77: =IF(B77="","",IF(I77="CompteEpargne",IF(IF(ISNA(VLOOKUP(B77,DATA!$A$1:$A$16,1,0)),"",VLOOKUP(B77,DATA!$A$1:$A$16,1,0))="",N76+E77,N76-E77),N76)) -> 42.64 | O77: =IF(B77="","",IF(J77="CompteEpargne",IF(IF(ISNA(VLOOKUP(B77,DATA!$A$1:$A$16,1,0)),"",VLOOKUP(B77,DATA!$A$1:$A$16,1,0))="",O76+E77,O76-E77),O76)) -> 42.64 | P77: =IF(L77="", "", SUM(L77,M77,N77,O77)) -> 4433.99
B78: EVENTS / Produits | C78: =C77+1 -> 74 | D78: 45979 | E78: 3.95 | F78: BLV | G78: Event XXX | H78: MCA | I78: CompteCourant | L78: =IF(B78="","",IF(I78="CompteCourant",IF(IF(ISNA(VLOOKUP(B78,DATA!$A$1:$A$16,1,0)),"",VLOOKUP(B78,DATA!$A$1:$A$16,1,0))="",L77+E78,L77-E78),L77)) -> 2110.46 | M78: =IF(B78="","",IF(I78="Coffre",IF(IF(ISNA(VLOOKUP(B78,DATA!$A$1:$A$16,1,0)),"",VLOOKUP(B78,DATA!$A$1:$A$16,1,0))="",M77+E78,M77-E78),M77)) -> 2242.2 | N78: =IF(B78="","",IF(I78="CompteEpargne",IF(IF(ISNA(VLOOKUP(B78,DATA!$A$1:$A$16,1,0)),"",VLOOKUP(B78,DATA!$A$1:$A$16,1,0))="",N77+E78,N77-E78),N77)) -> 42.64 | O78: =IF(B78="","",IF(J78="CompteEpargne",IF(IF(ISNA(VLOOKUP(B78,DATA!$A$1:$A$16,1,0)),"",VLOOKUP(B78,DATA!$A$1:$A$16,1,0))="",O77+E78,O77-E78),O77)) -> 42.64 | P78: =IF(L78="", "", SUM(L78,M78,N78,O78)) -> 4437.94
B79: EVENTS / Produits | C79: =C78+1 -> 75 | D79: 45979 | E79: 14.8 | F79: BLV | G79: Event XXX | H79: MCA | I79: CompteCourant | L79: =IF(B79="","",IF(I79="CompteCourant",IF(IF(ISNA(VLOOKUP(B79,DATA!$A$1:$A$16,1,0)),"",VLOOKUP(B79,DATA!$A$1:$A$16,1,0))="",L78+E79,L78-E79),L78)) -> 2125.26 | M79: =IF(B79="","",IF(I79="Coffre",IF(IF(ISNA(VLOOKUP(B79,DATA!$A$1:$A$16,1,0)),"",VLOOKUP(B79,DATA!$A$1:$A$16,1,0))="",M78+E79,M78-E79),M78)) -> 2242.2 | N79: =IF(B79="","",IF(I79="CompteEpargne",IF(IF(ISNA(VLOOKUP(B79,DATA!$A$1:$A$16,1,0)),"",VLOOKUP(B79,DATA!$A$1:$A$16,1,0))="",N78+E79,N78-E79),N78)) -> 42.64 | O79: =IF(B79="","",IF(J79="CompteEpargne",IF(IF(ISNA(VLOOKUP(B79,DATA!$A$1:$A$16,1,0)),"",VLOOKUP(B79,DATA!$A$1:$A$16,1,0))="",O78+E79,O78-E79),O78)) -> 42.64 | P79: =IF(L79="", "", SUM(L79,M79,N79,O79)) -> 4452.74
B80: ADMINISTRATION / Charges | C80: =C79+1 -> 76 | D80: 45982 | E80: 33.5 | F80: PMT CARTE Landi Nord vaudois V | H80: MCA | I80: CompteCourant | L80: =IF(B80="","",IF(I80="CompteCourant",IF(IF(ISNA(VLOOKUP(B80,DATA!$A$1:$A$16,1,0)),"",VLOOKUP(B80,DATA!$A$1:$A$16,1,0))="",L79+E80,L79-E80),L79)) -> 2091.76 | M80: =IF(B80="","",IF(I80="Coffre",IF(IF(ISNA(VLOOKUP(B80,DATA!$A$1:$A$16,1,0)),"",VLOOKUP(B80,DATA!$A$1:$A$16,1,0))="",M79+E80,M79-E80),M79)) -> 2242.2 | N80: =IF(B80="","",IF(I80="CompteEpargne",IF(IF(ISNA(VLOOKUP(B80,DATA!$A$1:$A$16,1,0)),"",VLOOKUP(B80,DATA!$A$1:$A$16,1,0))="",N79+E80,N79-E80),N79)) -> 42.64 | O80: =IF(B80="","",IF(J80="CompteEpargne",IF(IF(ISNA(VLOOKUP(B80,DATA!$A$1:$A$16,1,0)),"",VLOOKUP(B80,DATA!$A$1:$A$16,1,0))="",O79+E80,O79-E80),O79)) -> 42.64 | P80: =IF(L80="", "", SUM(L80,M80,N80,O80)) -> 4419.24
B81: EVENTS / Produits | C81: =C80+1 -> 77 | D81: 45982 | E81: 2.96 | F81: BLV | G81: entrée twint | H81: MCA | I81: CompteCourant | L81: =IF(B81="","",IF(I81="CompteCourant",IF(IF(ISNA(VLOOKUP(B81,DATA!$A$1:$A$16,1,0)),"",VLOOKUP(B81,DATA!$A$1:$A$16,1,0))="",L80+E81,L80-E81),L80)) -> 2094.72 | M81: =IF(B81="","",IF(I81="Coffre",IF(IF(ISNA(VLOOKUP(B81,DATA!$A$1:$A$16,1,0)),"",VLOOKUP(B81,DATA!$A$1:$A$16,1,0))="",M80+E81,M80-E81),M80)) -> 2242.2 | N81: =IF(B81="","",IF(I81="CompteEpargne",IF(IF(ISNA(VLOOKUP(B81,DATA!$A$1:$A$16,1,0)),"",VLOOKUP(B81,DATA!$A$1:$A$16,1,0))="",N80+E81,N80-E81),N80)) -> 42.64 | O81: =IF(B81="","",IF(J81="CompteEpargne",IF(IF(ISNA(VLOOKUP(B81,DATA!$A$1:$A$16,1,0)),"",VLOOKUP(B81,DATA!$A$1:$A$16,1,0))="",O80+E81,O80-E81),O80)) -> 42.64 | P81: =IF(L81="", "", SUM(L81,M81,N81,O81)) -> 4422.2
B82: ADMINISTRATION / Charges | C82: =C81+1 -> 78 | D82: 45983 | E82: 46.1 | F82: PMT CARTE Lidl Yverdon | H82: MCA | I82: CompteCourant | L82: =IF(B82="","",IF(I82="CompteCourant",IF(IF(ISNA(VLOOKUP(B82,DATA!$A$1:$A$16,1,0)),"",VLOOKUP(B82,DATA!$A$1:$A$16,1,0))="",L81+E82,L81-E82),L81)) -> 2048.62 | M82: =IF(B82="","",IF(I82="Coffre",IF(IF(ISNA(VLOOKUP(B82,DATA!$A$1:$A$16,1,0)),"",VLOOKUP(B82,DATA!$A$1:$A$16,1,0))="",M81+E82,M81-E82),M81)) -> 2242.2 | N82: =IF(B82="","",IF(I82="CompteEpargne",IF(IF(ISNA(VLOOKUP(B82,DATA!$A$1:$A$16,1,0)),"",VLOOKUP(B82,DATA!$A$1:$A$16,1,0))="",N81+E82,N81-E82),N81)) -> 42.64 | O82: =IF(B82="","",IF(J82="CompteEpargne",IF(IF(ISNA(VLOOKUP(B82,DATA!$A$1:$A$16,1,0)),"",VLOOKUP(B82,DATA!$A$1:$A$16,1,0))="",O81+E82,O81-E82),O81)) -> 42.64 | P82: =IF(L82="", "", SUM(L82,M82,N82,O82)) -> 4376.1
B83: EVENTS / Produits | C83: =C82+1 -> 79 | D83: 45985 | E83: 136.18 | F83: BLV | G83: entrée twint | H83: MCA | I83: CompteCourant | L83: =IF(B83="","",IF(I83="CompteCourant",IF(IF(ISNA(VLOOKUP(B83,DATA!$A$1:$A$16,1,0)),"",VLOOKUP(B83,DATA!$A$1:$A$16,1,0))="",L82+E83,L82-E83),L82)) -> 2184.8 | M83: =IF(B83="","",IF(I83="Coffre",IF(IF(ISNA(VLOOKUP(B83,DATA!$A$1:$A$16,1,0)),"",VLOOKUP(B83,DATA!$A$1:$A$16,1,0))="",M82+E83,M82-E83),M82)) -> 2242.2 | N83: =IF(B83="","",IF(I83="CompteEpargne",IF(IF(ISNA(VLOOKUP(B83,DATA!$A$1:$A$16,1,0)),"",VLOOKUP(B83,DATA!$A$1:$A$16,1,0))="",N82+E83,N82-E83),N82)) -> 42.64 | O83: =IF(B83="","",IF(J83="CompteEpargne",IF(IF(ISNA(VLOOKUP(B83,DATA!$A$1:$A$16,1,0)),"",VLOOKUP(B83,DATA!$A$1:$A$16,1,0))="",O82+E83,O82-E83),O82)) -> 42.64 | P83: =IF(L83="", "", SUM(L83,M83,N83,O83)) -> 4512.28
B84: EVENTS / Produits | C84: =C83+1 -> 80 | D84: 45985 | E84: 196.87 | F84: BLV | G84: entrée twint | H84: MCA | I84: CompteCourant | L84: =IF(B84="","",IF(I84="CompteCourant",IF(IF(ISNA(VLOOKUP(B84,DATA!$A$1:$A$16,1,0)),"",VLOOKUP(B84,DATA!$A$1:$A$16,1,0))="",L83+E84,L83-E84),L83)) -> 2381.67 | M84: =IF(B84="","",IF(I84="Coffre",IF(IF(ISNA(VLOOKUP(B84,DATA!$A$1:$A$16,1,0)),"",VLOOKUP(B84,DATA!$A$1:$A$16,1,0))="",M83+E84,M83-E84),M83)) -> 2242.2 | N84: =IF(B84="","",IF(I84="CompteEpargne",IF(IF(ISNA(VLOOKUP(B84,DATA!$A$1:$A$16,1,0)),"",VLOOKUP(B84,DATA!$A$1:$A$16,1,0))="",N83+E84,N83-E84),N83)) -> 42.64 | O84: =IF(B84="","",IF(J84="CompteEpargne",IF(IF(ISNA(VLOOKUP(B84,DATA!$A$1:$A$16,1,0)),"",VLOOKUP(B84,DATA!$A$1:$A$16,1,0))="",O83+E84,O83-E84),O83)) -> 42.64 | P84: =IF(L84="", "", SUM(L84,M84,N84,O84)) -> 4709.15
B85: SANS EFFET / Produits | C85: =C84+1 -> 81 | D85: 45986 | E85: 3919.55 | F85: BLV | G85: HEIG-VD remboursement cuisine | H85: MCA | I85: CompteCourant | L85: =IF(B85="","",IF(I85="CompteCourant",IF(IF(ISNA(VLOOKUP(B85,DATA!$A$1:$A$16,1,0)),"",VLOOKUP(B85,DATA!$A$1:$A$16,1,0))="",L84+E85,L84-E85),L84)) -> 6301.22 | M85: =IF(B85="","",IF(I85="Coffre",IF(IF(ISNA(VLOOKUP(B85,DATA!$A$1:$A$16,1,0)),"",VLOOKUP(B85,DATA!$A$1:$A$16,1,0))="",M84+E85,M84-E85),M84)) -> 2242.2 | N85: =IF(B85="","",IF(I85="CompteEpargne",IF(IF(ISNA(VLOOKUP(B85,DATA!$A$1:$A$16,1,0)),"",VLOOKUP(B85,DATA!$A$1:$A$16,1,0))="",N84+E85,N84-E85),N84)) -> 42.64 | O85: =IF(B85="","",IF(J85="CompteEpargne",IF(IF(ISNA(VLOOKUP(B85,DATA!$A$1:$A$16,1,0)),"",VLOOKUP(B85,DATA!$A$1:$A$16,1,0))="",O84+E85,O84-E85),O84)) -> 42.64 | P85: =IF(L85="", "", SUM(L85,M85,N85,O85)) -> 8628.7
B86: EVENTS / Produits | C86: =C85+1 -> 82 | D86: 45986 | E86: 20.73 | F86: BLV | G86: entrée twint | H86: MCA | I86: CompteCourant | L86: =IF(B86="","",IF(I86="CompteCourant",IF(IF(ISNA(VLOOKUP(B86,DATA!$A$1:$A$16,1,0)),"",VLOOKUP(B86,DATA!$A$1:$A$16,1,0))="",L85+E86,L85-E86),L85)) -> 6321.95 | M86: =IF(B86="","",IF(I86="Coffre",IF(IF(ISNA(VLOOKUP(B86,DATA!$A$1:$A$16,1,0)),"",VLOOKUP(B86,DATA!$A$1:$A$16,1,0))="",M85+E86,M85-E86),M85)) -> 2242.2 | N86: =IF(B86="","",IF(I86="CompteEpargne",IF(IF(ISNA(VLOOKUP(B86,DATA!$A$1:$A$16,1,0)),"",VLOOKUP(B86,DATA!$A$1:$A$16,1,0))="",N85+E86,N85-E86),N85)) -> 42.64 | O86: =IF(B86="","",IF(J86="CompteEpargne",IF(IF(ISNA(VLOOKUP(B86,DATA!$A$1:$A$16,1,0)),"",VLOOKUP(B86,DATA!$A$1:$A$16,1,0))="",O85+E86,O85-E86),O85)) -> 42.64 | P86: =IF(L86="", "", SUM(L86,M86,N86,O86)) -> 8649.43
B87: EVENTS / Produits | C87: =C86+1 -> 83 | D87: 45986 | E87: 19.74 | F87: BLV | G87: entrée twint | H87: MCA | I87: CompteCourant | L87: =IF(B87="","",IF(I87="CompteCourant",IF(IF(ISNA(VLOOKUP(B87,DATA!$A$1:$A$16,1,0)),"",VLOOKUP(B87,DATA!$A$1:$A$16,1,0))="",L86+E87,L86-E87),L86)) -> 6341.69 | M87: =IF(B87="","",IF(I87="Coffre",IF(IF(ISNA(VLOOKUP(B87,DATA!$A$1:$A$16,1,0)),"",VLOOKUP(B87,DATA!$A$1:$A$16,1,0))="",M86+E87,M86-E87),M86)) -> 2242.2 | N87: =IF(B87="","",IF(I87="CompteEpargne",IF(IF(ISNA(VLOOKUP(B87,DATA!$A$1:$A$16,1,0)),"",VLOOKUP(B87,DATA!$A$1:$A$16,1,0))="",N86+E87,N86-E87),N86)) -> 42.64 | O87: =IF(B87="","",IF(J87="CompteEpargne",IF(IF(ISNA(VLOOKUP(B87,DATA!$A$1:$A$16,1,0)),"",VLOOKUP(B87,DATA!$A$1:$A$16,1,0))="",O86+E87,O86-E87),O86)) -> 42.64 | P87: =IF(L87="", "", SUM(L87,M87,N87,O87)) -> 8669.17
B88: SANS EFFET / Charges | C88: =C87+1 -> 84 | D88: 45986 | E88: 400 | F88: PRELEVEMENT YVERDON | G88: Transfert caisse | H88: MCA | I88: CompteCourant | L88: =IF(B88="","",IF(I88="CompteCourant",IF(IF(ISNA(VLOOKUP(B88,DATA!$A$1:$A$16,1,0)),"",VLOOKUP(B88,DATA!$A$1:$A$16,1,0))="",L87+E88,L87-E88),L87)) -> 5941.69 | M88: =IF(B88="","",IF(I88="Coffre",IF(IF(ISNA(VLOOKUP(B88,DATA!$A$1:$A$16,1,0)),"",VLOOKUP(B88,DATA!$A$1:$A$16,1,0))="",M87+E88,M87-E88),M87)) -> 2242.2 | N88: =IF(B88="","",IF(I88="CompteEpargne",IF(IF(ISNA(VLOOKUP(B88,DATA!$A$1:$A$16,1,0)),"",VLOOKUP(B88,DATA!$A$1:$A$16,1,0))="",N87+E88,N87-E88),N87)) -> 42.64 | O88: =IF(B88="","",IF(J88="CompteEpargne",IF(IF(ISNA(VLOOKUP(B88,DATA!$A$1:$A$16,1,0)),"",VLOOKUP(B88,DATA!$A$1:$A$16,1,0))="",O87+E88,O87-E88),O87)) -> 42.64 | P88: =IF(L88="", "", SUM(L88,M88,N88,O88)) -> 8269.17
B89: ADMINISTRATION / Charges | C89: =C88+1 -> 85 | D89: 45987 | E89: 168 | F89: Lucas Charbonnier | H89: MCA | I89: CompteCourant | L89: =IF(B89="","",IF(I89="CompteCourant",IF(IF(ISNA(VLOOKUP(B89,DATA!$A$1:$A$16,1,0)),"",VLOOKUP(B89,DATA!$A$1:$A$16,1,0))="",L88+E89,L88-E89),L88)) -> 5773.69 | M89: =IF(B89="","",IF(I89="Coffre",IF(IF(ISNA(VLOOKUP(B89,DATA!$A$1:$A$16,1,0)),"",VLOOKUP(B89,DATA!$A$1:$A$16,1,0))="",M88+E89,M88-E89),M88)) -> 2242.2 | N89: =IF(B89="","",IF(I89="CompteEpargne",IF(IF(ISNA(VLOOKUP(B89,DATA!$A$1:$A$16,1,0)),"",VLOOKUP(B89,DATA!$A$1:$A$16,1,0))="",N88+E89,N88-E89),N88)) -> 42.64 | O89: =IF(B89="","",IF(J89="CompteEpargne",IF(IF(ISNA(VLOOKUP(B89,DATA!$A$1:$A$16,1,0)),"",VLOOKUP(B89,DATA!$A$1:$A$16,1,0))="",O88+E89,O88-E89),O88)) -> 42.64 | P89: =IF(L89="", "", SUM(L89,M89,N89,O89)) -> 8101.17
B90: ADMINISTRATION / Charges | C90: =C89+1 -> 86 | D90: 45987 | E90: 40.2 | F90: Fino Resto SA | G90: ??? | H90: MCA | I90: CompteCourant | L90: =IF(B90="","",IF(I90="CompteCourant",IF(IF(ISNA(VLOOKUP(B90,DATA!$A$1:$A$16,1,0)),"",VLOOKUP(B90,DATA!$A$1:$A$16,1,0))="",L89+E90,L89-E90),L89)) -> 5733.49 | M90: =IF(B90="","",IF(I90="Coffre",IF(IF(ISNA(VLOOKUP(B90,DATA!$A$1:$A$16,1,0)),"",VLOOKUP(B90,DATA!$A$1:$A$16,1,0))="",M89+E90,M89-E90),M89)) -> 2242.2 | N90: =IF(B90="","",IF(I90="CompteEpargne",IF(IF(ISNA(VLOOKUP(B90,DATA!$A$1:$A$16,1,0)),"",VLOOKUP(B90,DATA!$A$1:$A$16,1,0))="",N89+E90,N89-E90),N89)) -> 42.64 | O90: =IF(B90="","",IF(J90="CompteEpargne",IF(IF(ISNA(VLOOKUP(B90,DATA!$A$1:$A$16,1,0)),"",VLOOKUP(B90,DATA!$A$1:$A$16,1,0))="",O89+E90,O89-E90),O89)) -> 42.64 | P90: =IF(L90="", "", SUM(L90,M90,N90,O90)) -> 8060.97
B91: RAVITAILLEMENT / Produits | C91: =C90+1 -> 87 | D91: 45988 | E91: 54 | F91: BLV | G91: AGE : achat vin AG | H91: MCA | I91: CompteCourant | L91: =IF(B91="","",IF(I91="CompteCourant",IF(IF(ISNA(VLOOKUP(B91,DATA!$A$1:$A$16,1,0)),"",VLOOKUP(B91,DATA!$A$1:$A$16,1,0))="",L90+E91,L90-E91),L90)) -> 5787.49 | M91: =IF(B91="","",IF(I91="Coffre",IF(IF(ISNA(VLOOKUP(B91,DATA!$A$1:$A$16,1,0)),"",VLOOKUP(B91,DATA!$A$1:$A$16,1,0))="",M90+E91,M90-E91),M90)) -> 2242.2 | N91: =IF(B91="","",IF(I91="CompteEpargne",IF(IF(ISNA(VLOOKUP(B91,DATA!$A$1:$A$16,1,0)),"",VLOOKUP(B91,DATA!$A$1:$A$16,1,0))="",N90+E91,N90-E91),N90)) -> 42.64 | O91: =IF(B91="","",IF(J91="CompteEpargne",IF(IF(ISNA(VLOOKUP(B91,DATA!$A$1:$A$16,1,0)),"",VLOOKUP(B91,DATA!$A$1:$A$16,1,0))="",O90+E91,O90-E91),O90)) -> 42.64 | P91: =IF(L91="", "", SUM(L91,M91,N91,O91)) -> 8114.97
B92: EVENTS / Produits | C92: =C91+1 -> 88 | D92: 45988 | E92: 81.91 | F92: BLV | H92: MCA | I92: CompteCourant | L92: =IF(B92="","",IF(I92="CompteCourant",IF(IF(ISNA(VLOOKUP(B92,DATA!$A$1:$A$16,1,0)),"",VLOOKUP(B92,DATA!$A$1:$A$16,1,0))="",L91+E92,L91-E92),L91)) -> 5869.4 | M92: =IF(B92="","",IF(I92="Coffre",IF(IF(ISNA(VLOOKUP(B92,DATA!$A$1:$A$16,1,0)),"",VLOOKUP(B92,DATA!$A$1:$A$16,1,0))="",M91+E92,M91-E92),M91)) -> 2242.2 | N92: =IF(B92="","",IF(I92="CompteEpargne",IF(IF(ISNA(VLOOKUP(B92,DATA!$A$1:$A$16,1,0)),"",VLOOKUP(B92,DATA!$A$1:$A$16,1,0))="",N91+E92,N91-E92),N91)) -> 42.64 | O92: =IF(B92="","",IF(J92="CompteEpargne",IF(IF(ISNA(VLOOKUP(B92,DATA!$A$1:$A$16,1,0)),"",VLOOKUP(B92,DATA!$A$1:$A$16,1,0))="",O91+E92,O91-E92),O91)) -> 42.64 | P92: =IF(L92="", "", SUM(L92,M92,N92,O92)) -> 8196.88
B93: SANS EFFET / Produits | C93: =C92+1 -> 89 | D93: 45988 | E93: 263.9 | F93: BLV | G93: Versement caisse > CC | H93: MCA | I93: CompteCourant | L93: =IF(B93="","",IF(I93="CompteCourant",IF(IF(ISNA(VLOOKUP(B93,DATA!$A$1:$A$16,1,0)),"",VLOOKUP(B93,DATA!$A$1:$A$16,1,0))="",L92+E93,L92-E93),L92)) -> 6133.3 | M93: =IF(B93="","",IF(I93="Coffre",IF(IF(ISNA(VLOOKUP(B93,DATA!$A$1:$A$16,1,0)),"",VLOOKUP(B93,DATA!$A$1:$A$16,1,0))="",M92+E93,M92-E93),M92)) -> 2242.2 | N93: =IF(B93="","",IF(I93="CompteEpargne",IF(IF(ISNA(VLOOKUP(B93,DATA!$A$1:$A$16,1,0)),"",VLOOKUP(B93,DATA!$A$1:$A$16,1,0))="",N92+E93,N92-E93),N92)) -> 42.64 | O93: =IF(B93="","",IF(J93="CompteEpargne",IF(IF(ISNA(VLOOKUP(B93,DATA!$A$1:$A$16,1,0)),"",VLOOKUP(B93,DATA!$A$1:$A$16,1,0))="",O92+E93,O92-E93),O92)) -> 42.64 | P93: =IF(L93="", "", SUM(L93,M93,N93,O93)) -> 8460.78
B94: SANS EFFET / Produits | C94: =C93+1 -> 90 | D94: 45988 | E94: 300 | F94: BLV | G94: Versement caisse > CC | H94: MCA | I94: CompteCourant | L94: =IF(B94="","",IF(I94="CompteCourant",IF(IF(ISNA(VLOOKUP(B94,DATA!$A$1:$A$16,1,0)),"",VLOOKUP(B94,DATA!$A$1:$A$16,1,0))="",L93+E94,L93-E94),L93)) -> 6433.3 | M94: =IF(B94="","",IF(I94="Coffre",IF(IF(ISNA(VLOOKUP(B94,DATA!$A$1:$A$16,1,0)),"",VLOOKUP(B94,DATA!$A$1:$A$16,1,0))="",M93+E94,M93-E94),M93)) -> 2242.2 | N94: =IF(B94="","",IF(I94="CompteEpargne",IF(IF(ISNA(VLOOKUP(B94,DATA!$A$1:$A$16,1,0)),"",VLOOKUP(B94,DATA!$A$1:$A$16,1,0))="",N93+E94,N93-E94),N93)) -> 42.64 | O94: =IF(B94="","",IF(J94="CompteEpargne",IF(IF(ISNA(VLOOKUP(B94,DATA!$A$1:$A$16,1,0)),"",VLOOKUP(B94,DATA!$A$1:$A$16,1,0))="",O93+E94,O93-E94),O93)) -> 42.64 | P94: =IF(L94="", "", SUM(L94,M94,N94,O94)) -> 8760.78
B95: SANS EFFET / Charges | C95: =C94+1 -> 91 | D95: 45988 | E95: 700 | F95: PRELEVEMENT YVERDON | G95: Versement CC > Caisse | H95: MCA | I95: CompteCourant | L95: =IF(B95="","",IF(I95="CompteCourant",IF(IF(ISNA(VLOOKUP(B95,DATA!$A$1:$A$16,1,0)),"",VLOOKUP(B95,DATA!$A$1:$A$16,1,0))="",L94+E95,L94-E95),L94)) -> 5733.3 | M95: =IF(B95="","",IF(I95="Coffre",IF(IF(ISNA(VLOOKUP(B95,DATA!$A$1:$A$16,1,0)),"",VLOOKUP(B95,DATA!$A$1:$A$16,1,0))="",M94+E95,M94-E95),M94)) -> 2242.2 | N95: =IF(B95="","",IF(I95="CompteEpargne",IF(IF(ISNA(VLOOKUP(B95,DATA!$A$1:$A$16,1,0)),"",VLOOKUP(B95,DATA!$A$1:$A$16,1,0))="",N94+E95,N94-E95),N94)) -> 42.64 | O95: =IF(B95="","",IF(J95="CompteEpargne",IF(IF(ISNA(VLOOKUP(B95,DATA!$A$1:$A$16,1,0)),"",VLOOKUP(B95,DATA!$A$1:$A$16,1,0))="",O94+E95,O94-E95),O94)) -> 42.64 | P95: =IF(L95="", "", SUM(L95,M95,N95,O95)) -> 8060.78
B96: ADMINISTRATION / Charges | C96: =C95+1 -> 92 | D96: 45989 | E96: 14.05 | F96: PMT CARTE Landi Nord vaudois V | H96: MCA | I96: CompteCourant | L96: =IF(B96="","",IF(I96="CompteCourant",IF(IF(ISNA(VLOOKUP(B96,DATA!$A$1:$A$16,1,0)),"",VLOOKUP(B96,DATA!$A$1:$A$16,1,0))="",L95+E96,L95-E96),L95)) -> 5719.25 | M96: =IF(B96="","",IF(I96="Coffre",IF(IF(ISNA(VLOOKUP(B96,DATA!$A$1:$A$16,1,0)),"",VLOOKUP(B96,DATA!$A$1:$A$16,1,0))="",M95+E96,M95-E96),M95)) -> 2242.2 | N96: =IF(B96="","",IF(I96="CompteEpargne",IF(IF(ISNA(VLOOKUP(B96,DATA!$A$1:$A$16,1,0)),"",VLOOKUP(B96,DATA!$A$1:$A$16,1,0))="",N95+E96,N95-E96),N95)) -> 42.64 | O96: =IF(B96="","",IF(J96="CompteEpargne",IF(IF(ISNA(VLOOKUP(B96,DATA!$A$1:$A$16,1,0)),"",VLOOKUP(B96,DATA!$A$1:$A$16,1,0))="",O95+E96,O95-E96),O95)) -> 42.64 | P96: =IF(L96="", "", SUM(L96,M96,N96,O96)) -> 8046.73
B97: EVENTS / Produits | C97: =C96+1 -> 93 | D97: 45989 | E97: 2.96 | F97: BLV | G97: entrée twint | H97: MCA | I97: CompteCourant | L97: =IF(B97="","",IF(I97="CompteCourant",IF(IF(ISNA(VLOOKUP(B97,DATA!$A$1:$A$16,1,0)),"",VLOOKUP(B97,DATA!$A$1:$A$16,1,0))="",L96+E97,L96-E97),L96)) -> 5722.21 | M97: =IF(B97="","",IF(I97="Coffre",IF(IF(ISNA(VLOOKUP(B97,DATA!$A$1:$A$16,1,0)),"",VLOOKUP(B97,DATA!$A$1:$A$16,1,0))="",M96+E97,M96-E97),M96)) -> 2242.2 | N97: =IF(B97="","",IF(I97="CompteEpargne",IF(IF(ISNA(VLOOKUP(B97,DATA!$A$1:$A$16,1,0)),"",VLOOKUP(B97,DATA!$A$1:$A$16,1,0))="",N96+E97,N96-E97),N96)) -> 42.64 | O97: =IF(B97="","",IF(J97="CompteEpargne",IF(IF(ISNA(VLOOKUP(B97,DATA!$A$1:$A$16,1,0)),"",VLOOKUP(B97,DATA!$A$1:$A$16,1,0))="",O96+E97,O96-E97),O96)) -> 42.64 | P97: =IF(L97="", "", SUM(L97,M97,N97,O97)) -> 8049.69
B98: EVENTS / Produits | C98: =C97+1 -> 94 | D98: 45989 | E98: 1.97 | F98: BLV | G98: entrée sumup : manu test | H98: MCA | I98: CompteCourant | J98: MDN | L98: =IF(B98="","",IF(I98="CompteCourant",IF(IF(ISNA(VLOOKUP(B98,DATA!$A$1:$A$16,1,0)),"",VLOOKUP(B98,DATA!$A$1:$A$16,1,0))="",L97+E98,L97-E98),L97)) -> 5724.18 | M98: =IF(B98="","",IF(I98="Coffre",IF(IF(ISNA(VLOOKUP(B98,DATA!$A$1:$A$16,1,0)),"",VLOOKUP(B98,DATA!$A$1:$A$16,1,0))="",M97+E98,M97-E98),M97)) -> 2242.2 | N98: =IF(B98="","",IF(I98="CompteEpargne",IF(IF(ISNA(VLOOKUP(B98,DATA!$A$1:$A$16,1,0)),"",VLOOKUP(B98,DATA!$A$1:$A$16,1,0))="",N97+E98,N97-E98),N97)) -> 42.64 | O98: =IF(B98="","",IF(J98="CompteEpargne",IF(IF(ISNA(VLOOKUP(B98,DATA!$A$1:$A$16,1,0)),"",VLOOKUP(B98,DATA!$A$1:$A$16,1,0))="",O97+E98,O97-E98),O97)) -> 42.64 | P98: =IF(L98="", "", SUM(L98,M98,N98,O98)) -> 8051.66
B99: ADMINISTRATION / Charges | C99: =C98+1 -> 95 | D99: 45992 | E99: 370 | F99: Maxime Magnenat | G99: note de frais | H99: MCA | I99: CompteCourant | L99: =IF(B99="","",IF(I99="CompteCourant",IF(IF(ISNA(VLOOKUP(B99,DATA!$A$1:$A$16,1,0)),"",VLOOKUP(B99,DATA!$A$1:$A$16,1,0))="",L98+E99,L98-E99),L98)) -> 5354.18 | M99: =IF(B99="","",IF(I99="Coffre",IF(IF(ISNA(VLOOKUP(B99,DATA!$A$1:$A$16,1,0)),"",VLOOKUP(B99,DATA!$A$1:$A$16,1,0))="",M98+E99,M98-E99),M98)) -> 2242.2 | N99: =IF(B99="","",IF(I99="CompteEpargne",IF(IF(ISNA(VLOOKUP(B99,DATA!$A$1:$A$16,1,0)),"",VLOOKUP(B99,DATA!$A$1:$A$16,1,0))="",N98+E99,N98-E99),N98)) -> 42.64 | O99: =IF(B99="","",IF(J99="CompteEpargne",IF(IF(ISNA(VLOOKUP(B99,DATA!$A$1:$A$16,1,0)),"",VLOOKUP(B99,DATA!$A$1:$A$16,1,0))="",O98+E99,O98-E99),O98)) -> 42.64 | P99: =IF(L99="", "", SUM(L99,M99,N99,O99)) -> 7681.66
B100: EVENTS / Produits | C100: =C99+1 -> 96 | D100: 45992 | E100: 1.98 | F100: BLV | G100: Entrée twint | H100: MCA | I100: CompteCourant | L100: =IF(B100="","",IF(I100="CompteCourant",IF(IF(ISNA(VLOOKUP(B100,DATA!$A$1:$A$16,1,0)),"",VLOOKUP(B100,DATA!$A$1:$A$16,1,0))="",L99+E100,L99-E100),L99)) -> 5356.16 | M100: =IF(B100="","",IF(I100="Coffre",IF(IF(ISNA(VLOOKUP(B100,DATA!$A$1:$A$16,1,0)),"",VLOOKUP(B100,DATA!$A$1:$A$16,1,0))="",M99+E100,M99-E100),M99)) -> 2242.2 | N100: =IF(B100="","",IF(I100="CompteEpargne",IF(IF(ISNA(VLOOKUP(B100,DATA!$A$1:$A$16,1,0)),"",VLOOKUP(B100,DATA!$A$1:$A$16,1,0))="",N99+E100,N99-E100),N99)) -> 42.64 | O100: =IF(B100="","",IF(J100="CompteEpargne",IF(IF(ISNA(VLOOKUP(B100,DATA!$A$1:$A$16,1,0)),"",VLOOKUP(B100,DATA!$A$1:$A$16,1,0))="",O99+E100,O99-E100),O99)) -> 42.64 | P100: =IF(L100="", "", SUM(L100,M100,N100,O100)) -> 7683.64
...

Sheet RESULTATS
B1: RESULTATS
B2: Année | C2: 2025-2026
B3: Version du budget | C3: 1
B4: Date: | C4: =TODAY() -> 46097
C6: Nombre | D6: Prix
B7: Prélocs
B8: Entrées
B9: Billets subventionnés AGE | C9: 300
B11: Départements | C11: BUDGET | I11: Départements | J11: COMPTABILITE
C12: Charges | E12: Produits | G12: Bénéfices/Pertes | J12: Charges | L12: Produits | N12: Bénéfices/Pertes | Q12: Différence | R12: (par rapport au budget)
B13: =SECURITE!A1 -> SECURITE | C13: =SECURITE!E14 -> 11900 | D13: =C13/$C$29 -> 0.10477972 | E13: =SECURITE!E24 -> 0 | F13: =E13/$C$29 -> 0 | G13: =E13-C13 -> -11900 | I13: =B13 -> SECURITE | J13: =SECURITE!E45 -> 0 | K13: =J13/$J$29 -> 0 | L13: =SECURITE!E55 -> 0 | M13: =L13/$L$29 -> 0 | N13: =L13-J13 -> 0 | P13: =I13 -> SECURITE | Q13: =N13-G13 -> 11900
B14: =PROGRAMMATION!A1 -> PROGRAMMATION | C14: =PROGRAMMATION!E20 -> 18000 | D14: =C14/$C$29 -> 0.15849033 | E14: =PROGRAMMATION!E30 -> 0 | F14: =E14/$C$29 -> 0 | G14: =E14-C14 -> -18000 | I14: =B14 -> PROGRAMMATION | J14: =PROGRAMMATION!E75 -> 1415 | K14: =J14/$J$29 -> 0.064807211 | L14: =PROGRAMMATION!E87 -> 0 | M14: =L14/$L$29 -> 0 | N14: =L14-J14 -> -1415 | P14: =I14 -> PROGRAMMATION | Q14: =N14-G14 -> 16585
B15: =TECHNIQUE!A1 -> TECHNIQUE | C15: =TECHNIQUE!E14 -> 20700 | D15: =C15/$C$29 -> 0.18226388 | E15: =TECHNIQUE!E24 -> 0 | F15: =E15/$C$29 -> 0 | G15: =E15-C15 -> -20700 | H15: ? | I15: =B15 -> TECHNIQUE | J15: =TECHNIQUE!E48 -> 0 | K15: =J15/$J$29 -> 0 | L15: =TECHNIQUE!E58 -> 0 | M15: =L15/$L$29 -> 0 | N15: =L15-J15 -> 0 | P15: =I15 -> TECHNIQUE | Q15: =N15-G15 -> 20700
B16: =INFRASTRUCTURE!A1 -> INFRASTRUCTURE | C16: =INFRASTRUCTURE!E20 -> 9990 | D16: =C16/$C$29 -> 0.087962131 | E16: =INFRASTRUCTURE!E29 -> 200 | F16: =E16/$C$29 -> 0.0017610036 | G16: =E16-C16 -> -9790 | I16: =B16 -> INFRASTRUCTURE | J16: =INFRASTRUCTURE!E73 -> 100 | K16: =J16/$J$29 -> 0.0045800149 | L16: =INFRASTRUCTURE!E88 -> 0 | M16: =L16/$L$29 -> 0 | N16: =L16-J16 -> -100 | P16: =I16 -> INFRASTRUCTURE | Q16: =N16-G16 -> 9690
B17: =RAVITAILLEMENT!A1 -> RAVITAILLEMENT | C17: =RAVITAILLEMENT!E13 -> 16750 | D17: =C17/$C$29 -> 0.14748405 | E17: =RAVITAILLEMENT!E22 -> 30400 | F17: =E17/$C$29 -> 0.26767255 | G17: =E17-C17 -> 13650 | I17: =B17 -> RAVITAILLEMENT | J17: =RAVITAILLEMENT!E108 -> 0 | K17: =J17/$J$29 -> 0 | L17: =RAVITAILLEMENT!E144 -> 108 | M17: =L17/$L$29 -> 0.0049464161 | N17: =L17-J17 -> 108 | P17: =I17 -> RAVITAILLEMENT | Q17: =N17-G17 -> -13542
B18: =SPONSORING!A1 -> SPONSORING | C18: =SPONSORING!E11 -> 0 | D18: =C18/$C$29 -> 0 | E18: =SPONSORING!E50 -> 18500 | F18: =E18/$C$29 -> 0.16289284 | G18: =E18-C18 -> 18500 | I18: =B18 -> SPONSORING | J18: =SPONSORING!E71 -> 0 | K18: =J18/$J$29 -> 0 | L18: =SPONSORING!E102 -> 500 | M18: =L18/$L$29 -> 0.022900075 | N18: =L18-J18 -> 500 | P18: =I18 -> SPONSORING | Q18: =N18-G18 -> -18000
B19: =COMMUNICATION!A1 -> COMMUNICATION | C19: =COMMUNICATION!E20 -> 6562 | D19: =C19/$C$29 -> 0.057778529 | E19: =COMMUNICATION!E27 -> 2500 | F19: =E19/$C$29 -> 0.022012545 | G19: =E19-C19 -> -4062 | I19: =B19 -> COMMUNICATION | J19: =COMMUNICATION!E56 -> 0 | K19: =J19/$J$29 -> 0 | L19: =COMMUNICATION!E85 -> 0 | M19: =L19/$L$29 -> 0 | N19: =L19-J19 -> 0 | P19: =I19 -> COMMUNICATION | Q19: =N19-G19 -> 4062
B20: =ADMINISTRATION!A1 -> ADMINISTRATION | C20: =ADMINISTRATION!E15 -> 6020 | D20: =C20/$C$29 -> 0.053006209 | E20: =ADMINISTRATION!E25 -> 800 | F20: =E20/$C$29 -> 0.0070440145 | G20: =E20-C20 -> -5220 | I20: =B20 -> ADMINISTRATION | J20: =ADMINISTRATION!E53 -> 6440.7 | K20: =J20/$J$29 -> 0.29498502 | L20: =ADMINISTRATION!E79 -> 619.29 | M20: =L20/$L$29 -> 0.028363574 | N20: =L20-J20 -> -5821.41 | P20: =I20 -> ADMINISTRATION | Q20: =N20-G20 -> -601.41
B21: =PMW!A1 -> PMW | C21: =PMW!E15 -> 100 | D21: =C21/$C$29 -> 0.00088050182 | E21: =PMW!E25 -> 0 | F21: =E21/$C$29 -> 0 | G21: =E21-C21 -> -100 | I21: =B21 -> PMW | J21: =PMW!E46 -> 0 | K21: =J21/$J$29 -> 0 | L21: =PMW!E56 -> 0 | M21: =L21/$L$29 -> 0 | N21: =L21-J21 -> 0 | P21: =I21 -> PMW | Q21: =N21-G21 -> 100
B22: =DÉCORATION!A1 -> DÉCORATION | C22: =DÉCORATION!E15 -> 500 | D22: =C22/$C$29 -> 0.0044025091 | E22: =DÉCORATION!E25 -> 0 | F22: =E22/$C$29 -> 0 | G22: =E22-C22 -> -500 | I22: =B22 -> DÉCORATION | J22: =DÉCORATION!E46 -> 244.85 | K22: =J22/$J$29 -> 0.011214167 | L22: =DÉCORATION!E56 -> 0 | M22: =L22/$L$29 -> 0 | N22: =L22-J22 -> -244.85 | P22: =I22 -> DÉCORATION | Q22: =N22-G22 -> 255.15
B23: =ÉLECTRICITÉ!A1 -> ÉLECTRICITÉ | C23: =ÉLECTRICITÉ!E15 -> 300 | D23: =C23/$C$29 -> 0.0026415054 | E23: =ÉLECTRICITÉ!E25 -> 0 | F23: =E23/$C$29 -> 0 | G23: =E23-C23 -> -300 | I23: =B23 -> ÉLECTRICITÉ | J23: =ÉLECTRICITÉ!E46 -> 0 | K23: =J23/$J$29 -> 0 | L23: =ÉLECTRICITÉ!E56 -> 0 | M23: =L23/$L$29 -> 0 | N23: =L23-J23 -> 0 | P23: =I23 -> ÉLECTRICITÉ | Q23: =N23-G23 -> 300
B24: =LOGES!A1 -> LOGES | C24: =LOGES!E15 -> 800 | D24: =C24/$C$29 -> 0.0070440145 | E24: =LOGES!E25 -> 0 | F24: =E24/$C$29 -> 0 | G24: =E24-C24 -> -800 | I24: =B24 -> LOGES | J24: =LOGES!E46 -> 0 | K24: =J24/$J$29 -> 0 | L24: =LOGES!E56 -> 0 | M24: =L24/$L$29 -> 0 | N24: =L24-J24 -> 0 | P24: =I24 -> LOGES | Q24: =N24-G24 -> 800
B25: =ENTREES!A1 -> ENTREES | C25: =ENTREES!E12 -> 1770.6 | D25: =C25/$C$29 -> 0.015590165 | E25: =ENTREES!E23 -> 18700 | F25: =E25/$C$29 -> 0.16465384 | G25: =E25-C25 -> 16929.4 | I25: =B25 -> ENTREES | J25: =ENTREES!E35 -> 1117.35 | K25: =J25/$J$29 -> 0.051174797 | L25: =ENTREES!E99 -> 702.75 | M25: =L25/$L$29 -> 0.032186055 | N25: =L25-J25 -> -414.6 | P25: =I25 -> ENTREES | Q25: =N25-G25 -> -17344
B26: =EVENTS!A1 -> EVENTS | C26: =EVENTS!E21 -> 16179 | D26: =C26/$C$29 -> 0.14245639 | E26: =EVENTS!E39 -> 38552 | F26: =E26/$C$29 -> 0.33945106 | G26: =E26-C26 -> 22373 | H26: ? | I26: =B26 -> EVENTS | J26: =EVENTS!E175 -> 9977.29 | K26: =J26/$J$29 -> 0.45696137 | L26: =EVENTS!E450 -> 19903.95 | M26: =L26/$L$29 -> 0.91160388 | N26: =L26-J26 -> 9926.66 | P26: =I26 -> EVENTS | Q26: =N26-G26 -> -12446.34
B27: =DIVERS!A1 -> DIVERS | C27: =DIVERS!E17 -> 4000 | D27: =C27/$C$29 -> 0.035220073 | E27: =DIVERS!E27 -> 0 | F27: =E27/$C$29 -> 0 | G27: =E27-C27 -> -4000 | I27: =B27 -> DIVERS | J27: =DIVERS!E61 -> 34.2 | K27: =J27/$J$29 -> 0.0015663651 | L27: =DIVERS!E92 -> 0 | M27: =L27/$L$29 -> 0 | N27: =L27-J27 -> -34.2 | P27: =I27 -> DIVERS | Q27: =N27-G27 -> 3965.8
B28: BENEFICE/PERTE | C28: =IF(SUM(C13:C27)<SUM(E13:E27),SUM(E13:E27)-SUM(C13:C27),"") | E28: =IF(SUM(E13:E27)>SUM(C13:C27),"",SUM(C13:C27)-SUM(E13:E27)) -> 3919.6 | I28: BENEFICE/PERTE | J28: =IF(SUM(J13:J27)<SUM(L13:L27),SUM(L13:L27)-SUM(J13:J27),"") -> 2504.6 | L28: =IF(SUM(L13:L27)>SUM(J13:J27),"",SUM(J13:J27)-SUM(L13:L27))
B29: TOTAL | C29: =SUM(C13:C28) -> 113571.6 | E29: =SUM(E13:E28) -> 113571.6 | I29: TOTAL | J29: =SUM(J13:J28) -> 21833.99 | L29: =SUM(L13:L28) -> 21833.99 | P29: TOTAL | Q29: =L29-E29 -> -91737.61

Sheet ADMINISTRATION
A1: ADMINISTRATION
A3: BUDGET
A4: Charges | I4: weezevents | J4: PU | K4: Qte | L4: TOT
A5: Mois de facturation | B5: Libellé | E5: Montant | I5: solution bracelet activé | J5: 2.58 | K5: 800 | L5: =K5*J5 -> 2064
B6: Cotisations USLY | E6: 50 | I6: solution si bon prix | J6: 2 | K6: 800 | L6: =K6*J6 -> 1600
B7: Assurance RC | E7: 995 | I7: frais distribution | J7: 0.02 | K7: 30000 | L7: =K7*J7 -> 600
B8: Petzi | E8: 400 | I8: frais remboursement | J8: 100 | K8: 1 | L8: =K8*J8 -> 100
B9: Frais divers | E9: 300 | I9: assistance mail | J9: 0.05 | K9: 800 | L9: =K9*J9 -> 40
B10: POCAMA | E10: 400 | I10: bracelets | J10: 1.1 | K10: 800 | L10: =K10*J10 -> 880
B11: Weezevent (sans frais activation) | E11: 3600 | F11: worst case scenario | I11: transport | J11: 130 | K11: 1 | L11: =K11*J11 -> 130
B12: frais de compte | E12: 150
B13: Bracelets staff | E13: 85
B14: vignette | E14: 40
A15: Total | E15: =SUM(E6:E14) -> 6020
A16: Produits
A17: Mois de facturation | B17: Libellé | E17: Montant
B18: Activation puce (1 CHF 800 festivaliers) | E18: 800
A25: Total | E25: =SUM(E18:E24) -> 800
A27: COMPTABILITE
A28: Charges
A29: N° | B29: Libellé | C29: Date | D29: En faveur de | E29: Montant
A30: =IF(ISNA(VLOOKUP($A$1&" / "&$A$28,JOURNAL!$B$5:$I$1115,2,0)),"",VLOOKUP($A$1&" / "&$A$28,JOURNAL!$B$5:$I$1115,2,0)) -> 29 | B30: =IF($A30="","",VLOOKUP($A30,JOURNAL!$C$5:$I$1115,5,0)) -> Frais périodiques | C30: =IF($A30="","",VLOOKUP($A30,JOURNAL!$C$5:$I$1115,2,0)) -> 45930 | D30: =IF($A30="","",VLOOKUP($A30,JOURNAL!$C$5:$I$1115,4,0)) -> BCV | E30: =IF($A30="","",VLOOKUP($A30,JOURNAL!$C$5:$I$1115,3,0)) -> 25.2
A31: =IF(A30="","",IF(ISNA(VLOOKUP($A$1&" / "&$A$28,INDIRECT(ADDRESS(A30+5,2,1,,"JOURNAL")&":G500"),2,0)),"",VLOOKUP($A$1&" / "&$A$28,INDIRECT(ADDRESS(A30+5,2,1,,"JOURNAL")&":G500"),2,0))) -> 30 | B31: =IF($A31="","",VLOOKUP($A31,JOURNAL!$C$5:$I$1115,5,0)) -> SG : Pizza | C31: =IF($A31="","",VLOOKUP($A31,JOURNAL!$C$5:$I$1115,2,0)) -> 45932 | D31: =IF($A31="","",VLOOKUP($A31,JOURNAL!$C$5:$I$1115,4,0)) -> Le Csarda | E31: =IF($A31="","",VLOOKUP($A31,JOURNAL!$C$5:$I$1115,3,0)) -> 120
A32: =IF(A31="","",IF(ISNA(VLOOKUP($A$1&" / "&$A$28,INDIRECT(ADDRESS(A31+5,2,1,,"JOURNAL")&":G500"),2,0)),"",VLOOKUP($A$1&" / "&$A$28,INDIRECT(ADDRESS(A31+5,2,1,,"JOURNAL")&":G500"),2,0))) -> 32 | B32: =IF($A32="","",VLOOKUP($A32,JOURNAL!$C$5:$I$1115,5,0)) -> Renouvellement Infomaniak | C32: =IF($A32="","",VLOOKUP($A32,JOURNAL!$C$5:$I$1115,2,0)) -> 45957 | D32: =IF($A32="","",VLOOKUP($A32,JOURNAL!$C$5:$I$1115,4,0)) -> Maxime Magnenat | E32: =IF($A32="","",VLOOKUP($A32,JOURNAL!$C$5:$I$1115,3,0)) -> 36.75
A33: =IF(A32="","",IF(ISNA(VLOOKUP($A$1&" / "&$A$28,INDIRECT(ADDRESS(A32+5,2,1,,"JOURNAL")&":G500"),2,0)),"",VLOOKUP($A$1&" / "&$A$28,INDIRECT(ADDRESS(A32+5,2,1,,"JOURNAL")&":G500"),2,0))) -> 35 | B33: =IF($A33="","",VLOOKUP($A33,JOURNAL!$C$5:$I$1115,5,0)) -> A COMPLETER | C33: =IF($A33="","",VLOOKUP($A33,JOURNAL!$C$5:$I$1115,2,0)) -> 45933 | D33: =IF($A33="","",VLOOKUP($A33,JOURNAL!$C$5:$I$1115,4,0)) -> Landi | E33: =IF($A33="","",VLOOKUP($A33,JOURNAL!$C$5:$I$1115,3,0)) -> 172.6
A34: =IF(A33="","",IF(ISNA(VLOOKUP($A$1&" / "&$A$28,INDIRECT(ADDRESS(A33+5,2,1,,"JOURNAL")&":G500"),2,0)),"",VLOOKUP($A$1&" / "&$A$28,INDIRECT(ADDRESS(A33+5,2,1,,"JOURNAL")&":G500"),2,0))) -> 42 | B34: =IF($A34="","",VLOOKUP($A34,JOURNAL!$C$5:$I$1115,5,0)) -> Achat nouvelle cuisine | C34: =IF($A34="","",VLOOKUP($A34,JOURNAL!$C$5:$I$1115,2,0)) -> 45952 | D34: =IF($A34="","",VLOOKUP($A34,JOURNAL!$C$5:$I$1115,4,0)) -> Patrick Magnenat | E34: =IF($A34="","",VLOOKUP($A34,JOURNAL!$C$5:$I$1115,3,0)) -> 2977.65
A35: =IF(A34="","",IF(ISNA(VLOOKUP($A$1&" / "&$A$28,INDIRECT(ADDRESS(A34+5,2,1,,"JOURNAL")&":G500"),2,0)),"",VLOOKUP($A$1&" / "&$A$28,INDIRECT(ADDRESS(A34+5,2,1,,"JOURNAL")&":G500"),2,0))) -> 52 | B35: =IF($A35="","",VLOOKUP($A35,JOURNAL!$C$5:$I$1115,5,0)) -> Correction après comptage caisse | C35: =IF($A35="","",VLOOKUP($A35,JOURNAL!$C$5:$I$1115,2,0)) -> 45925 | D35: =IF($A35="","",VLOOKUP($A35,JOURNAL!$C$5:$I$1115,4,0)) -> BLV | E35: =IF($A35="","",VLOOKUP($A35,JOURNAL!$C$5:$I$1115,3,0)) -> 591.4
A36: =IF(A35="","",IF(ISNA(VLOOKUP($A$1&" / "&$A$28,INDIRECT(ADDRESS(A35+5,2,1,,"JOURNAL")&":G500"),2,0)),"",VLOOKUP($A$1&" / "&$A$28,INDIRECT(ADDRESS(A35+5,2,1,,"JOURNAL")&":G500"),2,0))) -> 54 | B36: =IF($A36="","",VLOOKUP($A36,JOURNAL!$C$5:$I$1115,5,0)) -> note de frais | C36: =IF($A36="","",VLOOKUP($A36,JOURNAL!$C$5:$I$1115,2,0)) -> 45957 | D36: =IF($A36="","",VLOOKUP($A36,JOURNAL!$C$5:$I$1115,4,0)) -> Maxime Magnenat | E36: =IF($A36="","",VLOOKUP($A36,JOURNAL!$C$5:$I$1115,3,0)) -> 26.85
A37: =IF(A36="","",IF(ISNA(VLOOKUP($A$1&" / "&$A$28,INDIRECT(ADDRESS(A36+5,2,1,,"JOURNAL")&":G500"),2,0)),"",VLOOKUP($A$1&" / "&$A$28,INDIRECT(ADDRESS(A36+5,2,1,,"JOURNAL")&":G500"),2,0))) -> 55 | B37: =IF($A37="","",VLOOKUP($A37,JOURNAL!$C$5:$I$1115,5,0)) -> note de frais | C37: =IF($A37="","",VLOOKUP($A37,JOURNAL!$C$5:$I$1115,2,0)) -> 45957 | D37: =IF($A37="","",VLOOKUP($A37,JOURNAL!$C$5:$I$1115,4,0)) -> Manuel Cabras | E37: =IF($A37="","",VLOOKUP($A37,JOURNAL!$C$5:$I$1115,3,0)) -> 210
A38: =IF(A37="","",IF(ISNA(VLOOKUP($A$1&" / "&$A$28,INDIRECT(ADDRESS(A37+5,2,1,,"JOURNAL")&":G700"),2,0)),"",VLOOKUP($A$1&" / "&$A$28,INDIRECT(ADDRESS(A37+5,2,1,,"JOURNAL")&":G700"),2,0))) -> 57 | B38: =IF($A38="","",VLOOKUP($A38,JOURNAL!$C$5:$I$1115,5,0)) -> note de frais | C38: =IF($A38="","",VLOOKUP($A38,JOURNAL!$C$5:$I$1115,2,0)) -> 45961 | D38: =IF($A38="","",VLOOKUP($A38,JOURNAL!$C$5:$I$1115,4,0)) -> Manuel Cabras | E38: =IF($A38="","",VLOOKUP($A38,JOURNAL!$C$5:$I$1115,3,0)) -> 107.6
A39: =IF(A38="","",IF(ISNA(VLOOKUP($A$1&" / "&$A$28,INDIRECT(ADDRESS(A38+5,2,1,,"JOURNAL")&":G700"),2,0)),"",VLOOKUP($A$1&" / "&$A$28,INDIRECT(ADDRESS(A38+5,2,1,,"JOURNAL")&":G700"),2,0))) -> 64 | B39: =IF($A39="","",VLOOKUP($A39,JOURNAL!$C$5:$I$1115,5,0)) -> Dépôt chalet Baleiski | C39: =IF($A39="","",VLOOKUP($A39,JOURNAL!$C$5:$I$1115,2,0)) -> 45972 | D39: =IF($A39="","",VLOOKUP($A39,JOURNAL!$C$5:$I$1115,4,0)) -> Entente intercomm. Crissier | E39: =IF($A39="","",VLOOKUP($A39,JOURNAL!$C$5:$I$1115,3,0)) -> 650
A40: =IF(A39="","",IF(ISNA(VLOOKUP($A$1&" / "&$A$28,INDIRECT(ADDRESS(A39+5,2,1,,"JOURNAL")&":G700"),2,0)),"",VLOOKUP($A$1&" / "&$A$28,INDIRECT(ADDRESS(A39+5,2,1,,"JOURNAL")&":G700"),2,0))) -> 71 | B40: =IF($A40="","",VLOOKUP($A40,JOURNAL!$C$5:$I$1115,5,0)) -> note de frais | C40: =IF($A40="","",VLOOKUP($A40,JOURNAL!$C$5:$I$1115,2,0)) -> 45978 | D40: =IF($A40="","",VLOOKUP($A40,JOURNAL!$C$5:$I$1115,4,0)) -> Gilles Rothermund | E40: =IF($A40="","",VLOOKUP($A40,JOURNAL!$C$5:$I$1115,3,0)) -> 51.5
A41: =IF(A40="","",IF(ISNA(VLOOKUP($A$1&" / "&$A$28,INDIRECT(ADDRESS(A40+5,2,1,,"JOURNAL")&":G700"),2,0)),"",VLOOKUP($A$1&" / "&$A$28,INDIRECT(ADDRESS(A40+5,2,1,,"JOURNAL")&":G700"),2,0))) -> 72 | B41: =IF($A41="","",VLOOKUP($A41,JOURNAL!$C$5:$I$1115,5,0)) -> note de frais | C41: =IF($A41="","",VLOOKUP($A41,JOURNAL!$C$5:$I$1115,2,0)) -> 45978 | D41: =IF($A41="","",VLOOKUP($A41,JOURNAL!$C$5:$I$1115,4,0)) -> Sarah Mallet | E41: =IF($A41="","",VLOOKUP($A41,JOURNAL!$C$5:$I$1115,3,0)) -> 45
A42: =IF(A41="","",IF(ISNA(VLOOKUP($A$1&" / "&$A$28,INDIRECT(ADDRESS(A41+5,2,1,,"JOURNAL")&":G700"),2,0)),"",VLOOKUP($A$1&" / "&$A$28,INDIRECT(ADDRESS(A41+5,2,1,,"JOURNAL")&":G700"),2,0))) -> 76 | B42: =IF($A42="","",VLOOKUP($A42,JOURNAL!$C$5:$I$1115,5,0)) -> 0 | C42: =IF($A42="","",VLOOKUP($A42,JOURNAL!$C$5:$I$1115,2,0)) -> 45982 | D42: =IF($A42="","",VLOOKUP($A42,JOURNAL!$C$5:$I$1115,4,0)) -> PMT CARTE Landi Nord vaudois V | E42: =IF($A42="","",VLOOKUP($A42,JOURNAL!$C$5:$I$1115,3,0)) -> 33.5
A43: =IF(A42="","",IF(ISNA(VLOOKUP($A$1&" / "&$A$28,INDIRECT(ADDRESS(A42+5,2,1,,"JOURNAL")&":G700"),2,0)),"",VLOOKUP($A$1&" / "&$A$28,INDIRECT(ADDRESS(A42+5,2,1,,"JOURNAL")&":G700"),2,0))) -> 78 | B43: =IF($A43="","",VLOOKUP($A43,JOURNAL!$C$5:$I$1115,5,0)) -> 0 | C43: =IF($A43="","",VLOOKUP($A43,JOURNAL!$C$5:$I$1115,2,0)) -> 45983 | D43: =IF($A43="","",VLOOKUP($A43,JOURNAL!$C$5:$I$1115,4,0)) -> PMT CARTE Lidl Yverdon | E43: =IF($A43="","",VLOOKUP($A43,JOURNAL!$C$5:$I$1115,3,0)) -> 46.1
A44: =IF(A43="","",IF(ISNA(VLOOKUP($A$1&" / "&$A$28,INDIRECT(ADDRESS(A43+5,2,1,,"JOURNAL")&":G700"),2,0)),"",VLOOKUP($A$1&" / "&$A$28,INDIRECT(ADDRESS(A43+5,2,1,,"JOURNAL")&":G700"),2,0))) -> 85 | B44: =IF($A44="","",VLOOKUP($A44,JOURNAL!$C$5:$I$1115,5,0)) -> 0 | C44: =IF($A44="","",VLOOKUP($A44,JOURNAL!$C$5:$I$1115,2,0)) -> 45987 | D44: =IF($A44="","",VLOOKUP($A44,JOURNAL!$C$5:$I$1115,4,0)) -> Lucas Charbonnier | E44: =IF($A44="","",VLOOKUP($A44,JOURNAL!$C$5:$I$1115,3,0)) -> 168
A45: =IF(A44="","",IF(ISNA(VLOOKUP($A$1&" / "&$A$28,INDIRECT(ADDRESS(A44+5,2,1,,"JOURNAL")&":G700"),2,0)),"",VLOOKUP($A$1&" / "&$A$28,INDIRECT(ADDRESS(A44+5,2,1,,"JOURNAL")&":G700"),2,0))) -> 86 | B45: =IF($A45="","",VLOOKUP($A45,JOURNAL!$C$5:$I$1115,5,0)) -> ??? | C45: =IF($A45="","",VLOOKUP($A45,JOURNAL!$C$5:$I$1115,2,0)) -> 45987 | D45: =IF($A45="","",VLOOKUP($A45,JOURNAL!$C$5:$I$1115,4,0)) -> Fino Resto SA | E45: =IF($A45="","",VLOOKUP($A45,JOURNAL!$C$5:$I$1115,3,0)) -> 40.2
A46: =IF(A45="","",IF(ISNA(VLOOKUP($A$1&" / "&$A$28,INDIRECT(ADDRESS(A45+5,2,1,,"JOURNAL")&":G700"),2,0)),"",VLOOKUP($A$1&" / "&$A$28,INDIRECT(ADDRESS(A45+5,2,1,,"JOURNAL")&":G700"),2,0))) -> 92 | B46: =IF($A46="","",VLOOKUP($A46,JOURNAL!$C$5:$I$1115,5,0)) -> 0 | C46: =IF($A46="","",VLOOKUP($A46,JOURNAL!$C$5:$I$1115,2,0)) -> 45989 | D46: =IF($A46="","",VLOOKUP($A46,JOURNAL!$C$5:$I$1115,4,0)) -> PMT CARTE Landi Nord vaudois V | E46: =IF($A46="","",VLOOKUP($A46,JOURNAL!$C$5:$I$1115,3,0)) -> 14.05
A47: =IF(A46="","",IF(ISNA(VLOOKUP($A$1&" / "&$A$28,INDIRECT(ADDRESS(A46+5,2,1,,"JOURNAL")&":G700"),2,0)),"",VLOOKUP($A$1&" / "&$A$28,INDIRECT(ADDRESS(A46+5,2,1,,"JOURNAL")&":G700"),2,0))) -> 95 | B47: =IF($A47="","",VLOOKUP($A47,JOURNAL!$C$5:$I$1115,5,0)) -> note de frais | C47: =IF($A47="","",VLOOKUP($A47,JOURNAL!$C$5:$I$1115,2,0)) -> 45992 | D47: =IF($A47="","",VLOOKUP($A47,JOURNAL!$C$5:$I$1115,4,0)) -> Maxime Magnenat | E47: =IF($A47="","",VLOOKUP($A47,JOURNAL!$C$5:$I$1115,3,0)) -> 370
A48: =IF(A47="","",IF(ISNA(VLOOKUP($A$1&" / "&$A$28,INDIRECT(ADDRESS(A47+5,2,1,,"JOURNAL")&":G700"),2,0)),"",VLOOKUP($A$1&" / "&$A$28,INDIRECT(ADDRESS(A47+5,2,1,,"JOURNAL")&":G700"),2,0))) -> 100 | B48: =IF($A48="","",VLOOKUP($A48,JOURNAL!$C$5:$I$1115,5,0)) -> 0 | C48: =IF($A48="","",VLOOKUP($A48,JOURNAL!$C$5:$I$1115,2,0)) -> 45993 | D48: =IF($A48="","",VLOOKUP($A48,JOURNAL!$C$5:$I$1115,4,0)) -> Maxime : PIZZAS SG 3 | E48: =IF($A48="","",VLOOKUP($A48,JOURNAL!$C$5:$I$1115,3,0)) -> 72
A49: =IF(A48="","",IF(ISNA(VLOOKUP($A$1&" / "&$A$28,INDIRECT(ADDRESS(A48+5,2,1,,"JOURNAL")&":G700"),2,0)),"",VLOOKUP($A$1&" / "&$A$28,INDIRECT(ADDRESS(A48+5,2,1,,"JOURNAL")&":G700"),2,0))) -> 138 | B49: =IF($A49="","",VLOOKUP($A49,JOURNAL!$C$5:$I$1115,5,0)) -> 0 | C49: =IF($A49="","",VLOOKUP($A49,JOURNAL!$C$5:$I$1115,2,0)) -> 46010 | D49: =IF($A49="","",VLOOKUP($A49,JOURNAL!$C$5:$I$1115,4,0)) -> Sarah : CADEAU AIDE CUISINE | E49: =IF($A49="","",VLOOKUP($A49,JOURNAL!$C$5:$I$1115,3,0)) -> 73
... A51: =IF(A50="","",IF(ISNA(VLOOKUP($A$1&" / "&$A$28,INDIRECT(ADDRESS(A50+5,2,1,,"JOURNAL")&":G700"),2,0)),"",VLOOKUP($A$1&" / "&$A$28,INDIRECT(ADDRESS(A50+5,2,1,,"JOURNAL")&":G700"),2,0))) -> 158 | B51: =IF($A51="","",VLOOKUP($A51,JOURNAL!$C$5:$I$1115,5,0)) -> 0 | C51: =IF($A51="","",VLOOKUP($A51,JOURNAL!$C$5:$I$1115,2,0)) -> 46030 | D51: =IF($A51="","",VLOOKUP($A51,JOURNAL!$C$5:$I$1115,4,0)) -> PMT CARTE ARTISANPIZZA SARL | E51: =IF($A51="","",VLOOKUP($A51,JOURNAL!$C$5:$I$1115,3,0)) -> 132
A52: {=IF(A51="","",IF(ISNA(VLOOKUP($A$1&" / "&$A$28,INDIRECT(ADDRESS(A51+5,2,1,,"JOURNAL")&":G500"),2,0)),"",VLOOKUP($A$1&" / "&$A$28,INDIRECT(ADDRESS(A51+5,2,1,,"JOURNAL")&":G500"),2,0)))} -> 169 | B52: =IF($A52="","",VLOOKUP($A52,JOURNAL!$C$5:$I$1115,5,0)) -> Avance caution baleiski | C52: =IF($A52="","",VLOOKUP($A52,JOURNAL!$C$5:$I$1115,2,0)) -> 46063 | D52: =IF($A52="","",VLOOKUP($A52,JOURNAL!$C$5:$I$1115,4,0)) -> Manuel Cabras | E52: =IF($A52="","",VLOOKUP($A52,JOURNAL!$C$5:$I$1115,3,0)) -> 400
A53: Total | E53: =SUM(E30:E52) -> 6440.7
A54: Produits
A55: N° | B55: Libellé | C55: Date | D55: En faveur de | E55: Montant
A56: =IF(ISNA(VLOOKUP($A$1&" / "&$A$54,JOURNAL!$B$5:$I$1115,2,0)),"",VLOOKUP($A$1&" / "&$A$54,JOURNAL!$B$5:$I$1115,2,0)) -> 31 | B56: =IF($A56="","",VLOOKUP($A56,JOURNAL!$C$5:$I$1115,5,0)) -> SG : Pizzas + boissons | C56: =IF($A56="","",VLOOKUP($A56,JOURNAL!$C$5:$I$1115,2,0)) -> 45932 | D56: =IF($A56="","",VLOOKUP($A56,JOURNAL!$C$5:$I$1115,4,0)) -> BLV | E56: =IF($A56="","",VLOOKUP($A56,JOURNAL!$C$5:$I$1115,3,0)) -> 156.9
A57: =IF(A56="","",IF(ISNA(VLOOKUP($A$1&" / "&$A$54,INDIRECT(ADDRESS(A56+5,2,1,,"JOURNAL")&":G700"),2,0)),"",VLOOKUP($A$1&" / "&$A$54,INDIRECT(ADDRESS(A56+5,2,1,,"JOURNAL")&":G700"),2,0))) -> 39 | B57: =IF($A57="","",VLOOKUP($A57,JOURNAL!$C$5:$I$1115,5,0)) -> Remboursement caution GM | C57: =IF($A57="","",VLOOKUP($A57,JOURNAL!$C$5:$I$1115,2,0)) -> 45943 | D57: =IF($A57="","",VLOOKUP($A57,JOURNAL!$C$5:$I$1115,4,0)) -> BLV | E57: =IF($A57="","",VLOOKUP($A57,JOURNAL!$C$5:$I$1115,3,0)) -> 192
A58: =IF(A57="","",IF(ISNA(VLOOKUP($A$1&" / "&$A$54,INDIRECT(ADDRESS(A57+5,2,1,,"JOURNAL")&":G700"),2,0)),"",VLOOKUP($A$1&" / "&$A$54,INDIRECT(ADDRESS(A57+5,2,1,,"JOURNAL")&":G700"),2,0))) -> 41 | B58: =IF($A58="","",VLOOKUP($A58,JOURNAL!$C$5:$I$1115,5,0)) -> Provenance : Etu'sounds | C58: =IF($A58="","",VLOOKUP($A58,JOURNAL!$C$5:$I$1115,2,0)) -> 45951 | D58: =IF($A58="","",VLOOKUP($A58,JOURNAL!$C$5:$I$1115,4,0)) -> BLV | E58: =IF($A58="","",VLOOKUP($A58,JOURNAL!$C$5:$I$1115,3,0)) -> 67
A59: =IF(A58="","",IF(ISNA(VLOOKUP($A$1&" / "&$A$54,INDIRECT(ADDRESS(A58+5,2,1,,"JOURNAL")&":G700"),2,0)),"",VLOOKUP($A$1&" / "&$A$54,INDIRECT(ADDRESS(A58+5,2,1,,"JOURNAL")&":G700"),2,0))) -> 62 | B59: =IF($A59="","",VLOOKUP($A59,JOURNAL!$C$5:$I$1115,5,0)) -> Depôt GM cheseaux pt 2 | C59: =IF($A59="","",VLOOKUP($A59,JOURNAL!$C$5:$I$1115,2,0)) -> 45965 | D59: =IF($A59="","",VLOOKUP($A59,JOURNAL!$C$5:$I$1115,4,0)) -> BLV | E59: =IF($A59="","",VLOOKUP($A59,JOURNAL!$C$5:$I$1115,3,0)) -> 8
A60: =IF(A59="","",IF(ISNA(VLOOKUP($A$1&" / "&$A$54,INDIRECT(ADDRESS(A59+5,2,1,,"JOURNAL")&":G700"),2,0)),"",VLOOKUP($A$1&" / "&$A$54,INDIRECT(ADDRESS(A59+5,2,1,,"JOURNAL")&":G700"),2,0))) -> 159 | B60: =IF($A60="","",VLOOKUP($A60,JOURNAL!$C$5:$I$1115,5,0)) -> entrée twint | C60: =IF($A60="","",VLOOKUP($A60,JOURNAL!$C$5:$I$1115,2,0)) -> 46030 | D60: =IF($A60="","",VLOOKUP($A60,JOURNAL!$C$5:$I$1115,4,0)) -> BLV | E60: =IF($A60="","",VLOOKUP($A60,JOURNAL!$C$5:$I$1115,3,0)) -> 97.7
A61: =IF(A60="","",IF(ISNA(VLOOKUP($A$1&" / "&$A$54,INDIRECT(ADDRESS(A60+5,2,1,,"JOURNAL")&":G700"),2,0)),"",VLOOKUP($A$1&" / "&$A$54,INDIRECT(ADDRESS(A60+5,2,1,,"JOURNAL")&":G700"),2,0))) -> 194 | B61: =IF($A61="","",VLOOKUP($A61,JOURNAL!$C$5:$I$1115,5,0)) -> Entrées SG | C61: =IF($A61="","",VLOOKUP($A61,JOURNAL!$C$5:$I$1115,2,0)) -> 46086 | D61: =IF($A61="","",VLOOKUP($A61,JOURNAL!$C$5:$I$1115,4,0)) -> BLV | E61: =IF($A61="","",VLOOKUP($A61,JOURNAL!$C$5:$I$1115,3,0)) -> 8.88
A62: =IF(A61="","",IF(ISNA(VLOOKUP($A$1&" / "&$A$54,INDIRECT(ADDRESS(A61+5,2,1,,"JOURNAL")&":G700"),2,0)),"",VLOOKUP($A$1&" / "&$A$54,INDIRECT(ADDRESS(A61+5,2,1,,"JOURNAL")&":G700"),2,0))) -> 195 | B62: =IF($A62="","",VLOOKUP($A62,JOURNAL!$C$5:$I$1115,5,0)) -> Entrées SG | C62: =IF($A62="","",VLOOKUP($A62,JOURNAL!$C$5:$I$1115,2,0)) -> 46086 | D62: =IF($A62="","",VLOOKUP($A62,JOURNAL!$C$5:$I$1115,4,0)) -> BLV | E62: =IF($A62="","",VLOOKUP($A62,JOURNAL!$C$5:$I$1115,3,0)) -> 88.81
A63: =IF(A62="","",IF(ISNA(VLOOKUP($A$1&" / "&$A$54,INDIRECT(ADDRESS(A62+5,2,1,,"JOURNAL")&":G700"),2,0)),"",VLOOKUP($A$1&" / "&$A$54,INDIRECT(ADDRESS(A62+5,2,1,,"JOURNAL")&":G700"),2,0))) -> 196 | B63: =IF($A63="","",VLOOKUP($A63,JOURNAL!$C$5:$I$1115,5,0)) -> Entrées SG | C63: =IF($A63="","",VLOOKUP($A63,JOURNAL!$C$5:$I$1115,2,0)) -> 46086 | D63: =IF($A63="","",VLOOKUP($A63,JOURNAL!$C$5:$I$1115,4,0)) -> BLV | E63: =IF($A63="","",VLOOKUP($A63,JOURNAL!$C$5:$I$1115,3,0)) -> 40.46
A64: =IF(A63="","",IF(ISNA(VLOOKUP($A$1&" / "&$A$54,INDIRECT(ADDRESS(A63+5,2,1,,"JOURNAL")&":G700"),2,0)),"",VLOOKUP($A$1&" / "&$A$54,INDIRECT(ADDRESS(A63+5,2,1,,"JOURNAL")&":G700"),2,0))) | B64: =IF($A64="","",VLOOKUP($A64,JOURNAL!$C$5:$I$1115,5,0)) | C64: =IF($A64="","",VLOOKUP($A64,JOURNAL!$C$5:$I$1115,2,0)) | D64: =IF($A64="","",VLOOKUP($A64,JOURNAL!$C$5:$I$1115,4,0)) | E64: =IF($A64="","",VLOOKUP($A64,JOURNAL!$C$5:$I$1115,3,0))
A65: =IF(A64="","",IF(ISNA(VLOOKUP($A$1&" / "&$A$54,INDIRECT(ADDRESS(A64+5,2,1,,"JOURNAL")&":G700"),2,0)),"",VLOOKUP($A$1&" / "&$A$54,INDIRECT(ADDRESS(A64+5,2,1,,"JOURNAL")&":G700"),2,0))) | B65: =IF($A65="","",VLOOKUP($A65,JOURNAL!$C$5:$I$1115,5,0)) | C65: =IF($A65="","",VLOOKUP($A65,JOURNAL!$C$5:$I$1115,2,0)) | D65: =IF($A65="","",VLOOKUP($A65,JOURNAL!$C$5:$I$1115,4,0)) | E65: =IF($A65="","",VLOOKUP($A65,JOURNAL!$C$5:$I$1115,3,0))
A66: =IF(A65="","",IF(ISNA(VLOOKUP($A$1&" / "&$A$54,INDIRECT(ADDRESS(A65+5,2,1,,"JOURNAL")&":G700"),2,0)),"",VLOOKUP($A$1&" / "&$A$54,INDIRECT(ADDRESS(A65+5,2,1,,"JOURNAL")&":G700"),2,0))) | B66: =IF($A66="","",VLOOKUP($A66,JOURNAL!$C$5:$I$1115,5,0)) | C66: =IF($A66="","",VLOOKUP($A66,JOURNAL!$C$5:$I$1115,2,0)) | D66: =IF($A66="","",VLOOKUP($A66,JOURNAL!$C$5:$I$1115,4,0)) | E66: =IF($A66="","",VLOOKUP($A66,JOURNAL!$C$5:$I$1115,3,0))
A67: =IF(A66="","",IF(ISNA(VLOOKUP($A$1&" / "&$A$54,INDIRECT(ADDRESS(A66+5,2,1,,"JOURNAL")&":G700"),2,0)),"",VLOOKUP($A$1&" / "&$A$54,INDIRECT(ADDRESS(A66+5,2,1,,"JOURNAL")&":G700"),2,0))) | B67: =IF($A67="","",VLOOKUP($A67,JOURNAL!$C$5:$I$1115,5,0)) | C67: =IF($A67="","",VLOOKUP($A67,JOURNAL!$C$5:$I$1115,2,0)) | D67: =IF($A67="","",VLOOKUP($A67,JOURNAL!$C$5:$I$1115,4,0)) | E67: =IF($A67="","",VLOOKUP($A67,JOURNAL!$C$5:$I$1115,3,0))
A68: =IF(A67="","",IF(ISNA(VLOOKUP($A$1&" / "&$A$54,INDIRECT(ADDRESS(A67+5,2,1,,"JOURNAL")&":G700"),2,0)),"",VLOOKUP($A$1&" / "&$A$54,INDIRECT(ADDRESS(A67+5,2,1,,"JOURNAL")&":G700"),2,0))) | B68: =IF($A68="","",VLOOKUP($A68,JOURNAL!$C$5:$I$1115,5,0)) | C68: =IF($A68="","",VLOOKUP($A68,JOURNAL!$C$5:$I$1115,2,0)) | D68: =IF($A68="","",VLOOKUP($A68,JOURNAL!$C$5:$I$1115,4,0)) | E68: =IF($A68="","",VLOOKUP($A68,JOURNAL!$C$5:$I$1115,3,0))
... A77: =IF(A76="","",IF(ISNA(VLOOKUP($A$1&" / "&$A$54,INDIRECT(ADDRESS(A76+5,2,1,,"JOURNAL")&":G700"),2,0)),"",VLOOKUP($A$1&" / "&$A$54,INDIRECT(ADDRESS(A76+5,2,1,,"JOURNAL")&":G700"),2,0))) | B77: =IF($A77="","",VLOOKUP($A77,JOURNAL!$C$5:$I$1115,5,0)) | C77: =IF($A77="","",VLOOKUP($A77,JOURNAL!$C$5:$I$1115,2,0)) | D77: =IF($A77="","",VLOOKUP($A77,JOURNAL!$C$5:$I$1115,4,0)) | E77: =IF($A77="","",VLOOKUP($A77,JOURNAL!$C$5:$I$1115,3,0))
A78: {=IF(A77="","",IF(ISNA(VLOOKUP($A$1&" / "&$A$54,INDIRECT(ADDRESS(A77+5,2,1,,"JOURNAL")&":G500"),2,0)),"",VLOOKUP($A$1&" / "&$A$54,INDIRECT(ADDRESS(A77+5,2,1,,"JOURNAL")&":G500"),2,0)))} | B78: =IF($A78="","",VLOOKUP($A78,JOURNAL!$C$5:$I$1115,5,0)) | C78: =IF($A78="","",VLOOKUP($A78,JOURNAL!$C$5:$I$1115,2,0)) | D78: =IF($A78="","",VLOOKUP($A78,JOURNAL!$C$5:$I$1115,4,0)) | E78: =IF($A78="","",VLOOKUP($A78,JOURNAL!$C$5:$I$1115,3,0))
A79: Total | E79: =SUM(E56:E62) -> 619.29

Sheet COMMUNICATION
A1: COMMUNICATION
A3: BUDGET
A4: Charges
A5: Mois de facturation | B5: Libellé | E5: Montant
A7: Novembre | B7: Stickers Baleinev édition 2026 Online Printers - étiquettes adhésives, ø 5cm, 90g/m² papier blanc structuré, 2000 pièces | E7: 155
A8: Décembre
A9: Fevrier | B9: Affiches festival, A2, impression recto seul, 115g/m² papier affiche (dos bleu), 500 impressions | E9: 145
A10: Fevrier | B10: Flyers festival, A5, impression recto/verso, 250g/m² papier couché, 1'000 impressions | E10: 65
A11: Fevrier | B11: Bâches PVC affichées à l'écoles, 300 x 150 cm, 500g/m² PVC mat, 2 bâches, Options supplémentaires ourlet et oeillets tout autour | E11: 190
A12: Fevrier | B12: Bâches PVC entrée de la ville, 400 x 50 cm, 500g/m² PVC mat, 2 bâches, Options supplémentaires ourlet et oeillets tout autour | E12: 120
A13: Avril | B13: Mise en place des bâches | E13: 400
A14: Fevrier | B14: T-shirts, hoodies, autre vêtement | E14: 3000
A15: Mars | B15: Concours réseaux sociaux 4 billets à gagner | E15: 100
A16: Septembre | B16: Site web | E16: 37
A17: Fevrier | B17: Social Media Marketing (Publicités en ligne) | E17: 2000 | G17: Voir campagne : mieux cibler (- de thune + de renta)
A18: Fevrier | B18: Goodies (Briquets) | E18: 0
A19: Janvier | B19: Pixartprinting bâche Travys/sponsors grande scène (présidence PV Travys) | E19: 350
A20: Total | E20: =SUM(E6:E19) -> 6562
A21: Produits
A22: Mois de facturation | B22: Libellé | E22: Montant
A23: Avril | B23: T-shirts, hoodies, autres vetements | E23: 2500
A27: Total | E27: =SUM(E23:E26) -> 2500
A29: COMPTABILITE
A30: Charges
A31: N° | B31: Libellé | C31: Date | D31: En faveur de | E31: Montant
A32: =IF(ISNA(VLOOKUP($A$1&" / "&$A$30,JOURNAL!$B$5:$I$1115,2,0)),"",VLOOKUP($A$1&" / "&$A$30,JOURNAL!$B$5:$I$277,2,0)) | B32: =IF($A32="","",VLOOKUP($A32,JOURNAL!$C$5:$I$1115,5,0)) | C32: =IF($A32="","",VLOOKUP($A32,JOURNAL!$C$5:$I$1115,2,0)) | D32: =IF($A32="","",VLOOKUP($A32,JOURNAL!$C$5:$I$1115,4,0)) | E32: =IF($A32="","",VLOOKUP($A32,JOURNAL!$C$5:$I$1115,3,0))
A33: =IF(A32="","",IF(ISNA(VLOOKUP($A$1&" / "&$A$30,INDIRECT(ADDRESS(A32+5,2,1,,"JOURNAL")&":G500"),2,0)),"",VLOOKUP($A$1&" / "&$A$30,INDIRECT(ADDRESS(A32+5,2,1,,"JOURNAL")&":G500"),2,0))) | B33: =IF($A33="","",VLOOKUP($A33,JOURNAL!$C$5:$I$1115,5,0)) | C33: =IF($A33="","",VLOOKUP($A33,JOURNAL!$C$5:$I$1115,2,0)) | D33: =IF($A33="","",VLOOKUP($A33,JOURNAL!$C$5:$I$1115,4,0)) | E33: =IF($A33="","",VLOOKUP($A33,JOURNAL!$C$5:$I$1115,3,0))
A34: =IF(A33="","",IF(ISNA(VLOOKUP($A$1&" / "&$A$30,INDIRECT(ADDRESS(A33+5,2,1,,"JOURNAL")&":G500"),2,0)),"",VLOOKUP($A$1&" / "&$A$30,INDIRECT(ADDRESS(A33+5,2,1,,"JOURNAL")&":G500"),2,0))) | B34: =IF($A34="","",VLOOKUP($A34,JOURNAL!$C$5:$I$1115,5,0)) | C34: =IF($A34="","",VLOOKUP($A34,JOURNAL!$C$5:$I$1115,2,0)) | D34: =IF($A34="","",VLOOKUP($A34,JOURNAL!$C$5:$I$1115,4,0)) | E34: =IF($A34="","",VLOOKUP($A34,JOURNAL!$C$5:$I$1115,3,0))
A35: =IF(A34="","",IF(ISNA(VLOOKUP($A$1&" / "&$A$30,INDIRECT(ADDRESS(A34+5,2,1,,"JOURNAL")&":G500"),2,0)),"",VLOOKUP($A$1&" / "&$A$30,INDIRECT(ADDRESS(A34+5,2,1,,"JOURNAL")&":G500"),2,0))) | B35: =IF($A35="","",VLOOKUP($A35,JOURNAL!$C$5:$I$1115,5,0)) | C35: =IF($A35="","",VLOOKUP($A35,JOURNAL!$C$5:$I$1115,2,0)) | D35: =IF($A35="","",VLOOKUP($A35,JOURNAL!$C$5:$I$1115,4,0)) | E35: =IF($A35="","",VLOOKUP($A35,JOURNAL!$C$5:$I$1115,3,0))
A36: =IF(A35="","",IF(ISNA(VLOOKUP($A$1&" / "&$A$30,INDIRECT(ADDRESS(A35+5,2,1,,"JOURNAL")&":G500"),2,0)),"",VLOOKUP($A$1&" / "&$A$30,INDIRECT(ADDRESS(A35+5,2,1,,"JOURNAL")&":G500"),2,0))) | B36: =IF($A36="","",VLOOKUP($A36,JOURNAL!$C$5:$I$1115,5,0)) | C36: =IF($A36="","",VLOOKUP($A36,JOURNAL!$C$5:$I$1115,2,0)) | D36: =IF($A36="","",VLOOKUP($A36,JOURNAL!$C$5:$I$1115,4,0)) | E36: =IF($A36="","",VLOOKUP($A36,JOURNAL!$C$5:$I$1115,3,0))
A37: =IF(A36="","",IF(ISNA(VLOOKUP($A$1&" / "&$A$30,INDIRECT(ADDRESS(A36+5,2,1,,"JOURNAL")&":G500"),2,0)),"",VLOOKUP($A$1&" / "&$A$30,INDIRECT(ADDRESS(A36+5,2,1,,"JOURNAL")&":G500"),2,0))) | B37: =IF($A37="","",VLOOKUP($A37,JOURNAL!$C$5:$I$1115,5,0)) | C37: =IF($A37="","",VLOOKUP($A37,JOURNAL!$C$5:$I$1115,2,0)) | D37: =IF($A37="","",VLOOKUP($A37,JOURNAL!$C$5:$I$1115,4,0)) | E37: =IF($A37="","",VLOOKUP($A37,JOURNAL!$C$5:$I$1115,3,0))
A38: =IF(A37="","",IF(ISNA(VLOOKUP($A$1&" / "&$A$30,INDIRECT(ADDRESS(A37+5,2,1,,"JOURNAL")&":G500"),2,0)),"",VLOOKUP($A$1&" / "&$A$30,INDIRECT(ADDRESS(A37+5,2,1,,"JOURNAL")&":G500"),2,0))) | B38: =IF($A38="","",VLOOKUP($A38,JOURNAL!$C$5:$I$1115,5,0)) | C38: =IF($A38="","",VLOOKUP($A38,JOURNAL!$C$5:$I$1115,2,0)) | D38: =IF($A38="","",VLOOKUP($A38,JOURNAL!$C$5:$I$1115,4,0)) | E38: =IF($A38="","",VLOOKUP($A38,JOURNAL!$C$5:$I$1115,3,0))
A39: =IF(A38="","",IF(ISNA(VLOOKUP($A$1&" / "&$A$30,INDIRECT(ADDRESS(A38+5,2,1,,"JOURNAL")&":G500"),2,0)),"",VLOOKUP($A$1&" / "&$A$30,INDIRECT(ADDRESS(A38+5,2,1,,"JOURNAL")&":G500"),2,0))) | B39: =IF($A39="","",VLOOKUP($A39,JOURNAL!$C$5:$I$1115,5,0)) | C39: =IF($A39="","",VLOOKUP($A39,JOURNAL!$C$5:$I$1115,2,0)) | D39: =IF($A39="","",VLOOKUP($A39,JOURNAL!$C$5:$I$1115,4,0)) | E39: =IF($A39="","",VLOOKUP($A39,JOURNAL!$C$5:$I$1115,3,0))
A40: =IF(A39="","",IF(ISNA(VLOOKUP($A$1&" / "&$A$30,INDIRECT(ADDRESS(A39+5,2,1,,"JOURNAL")&":G500"),2,0)),"",VLOOKUP($A$1&" / "&$A$30,INDIRECT(ADDRESS(A39+5,2,1,,"JOURNAL")&":G500"),2,0))) | B40: =IF($A40="","",VLOOKUP($A40,JOURNAL!$C$5:$I$1115,5,0)) | C40: =IF($A40="","",VLOOKUP($A40,JOURNAL!$C$5:$I$1115,2,0)) | D40: =IF($A40="","",VLOOKUP($A40,JOURNAL!$C$5:$I$1115,4,0)) | E40: =IF($A40="","",VLOOKUP($A40,JOURNAL!$C$5:$I$1115,3,0))
A41: =IF(A40="","",IF(ISNA(VLOOKUP($A$1&" / "&$A$30,INDIRECT(ADDRESS(A40+5,2,1,,"JOURNAL")&":G700"),2,0)),"",VLOOKUP($A$1&" / "&$A$30,INDIRECT(ADDRESS(A40+5,2,1,,"JOURNAL")&":G700"),2,0))) | B41: =IF($A41="","",VLOOKUP($A41,JOURNAL!$C$5:$I$1115,5,0)) | C41: =IF($A41="","",VLOOKUP($A41,JOURNAL!$C$5:$I$1115,2,0)) | D41: =IF($A41="","",VLOOKUP($A41,JOURNAL!$C$5:$I$1115,4,0)) | E41: =IF($A41="","",VLOOKUP($A41,JOURNAL!$C$5:$I$1115,3,0))
A42: =IF(A41="","",IF(ISNA(VLOOKUP($A$1&" / "&$A$30,INDIRECT(ADDRESS(A41+5,2,1,,"JOURNAL")&":G700"),2,0)),"",VLOOKUP($A$1&" / "&$A$30,INDIRECT(ADDRESS(A41+5,2,1,,"JOURNAL")&":G700"),2,0))) | B42: =IF($A42="","",VLOOKUP($A42,JOURNAL!$C$5:$I$1115,5,0)) | C42: =IF($A42="","",VLOOKUP($A42,JOURNAL!$C$5:$I$1115,2,0)) | D42: =IF($A42="","",VLOOKUP($A42,JOURNAL!$C$5:$I$1115,4,0)) | E42: =IF($A42="","",VLOOKUP($A42,JOURNAL!$C$5:$I$1115,3,0))
A43: =IF(A42="","",IF(ISNA(VLOOKUP($A$1&" / "&$A$30,INDIRECT(ADDRESS(A42+5,2,1,,"JOURNAL")&":G700"),2,0)),"",VLOOKUP($A$1&" / "&$A$30,INDIRECT(ADDRESS(A42+5,2,1,,"JOURNAL")&":G700"),2,0))) | B43: =IF($A43="","",VLOOKUP($A43,JOURNAL!$C$5:$I$1115,5,0)) | C43: =IF($A43="","",VLOOKUP($A43,JOURNAL!$C$5:$I$1115,2,0)) | D43: =IF($A43="","",VLOOKUP($A43,JOURNAL!$C$5:$I$1115,4,0)) | E43: =IF($A43="","",VLOOKUP($A43,JOURNAL!$C$5:$I$1115,3,0))
A44: =IF(A43="","",IF(ISNA(VLOOKUP($A$1&" / "&$A$30,INDIRECT(ADDRESS(A43+5,2,1,,"JOURNAL")&":G700"),2,0)),"",VLOOKUP($A$1&" / "&$A$30,INDIRECT(ADDRESS(A43+5,2,1,,"JOURNAL")&":G700"),2,0))) | B44: =IF($A44="","",VLOOKUP($A44,JOURNAL!$C$5:$I$1115,5,0)) | C44: =IF($A44="","",VLOOKUP($A44,JOURNAL!$C$5:$I$1115,2,0)) | D44: =IF($A44="","",VLOOKUP($A44,JOURNAL!$C$5:$I$1115,4,0)) | E44: =IF($A44="","",VLOOKUP($A44,JOURNAL!$C$5:$I$1115,3,0))
A45: =IF(A44="","",IF(ISNA(VLOOKUP($A$1&" / "&$A$30,INDIRECT(ADDRESS(A44+5,2,1,,"JOURNAL")&":G700"),2,0)),"",VLOOKUP($A$1&" / "&$A$30,INDIRECT(ADDRESS(A44+5,2,1,,"JOURNAL")&":G700"),2,0))) | B45: =IF($A45="","",VLOOKUP($A45,JOURNAL!$C$5:$I$1115,5,0)) | C45: =IF($A45="","",VLOOKUP($A45,JOURNAL!$C$5:$I$1115,2,0)) | D45: =IF($A45="","",VLOOKUP($A45,JOURNAL!$C$5:$I$1115,4,0)) | E45: =IF($A45="","",VLOOKUP($A45,JOURNAL!$C$5:$I$1115,3,0))
A46: =IF(A45="","",IF(ISNA(VLOOKUP($A$1&" / "&$A$30,INDIRECT(ADDRESS(A45+5,2,1,,"JOURNAL")&":G700"),2,0)),"",VLOOKUP($A$1&" / "&$A$30,INDIRECT(ADDRESS(A45+5,2,1,,"JOURNAL")&":G700"),2,0))) | B46: =IF($A46="","",VLOOKUP($A46,JOURNAL!$C$5:$I$1115,5,0)) | C46: =IF($A46="","",VLOOKUP($A46,JOURNAL!$C$5:$I$1115,2,0)) | D46: =IF($A46="","",VLOOKUP($A46,JOURNAL!$C$5:$I$1115,4,0)) | E46: =IF($A46="","",VLOOKUP($A46,JOURNAL!$C$5:$I$1115,3,0))
A47: =IF(A46="","",IF(ISNA(VLOOKUP($A$1&" / "&$A$30,INDIRECT(ADDRESS(A46+5,2,1,,"JOURNAL")&":G700"),2,0)),"",VLOOKUP($A$1&" / "&$A$30,INDIRECT(ADDRESS(A46+5,2,1,,"JOURNAL")&":G700"),2,0))) | B47: =IF($A47="","",VLOOKUP($A47,JOURNAL!$C$5:$I$1115,5,0)) | C47: =IF($A47="","",VLOOKUP($A47,JOURNAL!$C$5:$I$1115,2,0)) | D47: =IF($A47="","",VLOOKUP($A47,JOURNAL!$C$5:$I$1115,4,0)) | E47: =IF($A47="","",VLOOKUP($A47,JOURNAL!$C$5:$I$1115,3,0))
A48: =IF(A47="","",IF(ISNA(VLOOKUP($A$1&" / "&$A$30,INDIRECT(ADDRESS(A47+5,2,1,,"JOURNAL")&":G700"),2,0)),"",VLOOKUP($A$1&" / "&$A$30,INDIRECT(ADDRESS(A47+5,2,1,,"JOURNAL")&":G700"),2,0))) | B48: =IF($A48="","",VLOOKUP($A48,JOURNAL!$C$5:$I$1115,5,0)) | C48: =IF($A48="","",VLOOKUP($A48,JOURNAL!$C$5:$I$1115,2,0)) | D48: =IF($A48="","",VLOOKUP($A48,JOURNAL!$C$5:$I$1115,4,0)) | E48: =IF($A48="","",VLOOKUP($A48,JOURNAL!$C$5:$I$1115,3,0))
A49: =IF(A48="","",IF(ISNA(VLOOKUP($A$1&" / "&$A$30,INDIRECT(ADDRESS(A48+5,2,1,,"JOURNAL")&":G700"),2,0)),"",VLOOKUP($A$1&" / "&$A$30,INDIRECT(ADDRESS(A48+5,2,1,,"JOURNAL")&":G700"),2,0))) | B49: =IF($A49="","",VLOOKUP($A49,JOURNAL!$C$5:$I$1115,5,0)) | C49: =IF($A49="","",VLOOKUP($A49,JOURNAL!$C$5:$I$1115,2,0)) | D49: =IF($A49="","",VLOOKUP($A49,JOURNAL!$C$5:$I$1115,4,0)) | E49: =IF($A49="","",VLOOKUP($A49,JOURNAL!$C$5:$I$1115,3,0))
A50: =IF(A49="","",IF(ISNA(VLOOKUP($A$1&" / "&$A$30,INDIRECT(ADDRESS(A49+5,2,1,,"JOURNAL")&":G700"),2,0)),"",VLOOKUP($A$1&" / "&$A$30,INDIRECT(ADDRESS(A49+5,2,1,,"JOURNAL")&":G700"),2,0))) | B50: =IF($A50="","",VLOOKUP($A50,JOURNAL!$C$5:$I$1115,5,0)) | C50: =IF($A50="","",VLOOKUP($A50,JOURNAL!$C$5:$I$1115,2,0)) | D50: =IF($A50="","",VLOOKUP($A50,JOURNAL!$C$5:$I$1115,4,0)) | E50: =IF($A50="","",VLOOKUP($A50,JOURNAL!$C$5:$I$1115,3,0))
A51: =IF(A50="","",IF(ISNA(VLOOKUP($A$1&" / "&$A$30,INDIRECT(ADDRESS(A50+5,2,1,,"JOURNAL")&":G700"),2,0)),"",VLOOKUP($A$1&" / "&$A$30,INDIRECT(ADDRESS(A50+5,2,1,,"JOURNAL")&":G700"),2,0))) | B51: =IF($A51="","",VLOOKUP($A51,JOURNAL!$C$5:$I$1115,5,0)) | C51: =IF($A51="","",VLOOKUP($A51,JOURNAL!$C$5:$I$1115,2,0)) | D51: =IF($A51="","",VLOOKUP($A51,JOURNAL!$C$5:$I$1115,4,0)) | E51: =IF($A51="","",VLOOKUP($A51,JOURNAL!$C$5:$I$1115,3,0))
A52: =IF(A51="","",IF(ISNA(VLOOKUP($A$1&" / "&$A$30,INDIRECT(ADDRESS(A51+5,2,1,,"JOURNAL")&":G700"),2,0)),"",VLOOKUP($A$1&" / "&$A$30,INDIRECT(ADDRESS(A51+5,2,1,,"JOURNAL")&":G700"),2,0))) | B52: =IF($A52="","",VLOOKUP($A52,JOURNAL!$C$5:$I$1115,5,0)) | C52: =IF($A52="","",VLOOKUP($A52,JOURNAL!$C$5:$I$1115,2,0)) | D52: =IF($A52="","",VLOOKUP($A52,JOURNAL!$C$5:$I$1115,4,0)) | E52: =IF($A52="","",VLOOKUP($A52,JOURNAL!$C$5:$I$1115,3,0))
... A54: =IF(A53="","",IF(ISNA(VLOOKUP($A$1&" / "&$A$30,INDIRECT(ADDRESS(A53+5,2,1,,"JOURNAL")&":G700"),2,0)),"",VLOOKUP($A$1&" / "&$A$30,INDIRECT(ADDRESS(A53+5,2,1,,"JOURNAL")&":G700"),2,0))) | B54: =IF($A54="","",VLOOKUP($A54,JOURNAL!$C$5:$I$1115,5,0)) | C54: =IF($A54="","",VLOOKUP($A54,JOURNAL!$C$5:$I$1115,2,0)) | D54: =IF($A54="","",VLOOKUP($A54,JOURNAL!$C$5:$I$1115,4,0)) | E54: =IF($A54="","",VLOOKUP($A54,JOURNAL!$C$5:$I$1115,3,0))
A55: {=IF(A54="","",IF(ISNA(VLOOKUP($A$1&" / "&$A$30,INDIRECT(ADDRESS(A54+5,2,1,,"JOURNAL")&":G500"),2,0)),"",VLOOKUP($A$1&" / "&$A$30,INDIRECT(ADDRESS(A54+5,2,1,,"JOURNAL")&":G500"),2,0)))} | B55: =IF($A55="","",VLOOKUP($A55,JOURNAL!$C$5:$I$1115,5,0)) | C55: =IF($A55="","",VLOOKUP($A55,JOURNAL!$C$5:$I$1115,2,0)) | D55: =IF($A55="","",VLOOKUP($A55,JOURNAL!$C$5:$I$1115,4,0)) | E55: =IF($A55="","",VLOOKUP($A55,JOURNAL!$C$5:$I$1115,3,0))
A56: Total | E56: =SUM(E32:E55) -> 0
A57: Produits
A58: N° | B58: Libellé | C58: Date | D58: En faveur de | E58: Montant
A59: =IF(ISNA(VLOOKUP($A$1&" / "&$A$57,JOURNAL!$B$5:$I$1115,2,0)),"",VLOOKUP($A$1&" / "&$A$57,JOURNAL!$B$5:$I$1115,2,0)) | B59: =IF($A59="","",VLOOKUP($A59,JOURNAL!$C$5:$I$1115,5,0)) | C59: =IF($A59="","",VLOOKUP($A59,JOURNAL!$C$5:$I$1115,2,0)) | D59: =IF($A59="","",VLOOKUP($A59,JOURNAL!$C$5:$I$1115,4,0)) | E59: =IF($A59="","",VLOOKUP($A59,JOURNAL!$C$5:$I$1003,3,0))
A60: =IF(A59="","",IF(ISNA(VLOOKUP($A$1&" / "&$A$57,INDIRECT(ADDRESS(A59+5,2,1,,"JOURNAL")&":G500"),2,0)),"",VLOOKUP($A$1&" / "&$A$57,INDIRECT(ADDRESS(A59+5,2,1,,"JOURNAL")&":G500"),2,0))) | B60: =IF($A60="","",VLOOKUP($A60,JOURNAL!$C$5:$I$1115,5,0)) | C60: =IF($A60="","",VLOOKUP($A60,JOURNAL!$C$5:$I$1115,2,0)) | D60: =IF($A60="","",VLOOKUP($A60,JOURNAL!$C$5:$I$1115,4,0)) | E60: =IF($A60="","",VLOOKUP($A60,JOURNAL!$C$5:$I$1115,3,0))
A61: =IF(A60="","",IF(ISNA(VLOOKUP($A$1&" / "&$A$57,INDIRECT(ADDRESS(A60+5,2,1,,"JOURNAL")&":G500"),2,0)),"",VLOOKUP($A$1&" / "&$A$57,INDIRECT(ADDRESS(A60+5,2,1,,"JOURNAL")&":G500"),2,0))) | B61: =IF($A61="","",VLOOKUP($A61,JOURNAL!$C$5:$I$1115,5,0)) | C61: =IF($A61="","",VLOOKUP($A61,JOURNAL!$C$5:$I$1115,2,0)) | D61: =IF($A61="","",VLOOKUP($A61,JOURNAL!$C$5:$I$1115,4,0)) | E61: =IF($A61="","",VLOOKUP($A61,JOURNAL!$C$5:$I$1115,3,0))
A62: =IF(A61="","",IF(ISNA(VLOOKUP($A$1&" / "&$A$57,INDIRECT(ADDRESS(A61+5,2,1,,"JOURNAL")&":G500"),2,0)),"",VLOOKUP($A$1&" / "&$A$57,INDIRECT(ADDRESS(A61+5,2,1,,"JOURNAL")&":G500"),2,0))) | B62: =IF($A62="","",VLOOKUP($A62,JOURNAL!$C$5:$I$1115,5,0)) | C62: =IF($A62="","",VLOOKUP($A62,JOURNAL!$C$5:$I$1115,2,0)) | D62: =IF($A62="","",VLOOKUP($A62,JOURNAL!$C$5:$I$1115,4,0)) | E62: =IF($A62="","",VLOOKUP($A62,JOURNAL!$C$5:$I$1115,3,0))
A63: =IF(A62="","",IF(ISNA(VLOOKUP($A$1&" / "&$A$57,INDIRECT(ADDRESS(A62+5,2,1,,"JOURNAL")&":G500"),2,0)),"",VLOOKUP($A$1&" / "&$A$57,INDIRECT(ADDRESS(A62+5,2,1,,"JOURNAL")&":G500"),2,0))) | B63: =IF($A63="","",VLOOKUP($A63,JOURNAL!$C$5:$I$1115,5,0)) | C63: =IF($A63="","",VLOOKUP($A63,JOURNAL!$C$5:$I$1115,2,0)) | D63: =IF($A63="","",VLOOKUP($A63,JOURNAL!$C$5:$I$1115,4,0)) | E63: =IF($A63="","",VLOOKUP($A63,JOURNAL!$C$5:$I$1115,3,0))
A64: =IF(A63="","",IF(ISNA(VLOOKUP($A$1&" / "&$A$57,INDIRECT(ADDRESS(A63+5,2,1,,"JOURNAL")&":G500"),2,0)),"",VLOOKUP($A$1&" / "&$A$57,INDIRECT(ADDRESS(A63+5,2,1,,"JOURNAL")&":G500"),2,0))) | B64: =IF($A64="","",VLOOKUP($A64,JOURNAL!$C$5:$I$1115,5,0)) | C64: =IF($A64="","",VLOOKUP($A64,JOURNAL!$C$5:$I$1115,2,0)) | D64: =IF($A64="","",VLOOKUP($A64,JOURNAL!$C$5:$I$1115,4,0)) | E64: =IF($A64="","",VLOOKUP($A64,JOURNAL!$C$5:$I$1115,3,0))
A65: =IF(A64="","",IF(ISNA(VLOOKUP($A$1&" / "&$A$57,INDIRECT(ADDRESS(A64+5,2,1,,"JOURNAL")&":G500"),2,0)),"",VLOOKUP($A$1&" / "&$A$57,INDIRECT(ADDRESS(A64+5,2,1,,"JOURNAL")&":G500"),2,0))) | B65: =IF($A65="","",VLOOKUP($A65,JOURNAL!$C$5:$I$1115,5,0)) | C65: =IF($A65="","",VLOOKUP($A65,JOURNAL!$C$5:$I$1115,2,0)) | D65: =IF($A65="","",VLOOKUP($A65,JOURNAL!$C$5:$I$1115,4,0)) | E65: =IF($A65="","",VLOOKUP($A65,JOURNAL!$C$5:$I$1115,3,0))
A66: =IF(A65="","",IF(ISNA(VLOOKUP($A$1&" / "&$A$57,INDIRECT(ADDRESS(A65+5,2,1,,"JOURNAL")&":G500"),2,0)),"",VLOOKUP($A$1&" / "&$A$57,INDIRECT(ADDRESS(A65+5,2,1,,"JOURNAL")&":G500"),2,0))) | B66: =IF($A66="","",VLOOKUP($A66,JOURNAL!$C$5:$I$1115,5,0)) | C66: =IF($A66="","",VLOOKUP($A66,JOURNAL!$C$5:$I$1115,2,0)) | D66: =IF($A66="","",VLOOKUP($A66,JOURNAL!$C$5:$I$1115,4,0)) | E66: =IF($A66="","",VLOOKUP($A66,JOURNAL!$C$5:$I$1115,3,0))
A67: =IF(A66="","",IF(ISNA(VLOOKUP($A$1&" / "&$A$57,INDIRECT(ADDRESS(A66+5,2,1,,"JOURNAL")&":G500"),2,0)),"",VLOOKUP($A$1&" / "&$A$57,INDIRECT(ADDRESS(A66+5,2,1,,"JOURNAL")&":G500"),2,0))) | B67: =IF($A67="","",VLOOKUP($A67,JOURNAL!$C$5:$I$1115,5,0)) | C67: =IF($A67="","",VLOOKUP($A67,JOURNAL!$C$5:$I$1115,2,0)) | D67: =IF($A67="","",VLOOKUP($A67,JOURNAL!$C$5:$I$1115,4,0)) | E67: =IF($A67="","",VLOOKUP($A67,JOURNAL!$C$5:$I$1115,3,0))
A68: =IF(A67="","",IF(ISNA(VLOOKUP($A$1&" / "&$A$57,INDIRECT(ADDRESS(A67+5,2,1,,"JOURNAL")&":G500"),2,0)),"",VLOOKUP($A$1&" / "&$A$57,INDIRECT(ADDRESS(A67+5,2,1,,"JOURNAL")&":G500"),2,0))) | B68: =IF($A68="","",VLOOKUP($A68,JOURNAL!$C$5:$I$1115,5,0)) | C68: =IF($A68="","",VLOOKUP($A68,JOURNAL!$C$5:$I$1115,2,0)) | D68: =IF($A68="","",VLOOKUP($A68,JOURNAL!$C$5:$I$1115,4,0)) | E68: =IF($A68="","",VLOOKUP($A68,JOURNAL!$C$5:$I$1115,3,0))
A69: =IF(A68="","",IF(ISNA(VLOOKUP($A$1&" / "&$A$57,INDIRECT(ADDRESS(A68+5,2,1,,"JOURNAL")&":G500"),2,0)),"",VLOOKUP($A$1&" / "&$A$57,INDIRECT(ADDRESS(A68+5,2,1,,"JOURNAL")&":G500"),2,0))) | B69: =IF($A69="","",VLOOKUP($A69,JOURNAL!$C$5:$I$1115,5,0)) | C69: =IF($A69="","",VLOOKUP($A69,JOURNAL!$C$5:$I$1115,2,0)) | D69: =IF($A69="","",VLOOKUP($A69,JOURNAL!$C$5:$I$1115,4,0)) | E69: =IF($A69="","",VLOOKUP($A69,JOURNAL!$C$5:$I$1115,3,0))
A70: =IF(A69="","",IF(ISNA(VLOOKUP($A$1&" / "&$A$57,INDIRECT(ADDRESS(A69+5,2,1,,"JOURNAL")&":G500"),2,0)),"",VLOOKUP($A$1&" / "&$A$57,INDIRECT(ADDRESS(A69+5,2,1,,"JOURNAL")&":G500"),2,0))) | B70: =IF($A70="","",VLOOKUP($A70,JOURNAL!$C$5:$I$1115,5,0)) | C70: =IF($A70="","",VLOOKUP($A70,JOURNAL!$C$5:$I$1115,2,0)) | D70: =IF($A70="","",VLOOKUP($A70,JOURNAL!$C$5:$I$1115,4,0)) | E70: =IF($A70="","",VLOOKUP($A70,JOURNAL!$C$5:$I$1115,3,0))
A71: =IF(A70="","",IF(ISNA(VLOOKUP($A$1&" / "&$A$57,INDIRECT(ADDRESS(A70+5,2,1,,"JOURNAL")&":G500"),2,0)),"",VLOOKUP($A$1&" / "&$A$57,INDIRECT(ADDRESS(A70+5,2,1,,"JOURNAL")&":G500"),2,0))) | B71: =IF($A71="","",VLOOKUP($A71,JOURNAL!$C$5:$I$1115,5,0)) | C71: =IF($A71="","",VLOOKUP($A71,JOURNAL!$C$5:$I$1115,2,0)) | D71: =IF($A71="","",VLOOKUP($A71,JOURNAL!$C$5:$I$1115,4,0)) | E71: =IF($A71="","",VLOOKUP($A71,JOURNAL!$C$5:$I$1115,3,0))
... A74: =IF(A73="","",IF(ISNA(VLOOKUP($A$1&" / "&$A$57,INDIRECT(ADDRESS(A73+5,2,1,,"JOURNAL")&":G500"),2,0)),"",VLOOKUP($A$1&" / "&$A$57,INDIRECT(ADDRESS(A73+5,2,1,,"JOURNAL")&":G500"),2,0))) | B74: =IF($A74="","",VLOOKUP($A74,JOURNAL!$C$5:$I$1115,5,0)) | C74: =IF($A74="","",VLOOKUP($A74,JOURNAL!$C$5:$I$1115,2,0)) | D74: =IF($A74="","",VLOOKUP($A74,JOURNAL!$C$5:$I$1115,4,0)) | E74: =IF($A74="","",VLOOKUP($A74,JOURNAL!$C$5:$I$1115,3,0))
A75: =IF(A74="","",IF(ISNA(VLOOKUP($A$1&" / "&$A$57,INDIRECT(ADDRESS(A74+5,2,1,,"JOURNAL")&":G700"),2,0)),"",VLOOKUP($A$1&" / "&$A$57,INDIRECT(ADDRESS(A74+5,2,1,,"JOURNAL")&":G700"),2,0))) | B75: =IF($A75="","",VLOOKUP($A75,JOURNAL!$C$5:$I$1115,5,0)) | C75: =IF($A75="","",VLOOKUP($A75,JOURNAL!$C$5:$I$1115,2,0)) | D75: =IF($A75="","",VLOOKUP($A75,JOURNAL!$C$5:$I$1115,4,0)) | E75: =IF($A75="","",VLOOKUP($A75,JOURNAL!$C$5:$I$1115,3,0))
A76: =IF(A75="","",IF(ISNA(VLOOKUP($A$1&" / "&$A$57,INDIRECT(ADDRESS(A75+5,2,1,,"JOURNAL")&":G700"),2,0)),"",VLOOKUP($A$1&" / "&$A$57,INDIRECT(ADDRESS(A75+5,2,1,,"JOURNAL")&":G700"),2,0))) | B76: =IF($A76="","",VLOOKUP($A76,JOURNAL!$C$5:$I$1115,5,0)) | C76: =IF($A76="","",VLOOKUP($A76,JOURNAL!$C$5:$I$1115,2,0)) | D76: =IF($A76="","",VLOOKUP($A76,JOURNAL!$C$5:$I$1115,4,0)) | E76: =IF($A76="","",VLOOKUP($A76,JOURNAL!$C$5:$I$1115,3,0))
A77: =IF(A76="","",IF(ISNA(VLOOKUP($A$1&" / "&$A$57,INDIRECT(ADDRESS(A76+5,2,1,,"JOURNAL")&":G700"),2,0)),"",VLOOKUP($A$1&" / "&$A$57,INDIRECT(ADDRESS(A76+5,2,1,,"JOURNAL")&":G700"),2,0))) | B77: =IF($A77="","",VLOOKUP($A77,JOURNAL!$C$5:$I$1115,5,0)) | C77: =IF($A77="","",VLOOKUP($A77,JOURNAL!$C$5:$I$1115,2,0)) | D77: =IF($A77="","",VLOOKUP($A77,JOURNAL!$C$5:$I$1115,4,0)) | E77: =IF($A77="","",VLOOKUP($A77,JOURNAL!$C$5:$I$1115,3,0))
A78: =IF(A77="","",IF(ISNA(VLOOKUP($A$1&" / "&$A$57,INDIRECT(ADDRESS(A77+5,2,1,,"JOURNAL")&":G700"),2,0)),"",VLOOKUP($A$1&" / "&$A$57,INDIRECT(ADDRESS(A77+5,2,1,,"JOURNAL")&":G700"),2,0))) | B78: =IF($A78="","",VLOOKUP($A78,JOURNAL!$C$5:$I$1115,5,0)) | C78: =IF($A78="","",VLOOKUP($A78,JOURNAL!$C$5:$I$1115,2,0)) | D78: =IF($A78="","",VLOOKUP($A78,JOURNAL!$C$5:$I$1115,4,0)) | E78: =IF($A78="","",VLOOKUP($A78,JOURNAL!$C$5:$I$1115,3,0))
A79: =IF(A78="","",IF(ISNA(VLOOKUP($A$1&" / "&$A$57,INDIRECT(ADDRESS(A78+5,2,1,,"JOURNAL")&":G700"),2,0)),"",VLOOKUP($A$1&" / "&$A$57,INDIRECT(ADDRESS(A78+5,2,1,,"JOURNAL")&":G700"),2,0))) | B79: =IF($A79="","",VLOOKUP($A79,JOURNAL!$C$5:$I$1115,5,0)) | C79: =IF($A79="","",VLOOKUP($A79,JOURNAL!$C$5:$I$1115,2,0)) | D79: =IF($A79="","",VLOOKUP($A79,JOURNAL!$C$5:$I$1115,4,0)) | E79: =IF($A79="","",VLOOKUP($A79,JOURNAL!$C$5:$I$1115,3,0))
A80: =IF(A79="","",IF(ISNA(VLOOKUP($A$1&" / "&$A$57,INDIRECT(ADDRESS(A79+5,2,1,,"JOURNAL")&":G700"),2,0)),"",VLOOKUP($A$1&" / "&$A$57,INDIRECT(ADDRESS(A79+5,2,1,,"JOURNAL")&":G700"),2,0))) | B80: =IF($A80="","",VLOOKUP($A80,JOURNAL!$C$5:$I$1115,5,0)) | C80: =IF($A80="","",VLOOKUP($A80,JOURNAL!$C$5:$I$1115,2,0)) | D80: =IF($A80="","",VLOOKUP($A80,JOURNAL!$C$5:$I$1115,4,0)) | E80: =IF($A80="","",VLOOKUP($A80,JOURNAL!$C$5:$I$1115,3,0))
A81: =IF(A80="","",IF(ISNA(VLOOKUP($A$1&" / "&$A$57,INDIRECT(ADDRESS(A80+5,2,1,,"JOURNAL")&":G700"),2,0)),"",VLOOKUP($A$1&" / "&$A$57,INDIRECT(ADDRESS(A80+5,2,1,,"JOURNAL")&":G700"),2,0))) | B81: =IF($A81="","",VLOOKUP($A81,JOURNAL!$C$5:$I$1115,5,0)) | C81: =IF($A81="","",VLOOKUP($A81,JOURNAL!$C$5:$I$1115,2,0)) | D81: =IF($A81="","",VLOOKUP($A81,JOURNAL!$C$5:$I$1115,4,0)) | E81: =IF($A81="","",VLOOKUP($A81,JOURNAL!$C$5:$I$1115,3,0))
A82: =IF(A81="","",IF(ISNA(VLOOKUP($A$1&" / "&$A$57,INDIRECT(ADDRESS(A81+5,2,1,,"JOURNAL")&":G700"),2,0)),"",VLOOKUP($A$1&" / "&$A$57,INDIRECT(ADDRESS(A81+5,2,1,,"JOURNAL")&":G700"),2,0))) | B82: =IF($A82="","",VLOOKUP($A82,JOURNAL!$C$5:$I$1115,5,0)) | C82: =IF($A82="","",VLOOKUP($A82,JOURNAL!$C$5:$I$1115,2,0)) | D82: =IF($A82="","",VLOOKUP($A82,JOURNAL!$C$5:$I$1115,4,0)) | E82: =IF($A82="","",VLOOKUP($A82,JOURNAL!$C$5:$I$1115,3,0))
A83: =IF(A82="","",IF(ISNA(VLOOKUP($A$1&" / "&$A$57,INDIRECT(ADDRESS(A82+5,2,1,,"JOURNAL")&":G700"),2,0)),"",VLOOKUP($A$1&" / "&$A$57,INDIRECT(ADDRESS(A82+5,2,1,,"JOURNAL")&":G700"),2,0))) | B83: =IF($A83="","",VLOOKUP($A83,JOURNAL!$C$5:$I$1115,5,0)) | C83: =IF($A83="","",VLOOKUP($A83,JOURNAL!$C$5:$I$1115,2,0)) | D83: =IF($A83="","",VLOOKUP($A83,JOURNAL!$C$5:$I$1115,4,0)) | E83: =IF($A83="","",VLOOKUP($A83,JOURNAL!$C$5:$I$1115,3,0))
A84: {=IF(A83="","",IF(ISNA(VLOOKUP($A$1&" / "&$A$57,INDIRECT(ADDRESS(A83+5,2,1,,"JOURNAL")&":G500"),2,0)),"",VLOOKUP($A$1&" / "&$A$57,INDIRECT(ADDRESS(A83+5,2,1,,"JOURNAL")&":G500"),2,0)))} | B84: =IF($A84="","",VLOOKUP($A84,JOURNAL!$C$5:$I$1115,5,0)) | C84: =IF($A84="","",VLOOKUP($A84,JOURNAL!$C$5:$I$1115,2,0)) | D84: =IF($A84="","",VLOOKUP($A84,JOURNAL!$C$5:$I$1115,4,0)) | E84: =IF($A84="","",VLOOKUP($A84,JOURNAL!$C$5:$I$1115,3,0))
A85: Total | E85: =SUM(E59:E68) -> 0

Sheet DÉCORATION
A1: DÉCORATION
A3: BUDGET
A4: Charges
A5: Mois de facturation | B5: Libellé | E5: Montant
B6: Décoration festival | E6: 500 | F6: Contrôle d'accès par Staff | I6: Contrôle entrée par Balelec | K6: A valider lors de la présentation du thème
A15: Total | E15: =SUM(E6:E14) -> 500
A16: Produits
A17: Mois de facturation | B17: Libellé | E17: Montant
A25: Total | E25: =SUM(E18:E24) -> 0
A27: COMPTABILITE
A28: Charges
A29: N° | B29: Libellé | C29: Date | D29: En faveur de | E29: Montant
A30: =IF(ISNA(VLOOKUP($A$1&" / "&$A$28,JOURNAL!$B$5:$I$277,2,0)),"",VLOOKUP($A$1&" / "&$A$28,JOURNAL!$B$5:$I$277,2,0)) -> 70 | B30: =IF($A30="","",VLOOKUP($A30,JOURNAL!$C$5:$I$1115,5,0)) -> note de frais deco | C30: =IF($A30="","",VLOOKUP($A30,JOURNAL!$C$5:$I$1115,2,0)) -> 45978 | D30: =IF($A30="","",VLOOKUP($A30,JOURNAL!$C$5:$I$1115,4,0)) -> Cécile Cabaret | E30: =IF($A30="","",VLOOKUP($A30,JOURNAL!$C$5:$I$1115,3,0)) -> 114.8
A31: =IF(A30="","",IF(ISNA(VLOOKUP($A$1&" / "&$A$28,INDIRECT(ADDRESS(A30+5,2,1,,"JOURNAL")&":G500"),2,0)),"",VLOOKUP($A$1&" / "&$A$28,INDIRECT(ADDRESS(A30+5,2,1,,"JOURNAL")&":G500"),2,0))) -> 188 | B31: =IF($A31="","",VLOOKUP($A31,JOURNAL!$C$5:$I$1115,5,0)) -> Commande affiches | C31: =IF($A31="","",VLOOKUP($A31,JOURNAL!$C$5:$I$1115,2,0)) -> 46084 | D31: =IF($A31="","",VLOOKUP($A31,JOURNAL!$C$5:$I$1115,4,0)) -> Elia Nicolo | E31: =IF($A31="","",VLOOKUP($A31,JOURNAL!$C$5:$I$1115,3,0)) -> 130.05
A32: =IF(A31="","",IF(ISNA(VLOOKUP($A$1&" / "&$A$28,INDIRECT(ADDRESS(A31+5,2,1,,"JOURNAL")&":G500"),2,0)),"",VLOOKUP($A$1&" / "&$A$28,INDIRECT(ADDRESS(A31+5,2,1,,"JOURNAL")&":G500"),2,0))) | B32: =IF($A32="","",VLOOKUP($A32,JOURNAL!$C$5:$I$1115,5,0)) | C32: =IF($A32="","",VLOOKUP($A32,JOURNAL!$C$5:$I$1115,2,0)) | D32: =IF($A32="","",VLOOKUP($A32,JOURNAL!$C$5:$I$1115,4,0)) | E32: =IF($A32="","",VLOOKUP($A32,JOURNAL!$C$5:$I$1115,3,0))
A33: =IF(A32="","",IF(ISNA(VLOOKUP($A$1&" / "&$A$28,INDIRECT(ADDRESS(A32+5,2,1,,"JOURNAL")&":G500"),2,0)),"",VLOOKUP($A$1&" / "&$A$28,INDIRECT(ADDRESS(A32+5,2,1,,"JOURNAL")&":G500"),2,0))) | B33: =IF($A33="","",VLOOKUP($A33,JOURNAL!$C$5:$I$1115,5,0)) | C33: =IF($A33="","",VLOOKUP($A33,JOURNAL!$C$5:$I$1115,2,0)) | D33: =IF($A33="","",VLOOKUP($A33,JOURNAL!$C$5:$I$1115,4,0)) | E33: =IF($A33="","",VLOOKUP($A33,JOURNAL!$C$5:$I$1115,3,0))
A34: =IF(A33="","",IF(ISNA(VLOOKUP($A$1&" / "&$A$28,INDIRECT(ADDRESS(A33+5,2,1,,"JOURNAL")&":G700"),2,0)),"",VLOOKUP($A$1&" / "&$A$28,INDIRECT(ADDRESS(A33+5,2,1,,"JOURNAL")&":G700"),2,0))) | B34: =IF($A34="","",VLOOKUP($A34,JOURNAL!$C$5:$I$1115,5,0)) | C34: =IF($A34="","",VLOOKUP($A34,JOURNAL!$C$5:$I$1115,2,0)) | D34: =IF($A34="","",VLOOKUP($A34,JOURNAL!$C$5:$I$1115,4,0)) | E34: =IF($A34="","",VLOOKUP($A34,JOURNAL!$C$5:$I$1115,3,0))
A35: =IF(A34="","",IF(ISNA(VLOOKUP($A$1&" / "&$A$28,INDIRECT(ADDRESS(A34+5,2,1,,"JOURNAL")&":G700"),2,0)),"",VLOOKUP($A$1&" / "&$A$28,INDIRECT(ADDRESS(A34+5,2,1,,"JOURNAL")&":G700"),2,0))) | B35: =IF($A35="","",VLOOKUP($A35,JOURNAL!$C$5:$I$1115,5,0)) | C35: =IF($A35="","",VLOOKUP($A35,JOURNAL!$C$5:$I$1115,2,0)) | D35: =IF($A35="","",VLOOKUP($A35,JOURNAL!$C$5:$I$1115,4,0)) | E35: =IF($A35="","",VLOOKUP($A35,JOURNAL!$C$5:$I$1115,3,0))
A36: =IF(A35="","",IF(ISNA(VLOOKUP($A$1&" / "&$A$28,INDIRECT(ADDRESS(A35+5,2,1,,"JOURNAL")&":G700"),2,0)),"",VLOOKUP($A$1&" / "&$A$28,INDIRECT(ADDRESS(A35+5,2,1,,"JOURNAL")&":G700"),2,0))) | B36: =IF($A36="","",VLOOKUP($A36,JOURNAL!$C$5:$I$1115,5,0)) | C36: =IF($A36="","",VLOOKUP($A36,JOURNAL!$C$5:$I$1115,2,0)) | D36: =IF($A36="","",VLOOKUP($A36,JOURNAL!$C$5:$I$1115,4,0)) | E36: =IF($A36="","",VLOOKUP($A36,JOURNAL!$C$5:$I$1115,3,0))
A37: =IF(A36="","",IF(ISNA(VLOOKUP($A$1&" / "&$A$28,INDIRECT(ADDRESS(A36+5,2,1,,"JOURNAL")&":G700"),2,0)),"",VLOOKUP($A$1&" / "&$A$28,INDIRECT(ADDRESS(A36+5,2,1,,"JOURNAL")&":G700"),2,0))) | B37: =IF($A37="","",VLOOKUP($A37,JOURNAL!$C$5:$I$1115,5,0)) | C37: =IF($A37="","",VLOOKUP($A37,JOURNAL!$C$5:$I$1115,2,0)) | D37: =IF($A37="","",VLOOKUP($A37,JOURNAL!$C$5:$I$1115,4,0)) | E37: =IF($A37="","",VLOOKUP($A37,JOURNAL!$C$5:$I$1115,3,0))
A38: =IF(A37="","",IF(ISNA(VLOOKUP($A$1&" / "&$A$28,INDIRECT(ADDRESS(A37+5,2,1,,"JOURNAL")&":G700"),2,0)),"",VLOOKUP($A$1&" / "&$A$28,INDIRECT(ADDRESS(A37+5,2,1,,"JOURNAL")&":G700"),2,0))) | B38: =IF($A38="","",VLOOKUP($A38,JOURNAL!$C$5:$I$1115,5,0)) | C38: =IF($A38="","",VLOOKUP($A38,JOURNAL!$C$5:$I$1115,2,0)) | D38: =IF($A38="","",VLOOKUP($A38,JOURNAL!$C$5:$I$1115,4,0)) | E38: =IF($A38="","",VLOOKUP($A38,JOURNAL!$C$5:$I$1115,3,0))
A39: =IF(A38="","",IF(ISNA(VLOOKUP($A$1&" / "&$A$28,INDIRECT(ADDRESS(A38+5,2,1,,"JOURNAL")&":G700"),2,0)),"",VLOOKUP($A$1&" / "&$A$28,INDIRECT(ADDRESS(A38+5,2,1,,"JOURNAL")&":G700"),2,0))) | B39: =IF($A39="","",VLOOKUP($A39,JOURNAL!$C$5:$I$1115,5,0)) | C39: =IF($A39="","",VLOOKUP($A39,JOURNAL!$C$5:$I$1115,2,0)) | D39: =IF($A39="","",VLOOKUP($A39,JOURNAL!$C$5:$I$1115,4,0)) | E39: =IF($A39="","",VLOOKUP($A39,JOURNAL!$C$5:$I$1115,3,0))
A40: =IF(A39="","",IF(ISNA(VLOOKUP($A$1&" / "&$A$28,INDIRECT(ADDRESS(A39+5,2,1,,"JOURNAL")&":G700"),2,0)),"",VLOOKUP($A$1&" / "&$A$28,INDIRECT(ADDRESS(A39+5,2,1,,"JOURNAL")&":G700"),2,0))) | B40: =IF($A40="","",VLOOKUP($A40,JOURNAL!$C$5:$I$1115,5,0)) | C40: =IF($A40="","",VLOOKUP($A40,JOURNAL!$C$5:$I$1115,2,0)) | D40: =IF($A40="","",VLOOKUP($A40,JOURNAL!$C$5:$I$1115,4,0)) | E40: =IF($A40="","",VLOOKUP($A40,JOURNAL!$C$5:$I$1115,3,0))
A41: =IF(A40="","",IF(ISNA(VLOOKUP($A$1&" / "&$A$28,INDIRECT(ADDRESS(A40+5,2,1,,"JOURNAL")&":G700"),2,0)),"",VLOOKUP($A$1&" / "&$A$28,INDIRECT(ADDRESS(A40+5,2,1,,"JOURNAL")&":G700"),2,0))) | B41: =IF($A41="","",VLOOKUP($A41,JOURNAL!$C$5:$I$1115,5,0)) | C41: =IF($A41="","",VLOOKUP($A41,JOURNAL!$C$5:$I$1115,2,0)) | D41: =IF($A41="","",VLOOKUP($A41,JOURNAL!$C$5:$I$1115,4,0)) | E41: =IF($A41="","",VLOOKUP($A41,JOURNAL!$C$5:$I$1115,3,0))
A42: =IF(A41="","",IF(ISNA(VLOOKUP($A$1&" / "&$A$28,INDIRECT(ADDRESS(A41+5,2,1,,"JOURNAL")&":G700"),2,0)),"",VLOOKUP($A$1&" / "&$A$28,INDIRECT(ADDRESS(A41+5,2,1,,"JOURNAL")&":G700"),2,0))) | B42: =IF($A42="","",VLOOKUP($A42,JOURNAL!$C$5:$I$1115,5,0)) | C42: =IF($A42="","",VLOOKUP($A42,JOURNAL!$C$5:$I$1115,2,0)) | D42: =IF($A42="","",VLOOKUP($A42,JOURNAL!$C$5:$I$1115,4,0)) | E42: =IF($A42="","",VLOOKUP($A42,JOURNAL!$C$5:$I$1115,3,0))
A43: =IF(A42="","",IF(ISNA(VLOOKUP($A$1&" / "&$A$28,INDIRECT(ADDRESS(A42+5,2,1,,"JOURNAL")&":G700"),2,0)),"",VLOOKUP($A$1&" / "&$A$28,INDIRECT(ADDRESS(A42+5,2,1,,"JOURNAL")&":G700"),2,0))) | B43: =IF($A43="","",VLOOKUP($A43,JOURNAL!$C$5:$I$1115,5,0)) | C43: =IF($A43="","",VLOOKUP($A43,JOURNAL!$C$5:$I$1115,2,0)) | D43: =IF($A43="","",VLOOKUP($A43,JOURNAL!$C$5:$I$1115,4,0)) | E43: =IF($A43="","",VLOOKUP($A43,JOURNAL!$C$5:$I$1115,3,0))
A44: =IF(A43="","",IF(ISNA(VLOOKUP($A$1&" / "&$A$28,INDIRECT(ADDRESS(A43+5,2,1,,"JOURNAL")&":G700"),2,0)),"",VLOOKUP($A$1&" / "&$A$28,INDIRECT(ADDRESS(A43+5,2,1,,"JOURNAL")&":G700"),2,0))) | B44: =IF($A44="","",VLOOKUP($A44,JOURNAL!$C$5:$I$1115,5,0)) | C44: =IF($A44="","",VLOOKUP($A44,JOURNAL!$C$5:$I$1115,2,0)) | D44: =IF($A44="","",VLOOKUP($A44,JOURNAL!$C$5:$I$1115,4,0)) | E44: =IF($A44="","",VLOOKUP($A44,JOURNAL!$C$5:$I$1115,3,0))
A45: {=IF(A44="","",IF(ISNA(VLOOKUP($A$1&" / "&$A$28,INDIRECT(ADDRESS(A44+5,2,1,,"JOURNAL")&":G500"),2,0)),"",VLOOKUP($A$1&" / "&$A$28,INDIRECT(ADDRESS(A44+5,2,1,,"JOURNAL")&":G500"),2,0)))} | B45: =IF($A45="","",VLOOKUP($A45,JOURNAL!$C$5:$I$1115,5,0)) | C45: =IF($A45="","",VLOOKUP($A45,JOURNAL!$C$5:$I$1115,2,0)) | D45: =IF($A45="","",VLOOKUP($A45,JOURNAL!$C$5:$I$1115,4,0)) | E45: =IF($A45="","",VLOOKUP($A45,JOURNAL!$C$5:$I$1115,3,0))
A46: Total | E46: =SUM(E30:E45) -> 244.85
A47: Produits
A48: N° | B48: Libellé | C48: Date | D48: En faveur de | E48: Montant
A49: =IF(ISNA(VLOOKUP($A$1&" / "&$A$47,JOURNAL!$B$5:$I$277,2,0)),"",VLOOKUP($A$1&" / "&$A$47,JOURNAL!$B$5:$I$277,2,0)) | B49: =IF($A49="","",VLOOKUP($A49,JOURNAL!$C$5:$I$1115,5,0)) | C49: =IF($A49="","",VLOOKUP($A49,JOURNAL!$C$5:$I$1115,2,0)) | D49: =IF($A49="","",VLOOKUP($A49,JOURNAL!$C$5:$I$1115,4,0)) | E49: =IF($A49="","",VLOOKUP($A49,JOURNAL!$C$5:$I$1115,3,0))
A50: =IF(A49="","",IF(ISNA(VLOOKUP($A$1&" / "&$A$47,INDIRECT(ADDRESS(A49+5,2,1,,"JOURNAL")&":G700"),2,0)),"",VLOOKUP($A$1&" / "&$A$47,INDIRECT(ADDRESS(A49+5,2,1,,"JOURNAL")&":G700"),2,0))) | B50: =IF($A50="","",VLOOKUP($A50,JOURNAL!$C$5:$I$1115,5,0)) | C50: =IF($A50="","",VLOOKUP($A50,JOURNAL!$C$5:$I$1115,2,0)) | D50: =IF($A50="","",VLOOKUP($A50,JOURNAL!$C$5:$I$1115,4,0)) | E50: =IF($A50="","",VLOOKUP($A50,JOURNAL!$C$5:$I$1115,3,0))
A51: =IF(A50="","",IF(ISNA(VLOOKUP($A$1&" / "&$A$47,INDIRECT(ADDRESS(A50+5,2,1,,"JOURNAL")&":G700"),2,0)),"",VLOOKUP($A$1&" / "&$A$47,INDIRECT(ADDRESS(A50+5,2,1,,"JOURNAL")&":G700"),2,0))) | B51: =IF($A51="","",VLOOKUP($A51,JOURNAL!$C$5:$I$1115,5,0)) | C51: =IF($A51="","",VLOOKUP($A51,JOURNAL!$C$5:$I$1115,2,0)) | D51: =IF($A51="","",VLOOKUP($A51,JOURNAL!$C$5:$I$1115,4,0)) | E51: =IF($A51="","",VLOOKUP($A51,JOURNAL!$C$5:$I$1115,3,0))
A52: =IF(A51="","",IF(ISNA(VLOOKUP($A$1&" / "&$A$47,INDIRECT(ADDRESS(A51+5,2,1,,"JOURNAL")&":G700"),2,0)),"",VLOOKUP($A$1&" / "&$A$47,INDIRECT(ADDRESS(A51+5,2,1,,"JOURNAL")&":G700"),2,0))) | B52: =IF($A52="","",VLOOKUP($A52,JOURNAL!$C$5:$I$1115,5,0)) | C52: =IF($A52="","",VLOOKUP($A52,JOURNAL!$C$5:$I$1115,2,0)) | D52: =IF($A52="","",VLOOKUP($A52,JOURNAL!$C$5:$I$1115,4,0)) | E52: =IF($A52="","",VLOOKUP($A52,JOURNAL!$C$5:$I$1115,3,0))
A53: =IF(A52="","",IF(ISNA(VLOOKUP($A$1&" / "&$A$47,INDIRECT(ADDRESS(A52+5,2,1,,"JOURNAL")&":G700"),2,0)),"",VLOOKUP($A$1&" / "&$A$47,INDIRECT(ADDRESS(A52+5,2,1,,"JOURNAL")&":G700"),2,0))) | B53: =IF($A53="","",VLOOKUP($A53,JOURNAL!$C$5:$I$1115,5,0)) | C53: =IF($A53="","",VLOOKUP($A53,JOURNAL!$C$5:$I$1115,2,0)) | D53: =IF($A53="","",VLOOKUP($A53,JOURNAL!$C$5:$I$1115,4,0)) | E53: =IF($A53="","",VLOOKUP($A53,JOURNAL!$C$5:$I$1115,3,0))
A54: =IF(A53="","",IF(ISNA(VLOOKUP($A$1&" / "&$A$47,INDIRECT(ADDRESS(A53+5,2,1,,"JOURNAL")&":G700"),2,0)),"",VLOOKUP($A$1&" / "&$A$47,INDIRECT(ADDRESS(A53+5,2,1,,"JOURNAL")&":G700"),2,0))) | B54: =IF($A54="","",VLOOKUP($A54,JOURNAL!$C$5:$I$1115,5,0)) | C54: =IF($A54="","",VLOOKUP($A54,JOURNAL!$C$5:$I$1115,2,0)) | D54: =IF($A54="","",VLOOKUP($A54,JOURNAL!$C$5:$I$1115,4,0)) | E54: =IF($A54="","",VLOOKUP($A54,JOURNAL!$C$5:$I$1115,3,0))
A55: {=IF(A54="","",IF(ISNA(VLOOKUP($A$1&" / "&$A$47,INDIRECT(ADDRESS(A54+5,2,1,,"JOURNAL")&":G500"),2,0)),"",VLOOKUP($A$1&" / "&$A$47,INDIRECT(ADDRESS(A54+5,2,1,,"JOURNAL")&":G500"),2,0)))} | B55: =IF($A55="","",VLOOKUP($A55,JOURNAL!$C$5:$I$1115,5,0)) | C55: =IF($A55="","",VLOOKUP($A55,JOURNAL!$C$5:$I$1115,2,0)) | D55: =IF($A55="","",VLOOKUP($A55,JOURNAL!$C$5:$I$1115,4,0)) | E55: =IF($A55="","",VLOOKUP($A55,JOURNAL!$C$5:$I$1115,3,0))
A56: Total | E56: =SUM(E49:E55) -> 0

Sheet DIVERS
A1: DIVERS
A3: BUDGET
A4: Charges
A5: Mois de facturation | B5: Libellé | C5: Date | D5: En faveur de | E5: Montant
B6: Essence/Mobility | E6: 1500
B7: Imprévus | E7: 2500
A17: Total | E17: =SUM(E6:E16) -> 4000
A18: Produits
A19: Mois de facturation | B19: Libellé | C19: Date | D19: En faveur de | E19: Montant
A27: Total | E27: =SUM(E20:E26) -> 0
A29: COMPTABILITE
A30: Charges
A31: N° | B31: Libellé | C31: Date | D31: En faveur de | E31: Montant
A32: =IF(ISNA(VLOOKUP($A$1&" / "&$A$30,JOURNAL!$B$5:$I$1115,2,0)),"",VLOOKUP($A$1&" / "&$A$30,JOURNAL!$B$5:$I$1115,2,0)) -> 4 | B32: =IF($A32="","",VLOOKUP($A32,JOURNAL!$C$5:$I$1115,5,0)) -> Bière pour local | C32: =IF($A32="","",VLOOKUP($A32,JOURNAL!$C$5:$I$1115,2,0)) -> 46279 | D32: =IF($A32="","",VLOOKUP($A32,JOURNAL!$C$5:$I$1115,4,0)) -> Landi | E32: =IF($A32="","",VLOOKUP($A32,JOURNAL!$C$5:$I$1115,3,0)) -> 10.8
A33: =IF(A32="","",IF(ISNA(VLOOKUP($A$1&" / "&$A$30,INDIRECT(ADDRESS(A32+5,2,1,,"JOURNAL")&":G500"),2,0)),"",VLOOKUP($A$1&" / "&$A$30,INDIRECT(ADDRESS(A32+5,2,1,,"JOURNAL")&":G500"),2,0))) -> 20 | B33: =IF($A33="","",VLOOKUP($A33,JOURNAL!$C$5:$I$1115,5,0)) -> AG : Achat bières | C33: =IF($A33="","",VLOOKUP($A33,JOURNAL!$C$5:$I$1115,2,0)) -> 45911 | D33: =IF($A33="","",VLOOKUP($A33,JOURNAL!$C$5:$I$1115,4,0)) -> Landi | E33: =IF($A33="","",VLOOKUP($A33,JOURNAL!$C$5:$I$1115,3,0)) -> 23.4
A34: =IF(A33="","",IF(ISNA(VLOOKUP($A$1&" / "&$A$30,INDIRECT(ADDRESS(A33+5,2,1,,"JOURNAL")&":G500"),2,0)),"",VLOOKUP($A$1&" / "&$A$30,INDIRECT(ADDRESS(A33+5,2,1,,"JOURNAL")&":G500"),2,0))) | B34: =IF($A34="","",VLOOKUP($A34,JOURNAL!$C$5:$I$1115,5,0)) | C34: =IF($A34="","",VLOOKUP($A34,JOURNAL!$C$5:$I$1115,2,0)) | D34: =IF($A34="","",VLOOKUP($A34,JOURNAL!$C$5:$I$1115,4,0)) | E34: =IF($A34="","",VLOOKUP($A34,JOURNAL!$C$5:$I$1115,3,0))
A35: =IF(A34="","",IF(ISNA(VLOOKUP($A$1&" / "&$A$30,INDIRECT(ADDRESS(A34+5,2,1,,"JOURNAL")&":G500"),2,0)),"",VLOOKUP($A$1&" / "&$A$30,INDIRECT(ADDRESS(A34+5,2,1,,"JOURNAL")&":G500"),2,0))) | B35: =IF($A35="","",VLOOKUP($A35,JOURNAL!$C$5:$I$1115,5,0)) | C35: =IF($A35="","",VLOOKUP($A35,JOURNAL!$C$5:$I$1115,2,0)) | D35: =IF($A35="","",VLOOKUP($A35,JOURNAL!$C$5:$I$1115,4,0)) | E35: =IF($A35="","",VLOOKUP($A35,JOURNAL!$C$5:$I$1115,3,0))
A36: =IF(A35="","",IF(ISNA(VLOOKUP($A$1&" / "&$A$30,INDIRECT(ADDRESS(A35+5,2,1,,"JOURNAL")&":G500"),2,0)),"",VLOOKUP($A$1&" / "&$A$30,INDIRECT(ADDRESS(A35+5,2,1,,"JOURNAL")&":G500"),2,0))) | B36: =IF($A36="","",VLOOKUP($A36,JOURNAL!$C$5:$I$1115,5,0)) | C36: =IF($A36="","",VLOOKUP($A36,JOURNAL!$C$5:$I$1115,2,0)) | D36: =IF($A36="","",VLOOKUP($A36,JOURNAL!$C$5:$I$1115,4,0)) | E36: =IF($A36="","",VLOOKUP($A36,JOURNAL!$C$5:$I$1115,3,0))
A37: =IF(A36="","",IF(ISNA(VLOOKUP($A$1&" / "&$A$30,INDIRECT(ADDRESS(A36+5,2,1,,"JOURNAL")&":G500"),2,0)),"",VLOOKUP($A$1&" / "&$A$30,INDIRECT(ADDRESS(A36+5,2,1,,"JOURNAL")&":G500"),2,0))) | B37: =IF($A37="","",VLOOKUP($A37,JOURNAL!$C$5:$I$1115,5,0)) | C37: =IF($A37="","",VLOOKUP($A37,JOURNAL!$C$5:$I$1115,2,0)) | D37: =IF($A37="","",VLOOKUP($A37,JOURNAL!$C$5:$I$1115,4,0)) | E37: =IF($A37="","",VLOOKUP($A37,JOURNAL!$C$5:$I$1115,3,0))
A38: =IF(A37="","",IF(ISNA(VLOOKUP($A$1&" / "&$A$30,INDIRECT(ADDRESS(A37+5,2,1,,"JOURNAL")&":G500"),2,0)),"",VLOOKUP($A$1&" / "&$A$30,INDIRECT(ADDRESS(A37+5,2,1,,"JOURNAL")&":G500"),2,0))) | B38: =IF($A38="","",VLOOKUP($A38,JOURNAL!$C$5:$I$1115,5,0)) | C38: =IF($A38="","",VLOOKUP($A38,JOURNAL!$C$5:$I$1115,2,0)) | D38: =IF($A38="","",VLOOKUP($A38,JOURNAL!$C$5:$I$1115,4,0)) | E38: =IF($A38="","",VLOOKUP($A38,JOURNAL!$C$5:$I$1115,3,0))
A39: =IF(A38="","",IF(ISNA(VLOOKUP($A$1&" / "&$A$30,INDIRECT(ADDRESS(A38+5,2,1,,"JOURNAL")&":G500"),2,0)),"",VLOOKUP($A$1&" / "&$A$30,INDIRECT(ADDRESS(A38+5,2,1,,"JOURNAL")&":G500"),2,0))) | B39: =IF($A39="","",VLOOKUP($A39,JOURNAL!$C$5:$I$1115,5,0)) | C39: =IF($A39="","",VLOOKUP($A39,JOURNAL!$C$5:$I$1115,2,0)) | D39: =IF($A39="","",VLOOKUP($A39,JOURNAL!$C$5:$I$1115,4,0)) | E39: =IF($A39="","",VLOOKUP($A39,JOURNAL!$C$5:$I$1115,3,0))
A40: =IF(A39="","",IF(ISNA(VLOOKUP($A$1&" / "&$A$30,INDIRECT(ADDRESS(A39+5,2,1,,"JOURNAL")&":G500"),2,0)),"",VLOOKUP($A$1&" / "&$A$30,INDIRECT(ADDRESS(A39+5,2,1,,"JOURNAL")&":G500"),2,0))) | B40: =IF($A40="","",VLOOKUP($A40,JOURNAL!$C$5:$I$1115,5,0)) | C40: =IF($A40="","",VLOOKUP($A40,JOURNAL!$C$5:$I$1115,2,0)) | D40: =IF($A40="","",VLOOKUP($A40,JOURNAL!$C$5:$I$1115,4,0)) | E40: =IF($A40="","",VLOOKUP($A40,JOURNAL!$C$5:$I$1115,3,0))
A41: =IF(A40="","",IF(ISNA(VLOOKUP($A$1&" / "&$A$30,INDIRECT(ADDRESS(A40+5,2,1,,"JOURNAL")&":G700"),2,0)),"",VLOOKUP($A$1&" / "&$A$30,INDIRECT(ADDRESS(A40+5,2,1,,"JOURNAL")&":G700"),2,0))) | B41: =IF($A41="","",VLOOKUP($A41,JOURNAL!$C$5:$I$1115,5,0)) | C41: =IF($A41="","",VLOOKUP($A41,JOURNAL!$C$5:$I$1115,2,0)) | D41: =IF($A41="","",VLOOKUP($A41,JOURNAL!$C$5:$I$1115,4,0)) | E41: =IF($A41="","",VLOOKUP($A41,JOURNAL!$C$5:$I$1115,3,0))
A42: =IF(A41="","",IF(ISNA(VLOOKUP($A$1&" / "&$A$30,INDIRECT(ADDRESS(A41+5,2,1,,"JOURNAL")&":G700"),2,0)),"",VLOOKUP($A$1&" / "&$A$30,INDIRECT(ADDRESS(A41+5,2,1,,"JOURNAL")&":G700"),2,0))) | B42: =IF($A42="","",VLOOKUP($A42,JOURNAL!$C$5:$I$1115,5,0)) | C42: =IF($A42="","",VLOOKUP($A42,JOURNAL!$C$5:$I$1115,2,0)) | D42: =IF($A42="","",VLOOKUP($A42,JOURNAL!$C$5:$I$1115,4,0)) | E42: =IF($A42="","",VLOOKUP($A42,JOURNAL!$C$5:$I$1115,3,0))
A43: =IF(A42="","",IF(ISNA(VLOOKUP($A$1&" / "&$A$30,INDIRECT(ADDRESS(A42+5,2,1,,"JOURNAL")&":G700"),2,0)),"",VLOOKUP($A$1&" / "&$A$30,INDIRECT(ADDRESS(A42+5,2,1,,"JOURNAL")&":G700"),2,0))) | B43: =IF($A43="","",VLOOKUP($A43,JOURNAL!$C$5:$I$1115,5,0)) | C43: =IF($A43="","",VLOOKUP($A43,JOURNAL!$C$5:$I$1115,2,0)) | D43: =IF($A43="","",VLOOKUP($A43,JOURNAL!$C$5:$I$1115,4,0)) | E43: =IF($A43="","",VLOOKUP($A43,JOURNAL!$C$5:$I$1115,3,0))
A44: =IF(A43="","",IF(ISNA(VLOOKUP($A$1&" / "&$A$30,INDIRECT(ADDRESS(A43+5,2,1,,"JOURNAL")&":G700"),2,0)),"",VLOOKUP($A$1&" / "&$A$30,INDIRECT(ADDRESS(A43+5,2,1,,"JOURNAL")&":G700"),2,0))) | B44: =IF($A44="","",VLOOKUP($A44,JOURNAL!$C$5:$I$1115,5,0)) | C44: =IF($A44="","",VLOOKUP($A44,JOURNAL!$C$5:$I$1115,2,0)) | D44: =IF($A44="","",VLOOKUP($A44,JOURNAL!$C$5:$I$1115,4,0)) | E44: =IF($A44="","",VLOOKUP($A44,JOURNAL!$C$5:$I$1115,3,0))
A45: =IF(A44="","",IF(ISNA(VLOOKUP($A$1&" / "&$A$30,INDIRECT(ADDRESS(A44+5,2,1,,"JOURNAL")&":G700"),2,0)),"",VLOOKUP($A$1&" / "&$A$30,INDIRECT(ADDRESS(A44+5,2,1,,"JOURNAL")&":G700"),2,0))) | B45: =IF($A45="","",VLOOKUP($A45,JOURNAL!$C$5:$I$1115,5,0)) | C45: =IF($A45="","",VLOOKUP($A45,JOURNAL!$C$5:$I$1115,2,0)) | D45: =IF($A45="","",VLOOKUP($A45,JOURNAL!$C$5:$I$1115,4,0)) | E45: =IF($A45="","",VLOOKUP($A45,JOURNAL!$C$5:$I$1115,3,0))
A46: =IF(A45="","",IF(ISNA(VLOOKUP($A$1&" / "&$A$30,INDIRECT(ADDRESS(A45+5,2,1,,"JOURNAL")&":G700"),2,0)),"",VLOOKUP($A$1&" / "&$A$30,INDIRECT(ADDRESS(A45+5,2,1,,"JOURNAL")&":G700"),2,0))) | B46: =IF($A46="","",VLOOKUP($A46,JOURNAL!$C$5:$I$1115,5,0)) | C46: =IF($A46="","",VLOOKUP($A46,JOURNAL!$C$5:$I$1115,2,0)) | D46: =IF($A46="","",VLOOKUP($A46,JOURNAL!$C$5:$I$1115,4,0)) | E46: =IF($A46="","",VLOOKUP($A46,JOURNAL!$C$5:$I$1115,3,0))
A47: =IF(A46="","",IF(ISNA(VLOOKUP($A$1&" / "&$A$30,INDIRECT(ADDRESS(A46+5,2,1,,"JOURNAL")&":G700"),2,0)),"",VLOOKUP($A$1&" / "&$A$30,INDIRECT(ADDRESS(A46+5,2,1,,"JOURNAL")&":G700"),2,0))) | B47: =IF($A47="","",VLOOKUP($A47,JOURNAL!$C$5:$I$1115,5,0)) | C47: =IF($A47="","",VLOOKUP($A47,JOURNAL!$C$5:$I$1115,2,0)) | D47: =IF($A47="","",VLOOKUP($A47,JOURNAL!$C$5:$I$1115,4,0)) | E47: =IF($A47="","",VLOOKUP($A47,JOURNAL!$C$5:$I$1115,3,0))
A48: =IF(A47="","",IF(ISNA(VLOOKUP($A$1&" / "&$A$30,INDIRECT(ADDRESS(A47+5,2,1,,"JOURNAL")&":G700"),2,0)),"",VLOOKUP($A$1&" / "&$A$30,INDIRECT(ADDRESS(A47+5,2,1,,"JOURNAL")&":G700"),2,0))) | B48: =IF($A48="","",VLOOKUP($A48,JOURNAL!$C$5:$I$1115,5,0)) | C48: =IF($A48="","",VLOOKUP($A48,JOURNAL!$C$5:$I$1115,2,0)) | D48: =IF($A48="","",VLOOKUP($A48,JOURNAL!$C$5:$I$1115,4,0)) | E48: =IF($A48="","",VLOOKUP($A48,JOURNAL!$C$5:$I$1115,3,0))
A49: =IF(A48="","",IF(ISNA(VLOOKUP($A$1&" / "&$A$30,INDIRECT(ADDRESS(A48+5,2,1,,"JOURNAL")&":G700"),2,0)),"",VLOOKUP($A$1&" / "&$A$30,INDIRECT(ADDRESS(A48+5,2,1,,"JOURNAL")&":G700"),2,0))) | B49: =IF($A49="","",VLOOKUP($A49,JOURNAL!$C$5:$I$1115,5,0)) | C49: =IF($A49="","",VLOOKUP($A49,JOURNAL!$C$5:$I$1115,2,0)) | D49: =IF($A49="","",VLOOKUP($A49,JOURNAL!$C$5:$I$1115,4,0)) | E49: =IF($A49="","",VLOOKUP($A49,JOURNAL!$C$5:$I$1115,3,0))
A50: =IF(A49="","",IF(ISNA(VLOOKUP($A$1&" / "&$A$30,INDIRECT(ADDRESS(A49+5,2,1,,"JOURNAL")&":G700"),2,0)),"",VLOOKUP($A$1&" / "&$A$30,INDIRECT(ADDRESS(A49+5,2,1,,"JOURNAL")&":G700"),2,0))) | B50: =IF($A50="","",VLOOKUP($A50,JOURNAL!$C$5:$I$1115,5,0)) | C50: =IF($A50="","",VLOOKUP($A50,JOURNAL!$C$5:$I$1115,2,0)) | D50: =IF($A50="","",VLOOKUP($A50,JOURNAL!$C$5:$I$1115,4,0)) | E50: =IF($A50="","",VLOOKUP($A50,JOURNAL!$C$5:$I$1115,3,0))
A51: =IF(A50="","",IF(ISNA(VLOOKUP($A$1&" / "&$A$30,INDIRECT(ADDRESS(A50+5,2,1,,"JOURNAL")&":G700"),2,0)),"",VLOOKUP($A$1&" / "&$A$30,INDIRECT(ADDRESS(A50+5,2,1,,"JOURNAL")&":G700"),2,0))) | B51: =IF($A51="","",VLOOKUP($A51,JOURNAL!$C$5:$I$1115,5,0)) | C51: =IF($A51="","",VLOOKUP($A51,JOURNAL!$C$5:$I$1115,2,0)) | D51: =IF($A51="","",VLOOKUP($A51,JOURNAL!$C$5:$I$1115,4,0)) | E51: =IF($A51="","",VLOOKUP($A51,JOURNAL!$C$5:$I$1115,3,0))
A52: =IF(A51="","",IF(ISNA(VLOOKUP($A$1&" / "&$A$30,INDIRECT(ADDRESS(A51+5,2,1,,"JOURNAL")&":G700"),2,0)),"",VLOOKUP($A$1&" / "&$A$30,INDIRECT(ADDRESS(A51+5,2,1,,"JOURNAL")&":G700"),2,0))) | B52: =IF($A52="","",VLOOKUP($A52,JOURNAL!$C$5:$I$1115,5,0)) | C52: =IF($A52="","",VLOOKUP($A52,JOURNAL!$C$5:$I$1115,2,0)) | D52: =IF($A52="","",VLOOKUP($A52,JOURNAL!$C$5:$I$1115,4,0)) | E52: =IF($A52="","",VLOOKUP($A52,JOURNAL!$C$5:$I$1115,3,0))
... A59: =IF(A58="","",IF(ISNA(VLOOKUP($A$1&" / "&$A$30,INDIRECT(ADDRESS(A58+5,2,1,,"JOURNAL")&":G700"),2,0)),"",VLOOKUP($A$1&" / "&$A$30,INDIRECT(ADDRESS(A58+5,2,1,,"JOURNAL")&":G700"),2,0))) | B59: =IF($A59="","",VLOOKUP($A59,JOURNAL!$C$5:$I$1115,5,0)) | C59: =IF($A59="","",VLOOKUP($A59,JOURNAL!$C$5:$I$1115,2,0)) | D59: =IF($A59="","",VLOOKUP($A59,JOURNAL!$C$5:$I$1115,4,0)) | E59: =IF($A59="","",VLOOKUP($A59,JOURNAL!$C$5:$I$1115,3,0))
A60: {=IF(A59="","",IF(ISNA(VLOOKUP($A$1&" / "&$A$30,INDIRECT(ADDRESS(A59+5,2,1,,"JOURNAL")&":G500"),2,0)),"",VLOOKUP($A$1&" / "&$A$30,INDIRECT(ADDRESS(A59+5,2,1,,"JOURNAL")&":G500"),2,0)))} | B60: =IF($A60="","",VLOOKUP($A60,JOURNAL!$C$5:$I$1115,5,0)) | C60: =IF($A60="","",VLOOKUP($A60,JOURNAL!$C$5:$I$1115,2,0)) | D60: =IF($A60="","",VLOOKUP($A60,JOURNAL!$C$5:$I$1115,4,0)) | E60: =IF($A60="","",VLOOKUP($A60,JOURNAL!$C$5:$I$1115,3,0))
A61: Total | E61: =SUM(E32:E60) -> 34.2
A62: Produits
A63: N° | B63: Libellé | C63: Date | D63: En faveur de | E63: Montant
A64: =IF(ISNA(VLOOKUP($A$1&" / "&$A$62,JOURNAL!$B$5:$I$1115,2,0)),"",VLOOKUP($A$1&" / "&$A$62,JOURNAL!$B$5:$I$1115,2,0)) | B64: =IF($A64="","",VLOOKUP($A64,JOURNAL!$C$5:$I$1115,5,0)) | C64: =IF($A64="","",VLOOKUP($A64,JOURNAL!$C$5:$I$1115,2,0)) | D64: =IF($A64="","",VLOOKUP($A64,JOURNAL!$C$5:$I$1115,4,0)) | E64: =IF($A64="","",VLOOKUP($A64,JOURNAL!$C$5:$I$1115,3,0))
A65: =IF(A64="","",IF(ISNA(VLOOKUP($A$1&" / "&$A$62,INDIRECT(ADDRESS(A64+5,2,1,,"JOURNAL")&":G700"),2,0)),"",VLOOKUP($A$1&" / "&$A$62,INDIRECT(ADDRESS(A64+5,2,1,,"JOURNAL")&":G700"),2,0))) | B65: =IF($A65="","",VLOOKUP($A65,JOURNAL!$C$5:$I$1115,5,0)) | C65: =IF($A65="","",VLOOKUP($A65,JOURNAL!$C$5:$I$1115,2,0)) | D65: =IF($A65="","",VLOOKUP($A65,JOURNAL!$C$5:$I$1115,4,0)) | E65: =IF($A65="","",VLOOKUP($A65,JOURNAL!$C$5:$I$1115,3,0))
A66: =IF(A65="","",IF(ISNA(VLOOKUP($A$1&" / "&$A$62,INDIRECT(ADDRESS(A65+5,2,1,,"JOURNAL")&":G700"),2,0)),"",VLOOKUP($A$1&" / "&$A$62,INDIRECT(ADDRESS(A65+5,2,1,,"JOURNAL")&":G700"),2,0))) | B66: =IF($A66="","",VLOOKUP($A66,JOURNAL!$C$5:$I$1115,5,0)) | C66: =IF($A66="","",VLOOKUP($A66,JOURNAL!$C$5:$I$1115,2,0)) | D66: =IF($A66="","",VLOOKUP($A66,JOURNAL!$C$5:$I$1115,4,0)) | E66: =IF($A66="","",VLOOKUP($A66,JOURNAL!$C$5:$I$1115,3,0))
A67: =IF(A66="","",IF(ISNA(VLOOKUP($A$1&" / "&$A$62,INDIRECT(ADDRESS(A66+5,2,1,,"JOURNAL")&":G700"),2,0)),"",VLOOKUP($A$1&" / "&$A$62,INDIRECT(ADDRESS(A66+5,2,1,,"JOURNAL")&":G700"),2,0))) | B67: =IF($A67="","",VLOOKUP($A67,JOURNAL!$C$5:$I$1115,5,0)) | C67: =IF($A67="","",VLOOKUP($A67,JOURNAL!$C$5:$I$1115,2,0)) | D67: =IF($A67="","",VLOOKUP($A67,JOURNAL!$C$5:$I$1115,4,0)) | E67: =IF($A67="","",VLOOKUP($A67,JOURNAL!$C$5:$I$1115,3,0))
A68: =IF(A67="","",IF(ISNA(VLOOKUP($A$1&" / "&$A$62,INDIRECT(ADDRESS(A67+5,2,1,,"JOURNAL")&":G700"),2,0)),"",VLOOKUP($A$1&" / "&$A$62,INDIRECT(ADDRESS(A67+5,2,1,,"JOURNAL")&":G700"),2,0))) | B68: =IF($A68="","",VLOOKUP($A68,JOURNAL!$C$5:$I$1115,5,0)) | C68: =IF($A68="","",VLOOKUP($A68,JOURNAL!$C$5:$I$1115,2,0)) | D68: =IF($A68="","",VLOOKUP($A68,JOURNAL!$C$5:$I$1115,4,0)) | E68: =IF($A68="","",VLOOKUP($A68,JOURNAL!$C$5:$I$1115,3,0))
A69: =IF(A68="","",IF(ISNA(VLOOKUP($A$1&" / "&$A$62,INDIRECT(ADDRESS(A68+5,2,1,,"JOURNAL")&":G700"),2,0)),"",VLOOKUP($A$1&" / "&$A$62,INDIRECT(ADDRESS(A68+5,2,1,,"JOURNAL")&":G700"),2,0))) | B69: =IF($A69="","",VLOOKUP($A69,JOURNAL!$C$5:$I$1115,5,0)) | C69: =IF($A69="","",VLOOKUP($A69,JOURNAL!$C$5:$I$1115,2,0)) | D69: =IF($A69="","",VLOOKUP($A69,JOURNAL!$C$5:$I$1115,4,0)) | E69: =IF($A69="","",VLOOKUP($A69,JOURNAL!$C$5:$I$1115,3,0))
A70: =IF(A69="","",IF(ISNA(VLOOKUP($A$1&" / "&$A$62,INDIRECT(ADDRESS(A69+5,2,1,,"JOURNAL")&":G700"),2,0)),"",VLOOKUP($A$1&" / "&$A$62,INDIRECT(ADDRESS(A69+5,2,1,,"JOURNAL")&":G700"),2,0))) | B70: =IF($A70="","",VLOOKUP($A70,JOURNAL!$C$5:$I$1115,5,0)) | C70: =IF($A70="","",VLOOKUP($A70,JOURNAL!$C$5:$I$1115,2,0)) | D70: =IF($A70="","",VLOOKUP($A70,JOURNAL!$C$5:$I$1115,4,0)) | E70: =IF($A70="","",VLOOKUP($A70,JOURNAL!$C$5:$I$1115,3,0))
A71: =IF(A70="","",IF(ISNA(VLOOKUP($A$1&" / "&$A$62,INDIRECT(ADDRESS(A70+5,2,1,,"JOURNAL")&":G700"),2,0)),"",VLOOKUP($A$1&" / "&$A$62,INDIRECT(ADDRESS(A70+5,2,1,,"JOURNAL")&":G700"),2,0))) | B71: =IF($A71="","",VLOOKUP($A71,JOURNAL!$C$5:$I$1115,5,0)) | C71: =IF($A71="","",VLOOKUP($A71,JOURNAL!$C$5:$I$1115,2,0)) | D71: =IF($A71="","",VLOOKUP($A71,JOURNAL!$C$5:$I$1115,4,0)) | E71: =IF($A71="","",VLOOKUP($A71,JOURNAL!$C$5:$I$1115,3,0))
A72: =IF(A71="","",IF(ISNA(VLOOKUP($A$1&" / "&$A$62,INDIRECT(ADDRESS(A71+5,2,1,,"JOURNAL")&":G700"),2,0)),"",VLOOKUP($A$1&" / "&$A$62,INDIRECT(ADDRESS(A71+5,2,1,,"JOURNAL")&":G700"),2,0))) | B72: =IF($A72="","",VLOOKUP($A72,JOURNAL!$C$5:$I$1115,5,0)) | C72: =IF($A72="","",VLOOKUP($A72,JOURNAL!$C$5:$I$1115,2,0)) | D72: =IF($A72="","",VLOOKUP($A72,JOURNAL!$C$5:$I$1115,4,0)) | E72: =IF($A72="","",VLOOKUP($A72,JOURNAL!$C$5:$I$1115,3,0))
A73: =IF(A72="","",IF(ISNA(VLOOKUP($A$1&" / "&$A$62,INDIRECT(ADDRESS(A72+5,2,1,,"JOURNAL")&":G700"),2,0)),"",VLOOKUP($A$1&" / "&$A$62,INDIRECT(ADDRESS(A72+5,2,1,,"JOURNAL")&":G700"),2,0))) | B73: =IF($A73="","",VLOOKUP($A73,JOURNAL!$C$5:$I$1115,5,0)) | C73: =IF($A73="","",VLOOKUP($A73,JOURNAL!$C$5:$I$1115,2,0)) | D73: =IF($A73="","",VLOOKUP($A73,JOURNAL!$C$5:$I$1115,4,0)) | E73: =IF($A73="","",VLOOKUP($A73,JOURNAL!$C$5:$I$1115,3,0))
A74: =IF(A73="","",IF(ISNA(VLOOKUP($A$1&" / "&$A$62,INDIRECT(ADDRESS(A73+5,2,1,,"JOURNAL")&":G700"),2,0)),"",VLOOKUP($A$1&" / "&$A$62,INDIRECT(ADDRESS(A73+5,2,1,,"JOURNAL")&":G700"),2,0))) | B74: =IF($A74="","",VLOOKUP($A74,JOURNAL!$C$5:$I$1115,5,0)) | C74: =IF($A74="","",VLOOKUP($A74,JOURNAL!$C$5:$I$1115,2,0)) | D74: =IF($A74="","",VLOOKUP($A74,JOURNAL!$C$5:$I$1115,4,0)) | E74: =IF($A74="","",VLOOKUP($A74,JOURNAL!$C$5:$I$1115,3,0))
A75: =IF(A74="","",IF(ISNA(VLOOKUP($A$1&" / "&$A$62,INDIRECT(ADDRESS(A74+5,2,1,,"JOURNAL")&":G700"),2,0)),"",VLOOKUP($A$1&" / "&$A$62,INDIRECT(ADDRESS(A74+5,2,1,,"JOURNAL")&":G700"),2,0))) | B75: =IF($A75="","",VLOOKUP($A75,JOURNAL!$C$5:$I$1115,5,0)) | C75: =IF($A75="","",VLOOKUP($A75,JOURNAL!$C$5:$I$1115,2,0)) | D75: =IF($A75="","",VLOOKUP($A75,JOURNAL!$C$5:$I$1115,4,0)) | E75: =IF($A75="","",VLOOKUP($A75,JOURNAL!$C$5:$I$1115,3,0))
A76: =IF(A75="","",IF(ISNA(VLOOKUP($A$1&" / "&$A$62,INDIRECT(ADDRESS(A75+5,2,1,,"JOURNAL")&":G700"),2,0)),"",VLOOKUP($A$1&" / "&$A$62,INDIRECT(ADDRESS(A75+5,2,1,,"JOURNAL")&":G700"),2,0))) | B76: =IF($A76="","",VLOOKUP($A76,JOURNAL!$C$5:$I$1115,5,0)) | C76: =IF($A76="","",VLOOKUP($A76,JOURNAL!$C$5:$I$1115,2,0)) | D76: =IF($A76="","",VLOOKUP($A76,JOURNAL!$C$5:$I$1115,4,0)) | E76: =IF($A76="","",VLOOKUP($A76,JOURNAL!$C$5:$I$1115,3,0))
... A90: =IF(A89="","",IF(ISNA(VLOOKUP($A$1&" / "&$A$62,INDIRECT(ADDRESS(A89+5,2,1,,"JOURNAL")&":G700"),2,0)),"",VLOOKUP($A$1&" / "&$A$62,INDIRECT(ADDRESS(A89+5,2,1,,"JOURNAL")&":G700"),2,0))) | B90: =IF($A90="","",VLOOKUP($A90,JOURNAL!$C$5:$I$1115,5,0)) | C90: =IF($A90="","",VLOOKUP($A90,JOURNAL!$C$5:$I$1115,2,0)) | D90: =IF($A90="","",VLOOKUP($A90,JOURNAL!$C$5:$I$1115,4,0)) | E90: =IF($A90="","",VLOOKUP($A90,JOURNAL!$C$5:$I$1115,3,0))
A91: {=IF(A90="","",IF(ISNA(VLOOKUP($A$1&" / "&$A$62,INDIRECT(ADDRESS(A90+5,2,1,,"JOURNAL")&":G500"),2,0)),"",VLOOKUP($A$1&" / "&$A$62,INDIRECT(ADDRESS(A90+5,2,1,,"JOURNAL")&":G500"),2,0)))} | B91: =IF($A91="","",VLOOKUP($A91,JOURNAL!$C$5:$I$1115,5,0)) | C91: =IF($A91="","",VLOOKUP($A91,JOURNAL!$C$5:$I$1115,2,0)) | D91: =IF($A91="","",VLOOKUP($A91,JOURNAL!$C$5:$I$1115,4,0)) | E91: =IF($A91="","",VLOOKUP($A91,JOURNAL!$C$5:$I$1115,3,0))
A92: Total | E92: =SUM(E64:E75) -> 0

Sheet ÉLECTRICITÉ
A1: ÉLECTRICITÉ
A3: BUDGET
A4: Charges
A5: Mois de facturation | B5: Libellé | E5: Montant
B6: Divers | E6: 300 | F6: Contrôle d'accès par Staff | I6: Contrôle entrée par Balelec
A15: Total | E15: =SUM(E6:E14) -> 300
A16: Produits
A17: Mois de facturation | B17: Libellé | E17: Montant
A25: Total | E25: =SUM(E18:E24) -> 0
A27: COMPTABILITE
A28: Charges
A29: N° | B29: Libellé | C29: Date | D29: En faveur de | E29: Montant
A30: =IF(ISNA(VLOOKUP($A$1&" / "&$A$28,JOURNAL!$B$5:$I$1115,2,0)),"",VLOOKUP($A$1&" / "&$A$28,JOURNAL!$B$5:$I$1115,2,0)) | B30: =IF($A30="","",VLOOKUP($A30,JOURNAL!$C$5:$I$1115,5,0)) | C30: =IF($A30="","",VLOOKUP($A30,JOURNAL!$C$5:$I$1115,2,0)) | D30: =IF($A30="","",VLOOKUP($A30,JOURNAL!$C$5:$I$1115,4,0)) | E30: =IF($A30="","",VLOOKUP($A30,JOURNAL!$C$5:$I$1115,3,0))
A31: =IF(A30="","",IF(ISNA(VLOOKUP($A$1&" / "&$A$28,INDIRECT(ADDRESS(A30+5,2,1,,"JOURNAL")&":G700"),2,0)),"",VLOOKUP($A$1&" / "&$A$28,INDIRECT(ADDRESS(A30+5,2,1,,"JOURNAL")&":G700"),2,0))) | B31: =IF($A31="","",VLOOKUP($A31,JOURNAL!$C$5:$I$1115,5,0)) | C31: =IF($A31="","",VLOOKUP($A31,JOURNAL!$C$5:$I$1115,2,0)) | D31: =IF($A31="","",VLOOKUP($A31,JOURNAL!$C$5:$I$1115,4,0)) | E31: =IF($A31="","",VLOOKUP($A31,JOURNAL!$C$5:$I$1115,3,0))
A32: =IF(A31="","",IF(ISNA(VLOOKUP($A$1&" / "&$A$28,INDIRECT(ADDRESS(A31+5,2,1,,"JOURNAL")&":G700"),2,0)),"",VLOOKUP($A$1&" / "&$A$28,INDIRECT(ADDRESS(A31+5,2,1,,"JOURNAL")&":G700"),2,0))) | B32: =IF($A32="","",VLOOKUP($A32,JOURNAL!$C$5:$I$1115,5,0)) | C32: =IF($A32="","",VLOOKUP($A32,JOURNAL!$C$5:$I$1115,2,0)) | D32: =IF($A32="","",VLOOKUP($A32,JOURNAL!$C$5:$I$1115,4,0)) | E32: =IF($A32="","",VLOOKUP($A32,JOURNAL!$C$5:$I$1115,3,0))
A33: =IF(A32="","",IF(ISNA(VLOOKUP($A$1&" / "&$A$28,INDIRECT(ADDRESS(A32+5,2,1,,"JOURNAL")&":G700"),2,0)),"",VLOOKUP($A$1&" / "&$A$28,INDIRECT(ADDRESS(A32+5,2,1,,"JOURNAL")&":G700"),2,0))) | B33: =IF($A33="","",VLOOKUP($A33,JOURNAL!$C$5:$I$1115,5,0)) | C33: =IF($A33="","",VLOOKUP($A33,JOURNAL!$C$5:$I$1115,2,0)) | D33: =IF($A33="","",VLOOKUP($A33,JOURNAL!$C$5:$I$1115,4,0)) | E33: =IF($A33="","",VLOOKUP($A33,JOURNAL!$C$5:$I$1115,3,0))
A34: =IF(A33="","",IF(ISNA(VLOOKUP($A$1&" / "&$A$28,INDIRECT(ADDRESS(A33+5,2,1,,"JOURNAL")&":G700"),2,0)),"",VLOOKUP($A$1&" / "&$A$28,INDIRECT(ADDRESS(A33+5,2,1,,"JOURNAL")&":G700"),2,0))) | B34: =IF($A34="","",VLOOKUP($A34,JOURNAL!$C$5:$I$1115,5,0)) | C34: =IF($A34="","",VLOOKUP($A34,JOURNAL!$C$5:$I$1115,2,0)) | D34: =IF($A34="","",VLOOKUP($A34,JOURNAL!$C$5:$I$1115,4,0)) | E34: =IF($A34="","",VLOOKUP($A34,JOURNAL!$C$5:$I$1115,3,0))
A35: =IF(A34="","",IF(ISNA(VLOOKUP($A$1&" / "&$A$28,INDIRECT(ADDRESS(A34+5,2,1,,"JOURNAL")&":G700"),2,0)),"",VLOOKUP($A$1&" / "&$A$28,INDIRECT(ADDRESS(A34+5,2,1,,"JOURNAL")&":G700"),2,0))) | B35: =IF($A35="","",VLOOKUP($A35,JOURNAL!$C$5:$I$1115,5,0)) | C35: =IF($A35="","",VLOOKUP($A35,JOURNAL!$C$5:$I$1115,2,0)) | D35: =IF($A35="","",VLOOKUP($A35,JOURNAL!$C$5:$I$1115,4,0)) | E35: =IF($A35="","",VLOOKUP($A35,JOURNAL!$C$5:$I$1115,3,0))
A36: =IF(A35="","",IF(ISNA(VLOOKUP($A$1&" / "&$A$28,INDIRECT(ADDRESS(A35+5,2,1,,"JOURNAL")&":G700"),2,0)),"",VLOOKUP($A$1&" / "&$A$28,INDIRECT(ADDRESS(A35+5,2,1,,"JOURNAL")&":G700"),2,0))) | B36: =IF($A36="","",VLOOKUP($A36,JOURNAL!$C$5:$I$1115,5,0)) | C36: =IF($A36="","",VLOOKUP($A36,JOURNAL!$C$5:$I$1115,2,0)) | D36: =IF($A36="","",VLOOKUP($A36,JOURNAL!$C$5:$I$1115,4,0)) | E36: =IF($A36="","",VLOOKUP($A36,JOURNAL!$C$5:$I$1115,3,0))
A37: =IF(A36="","",IF(ISNA(VLOOKUP($A$1&" / "&$A$28,INDIRECT(ADDRESS(A36+5,2,1,,"JOURNAL")&":G700"),2,0)),"",VLOOKUP($A$1&" / "&$A$28,INDIRECT(ADDRESS(A36+5,2,1,,"JOURNAL")&":G700"),2,0))) | B37: =IF($A37="","",VLOOKUP($A37,JOURNAL!$C$5:$I$1115,5,0)) | C37: =IF($A37="","",VLOOKUP($A37,JOURNAL!$C$5:$I$1115,2,0)) | D37: =IF($A37="","",VLOOKUP($A37,JOURNAL!$C$5:$I$1115,4,0)) | E37: =IF($A37="","",VLOOKUP($A37,JOURNAL!$C$5:$I$1115,3,0))
A38: =IF(A37="","",IF(ISNA(VLOOKUP($A$1&" / "&$A$28,INDIRECT(ADDRESS(A37+5,2,1,,"JOURNAL")&":G700"),2,0)),"",VLOOKUP($A$1&" / "&$A$28,INDIRECT(ADDRESS(A37+5,2,1,,"JOURNAL")&":G700"),2,0))) | B38: =IF($A38="","",VLOOKUP($A38,JOURNAL!$C$5:$I$1115,5,0)) | C38: =IF($A38="","",VLOOKUP($A38,JOURNAL!$C$5:$I$1115,2,0)) | D38: =IF($A38="","",VLOOKUP($A38,JOURNAL!$C$5:$I$1115,4,0)) | E38: =IF($A38="","",VLOOKUP($A38,JOURNAL!$C$5:$I$1115,3,0))
A39: =IF(A38="","",IF(ISNA(VLOOKUP($A$1&" / "&$A$28,INDIRECT(ADDRESS(A38+5,2,1,,"JOURNAL")&":G700"),2,0)),"",VLOOKUP($A$1&" / "&$A$28,INDIRECT(ADDRESS(A38+5,2,1,,"JOURNAL")&":G700"),2,0))) | B39: =IF($A39="","",VLOOKUP($A39,JOURNAL!$C$5:$I$1115,5,0)) | C39: =IF($A39="","",VLOOKUP($A39,JOURNAL!$C$5:$I$1115,2,0)) | D39: =IF($A39="","",VLOOKUP($A39,JOURNAL!$C$5:$I$1115,4,0)) | E39: =IF($A39="","",VLOOKUP($A39,JOURNAL!$C$5:$I$1115,3,0))
A40: =IF(A39="","",IF(ISNA(VLOOKUP($A$1&" / "&$A$28,INDIRECT(ADDRESS(A39+5,2,1,,"JOURNAL")&":G700"),2,0)),"",VLOOKUP($A$1&" / "&$A$28,INDIRECT(ADDRESS(A39+5,2,1,,"JOURNAL")&":G700"),2,0))) | B40: =IF($A40="","",VLOOKUP($A40,JOURNAL!$C$5:$I$1115,5,0)) | C40: =IF($A40="","",VLOOKUP($A40,JOURNAL!$C$5:$I$1115,2,0)) | D40: =IF($A40="","",VLOOKUP($A40,JOURNAL!$C$5:$I$1115,4,0)) | E40: =IF($A40="","",VLOOKUP($A40,JOURNAL!$C$5:$I$1115,3,0))
A41: =IF(A40="","",IF(ISNA(VLOOKUP($A$1&" / "&$A$28,INDIRECT(ADDRESS(A40+5,2,1,,"JOURNAL")&":G700"),2,0)),"",VLOOKUP($A$1&" / "&$A$28,INDIRECT(ADDRESS(A40+5,2,1,,"JOURNAL")&":G700"),2,0))) | B41: =IF($A41="","",VLOOKUP($A41,JOURNAL!$C$5:$I$1115,5,0)) | C41: =IF($A41="","",VLOOKUP($A41,JOURNAL!$C$5:$I$1115,2,0)) | D41: =IF($A41="","",VLOOKUP($A41,JOURNAL!$C$5:$I$1115,4,0)) | E41: =IF($A41="","",VLOOKUP($A41,JOURNAL!$C$5:$I$1115,3,0))
A42: =IF(A41="","",IF(ISNA(VLOOKUP($A$1&" / "&$A$28,INDIRECT(ADDRESS(A41+5,2,1,,"JOURNAL")&":G700"),2,0)),"",VLOOKUP($A$1&" / "&$A$28,INDIRECT(ADDRESS(A41+5,2,1,,"JOURNAL")&":G700"),2,0))) | B42: =IF($A42="","",VLOOKUP($A42,JOURNAL!$C$5:$I$1115,5,0)) | C42: =IF($A42="","",VLOOKUP($A42,JOURNAL!$C$5:$I$1115,2,0)) | D42: =IF($A42="","",VLOOKUP($A42,JOURNAL!$C$5:$I$1115,4,0)) | E42: =IF($A42="","",VLOOKUP($A42,JOURNAL!$C$5:$I$1115,3,0))
... A45: =IF(A44="","",IF(ISNA(VLOOKUP($A$1&" / "&$A$28,INDIRECT(ADDRESS(A44+5,2,1,,"JOURNAL")&":G700"),2,0)),"",VLOOKUP($A$1&" / "&$A$28,INDIRECT(ADDRESS(A44+5,2,1,,"JOURNAL")&":G700"),2,0))) | B45: =IF($A45="","",VLOOKUP($A45,JOURNAL!$C$5:$I$1115,5,0)) | C45: =IF($A45="","",VLOOKUP($A45,JOURNAL!$C$5:$I$1115,2,0)) | D45: =IF($A45="","",VLOOKUP($A45,JOURNAL!$C$5:$I$1115,4,0)) | E45: =IF($A45="","",VLOOKUP($A45,JOURNAL!$C$5:$I$1115,3,0))
A46: Total | E46: =SUM(E30:E45) -> 0
A47: Produits
A48: N° | B48: Libellé | C48: Date | D48: En faveur de | E48: Montant
A49: =IF(ISNA(VLOOKUP($A$1&" / "&$A$47,JOURNAL!$B$5:$I$1115,2,0)),"",VLOOKUP($A$1&" / "&$A$47,JOURNAL!$B$5:$I$277,2,0)) | B49: =IF($A49="","",VLOOKUP($A49,JOURNAL!$C$5:$I$1115,5,0)) | C49: =IF($A49="","",VLOOKUP($A49,JOURNAL!$C$5:$I$1115,2,0)) | D49: =IF($A49="","",VLOOKUP($A49,JOURNAL!$C$5:$I$1115,4,0)) | E49: =IF($A49="","",VLOOKUP($A49,JOURNAL!$C$5:$I$1115,3,0))
A50: =IF(A49="","",IF(ISNA(VLOOKUP($A$1&" / "&$A$47,INDIRECT(ADDRESS(A49+5,2,1,,"JOURNAL")&":G700"),2,0)),"",VLOOKUP($A$1&" / "&$A$47,INDIRECT(ADDRESS(A49+5,2,1,,"JOURNAL")&":G700"),2,0))) | B50: =IF($A50="","",VLOOKUP($A50,JOURNAL!$C$5:$I$1115,5,0)) | C50: =IF($A50="","",VLOOKUP($A50,JOURNAL!$C$5:$I$1115,2,0)) | D50: =IF($A50="","",VLOOKUP($A50,JOURNAL!$C$5:$I$1115,4,0)) | E50: =IF($A50="","",VLOOKUP($A50,JOURNAL!$C$5:$I$1115,3,0))
A51: =IF(A50="","",IF(ISNA(VLOOKUP($A$1&" / "&$A$47,INDIRECT(ADDRESS(A50+5,2,1,,"JOURNAL")&":G700"),2,0)),"",VLOOKUP($A$1&" / "&$A$47,INDIRECT(ADDRESS(A50+5,2,1,,"JOURNAL")&":G700"),2,0))) | B51: =IF($A51="","",VLOOKUP($A51,JOURNAL!$C$5:$I$1115,5,0)) | C51: =IF($A51="","",VLOOKUP($A51,JOURNAL!$C$5:$I$1115,2,0)) | D51: =IF($A51="","",VLOOKUP($A51,JOURNAL!$C$5:$I$1115,4,0)) | E51: =IF($A51="","",VLOOKUP($A51,JOURNAL!$C$5:$I$1115,3,0))
A52: =IF(A51="","",IF(ISNA(VLOOKUP($A$1&" / "&$A$47,INDIRECT(ADDRESS(A51+5,2,1,,"JOURNAL")&":G700"),2,0)),"",VLOOKUP($A$1&" / "&$A$47,INDIRECT(ADDRESS(A51+5,2,1,,"JOURNAL")&":G700"),2,0))) | B52: =IF($A52="","",VLOOKUP($A52,JOURNAL!$C$5:$I$1115,5,0)) | C52: =IF($A52="","",VLOOKUP($A52,JOURNAL!$C$5:$I$1115,2,0)) | D52: =IF($A52="","",VLOOKUP($A52,JOURNAL!$C$5:$I$1115,4,0)) | E52: =IF($A52="","",VLOOKUP($A52,JOURNAL!$C$5:$I$1115,3,0))
A53: =IF(A52="","",IF(ISNA(VLOOKUP($A$1&" / "&$A$47,INDIRECT(ADDRESS(A52+5,2,1,,"JOURNAL")&":G700"),2,0)),"",VLOOKUP($A$1&" / "&$A$47,INDIRECT(ADDRESS(A52+5,2,1,,"JOURNAL")&":G700"),2,0))) | B53: =IF($A53="","",VLOOKUP($A53,JOURNAL!$C$5:$I$1115,5,0)) | C53: =IF($A53="","",VLOOKUP($A53,JOURNAL!$C$5:$I$1115,2,0)) | D53: =IF($A53="","",VLOOKUP($A53,JOURNAL!$C$5:$I$1115,4,0)) | E53: =IF($A53="","",VLOOKUP($A53,JOURNAL!$C$5:$I$1115,3,0))
A54: =IF(A53="","",IF(ISNA(VLOOKUP($A$1&" / "&$A$47,INDIRECT(ADDRESS(A53+5,2,1,,"JOURNAL")&":G700"),2,0)),"",VLOOKUP($A$1&" / "&$A$47,INDIRECT(ADDRESS(A53+5,2,1,,"JOURNAL")&":G700"),2,0))) | B54: =IF($A54="","",VLOOKUP($A54,JOURNAL!$C$5:$I$1115,5,0)) | C54: =IF($A54="","",VLOOKUP($A54,JOURNAL!$C$5:$I$1115,2,0)) | D54: =IF($A54="","",VLOOKUP($A54,JOURNAL!$C$5:$I$1115,4,0)) | E54: =IF($A54="","",VLOOKUP($A54,JOURNAL!$C$5:$I$1115,3,0))
A55: {=IF(A54="","",IF(ISNA(VLOOKUP($A$1&" / "&$A$47,INDIRECT(ADDRESS(A54+5,2,1,,"JOURNAL")&":G500"),2,0)),"",VLOOKUP($A$1&" / "&$A$47,INDIRECT(ADDRESS(A54+5,2,1,,"JOURNAL")&":G500"),2,0)))} | B55: =IF($A55="","",VLOOKUP($A55,JOURNAL!$C$5:$I$1115,5,0)) | C55: =IF($A55="","",VLOOKUP($A55,JOURNAL!$C$5:$I$1115,2,0)) | D55: =IF($A55="","",VLOOKUP($A55,JOURNAL!$C$5:$I$1115,4,0)) | E55: =IF($A55="","",VLOOKUP($A55,JOURNAL!$C$5:$I$1115,3,0))
A56: Total | E56: =SUM(E49:E55) -> 0

Sheet ENTREES
A1: ENTREES
A3: BUDGET
A4: Charges
A5: Mois de facturation | B5: Libellé | E5: Montant
B6: SUISA | D6: 0.06 | E6: =D6*(E23) -> 1122
B7: Infomaniak frais vente en ligne | D7: 0.018 | E7: =E23*1.8/100 -> 336.6
B8: Infomaniak comission par billet | D8: 0.39 | E8: =D8*C19 -> 312
A12: Total | E12: =SUM(E6:E11) -> 1770.6
A13: Produits
A14: Mois de facturation | B14: Libellé | E14: Montant | F14: vendu 2025 | G14: dont rabais
B15: Early bird | C15: 350 | D15: 20 | E15: =C15*D15 -> 7000 | F15: 348 | G15: 161
B16: Préloc standard | C16: 300 | D16: 25 | E16: =C16*D16 -> 7500 | F16: 327 | G16: 30
B17: Sur place | C17: 150 | D17: 30 | E17: =C17*D17 -> 4500 | F17: 159
B18: reduc AGE | C18: 200 | D18: -5 | E18: =C18*D18 -> -1000 | F18: 191
B19: Total des entrées | C19: =SUM(C15:C17) -> 800 | F19: 144 | G19: gratuit
B20: Parking selon 25 (542.20) | E20: 500 | F20: =SUM(F15:F17) -> 834 | G20: total
B21: Vestiaires (basé sur 100 vestes) | E21: 200
A23: Total | E23: =SUM(E15:E22) -> 18700
A25: COMPTABILITE
A26: Charges
A27: N° | B27: Libellé | C27: Date | D27: En faveur de | E27: Montant
A28: =IF(ISNA(VLOOKUP($A$1&" / "&$A$26,JOURNAL!$B$5:$I$1115,2,0)),"",VLOOKUP($A$1&" / "&$A$26,JOURNAL!$B$5:$I$1115,2,0)) -> 163 | B28: =IF($A28="","",VLOOKUP($A28,JOURNAL!$C$5:$I$1115,5,0)) -> 0 | C28: =IF($A28="","",VLOOKUP($A28,JOURNAL!$C$5:$I$1115,2,0)) -> 46031 | D28: =IF($A28="","",VLOOKUP($A28,JOURNAL!$C$5:$I$1115,4,0)) -> SUISA | E28: =IF($A28="","",VLOOKUP($A28,JOURNAL!$C$5:$I$1115,3,0)) -> 1117.35
A29: =IF(A28="","",IF(ISNA(VLOOKUP($A$1&" / "&$A$26,INDIRECT(ADDRESS(A28+5,2,1,,"JOURNAL")&":G700"),2,0)),"",VLOOKUP($A$1&" / "&$A$26,INDIRECT(ADDRESS(A28+5,2,1,,"JOURNAL")&":G700"),2,0))) | B29: =IF($A29="","",VLOOKUP($A29,JOURNAL!$C$5:$I$1115,5,0)) | C29: =IF($A29="","",VLOOKUP($A29,JOURNAL!$C$5:$I$1115,2,0)) | D29: =IF($A29="","",VLOOKUP($A29,JOURNAL!$C$5:$I$1115,4,0)) | E29: =IF($A29="","",VLOOKUP($A29,JOURNAL!$C$5:$I$1115,3,0))
A30: =IF(A29="","",IF(ISNA(VLOOKUP($A$1&" / "&$A$26,INDIRECT(ADDRESS(A29+5,2,1,,"JOURNAL")&":G700"),2,0)),"",VLOOKUP($A$1&" / "&$A$26,INDIRECT(ADDRESS(A29+5,2,1,,"JOURNAL")&":G700"),2,0))) | B30: =IF($A30="","",VLOOKUP($A30,JOURNAL!$C$5:$I$1115,5,0)) | C30: =IF($A30="","",VLOOKUP($A30,JOURNAL!$C$5:$I$1115,2,0)) | D30: =IF($A30="","",VLOOKUP($A30,JOURNAL!$C$5:$I$1115,4,0)) | E30: =IF($A30="","",VLOOKUP($A30,JOURNAL!$C$5:$I$1115,3,0))
A31: =IF(A30="","",IF(ISNA(VLOOKUP($A$1&" / "&$A$26,INDIRECT(ADDRESS(A30+5,2,1,,"JOURNAL")&":G700"),2,0)),"",VLOOKUP($A$1&" / "&$A$26,INDIRECT(ADDRESS(A30+5,2,1,,"JOURNAL")&":G700"),2,0))) | B31: =IF($A31="","",VLOOKUP($A31,JOURNAL!$C$5:$I$1115,5,0)) | C31: =IF($A31="","",VLOOKUP($A31,JOURNAL!$C$5:$I$1115,2,0)) | D31: =IF($A31="","",VLOOKUP($A31,JOURNAL!$C$5:$I$1115,4,0)) | E31: =IF($A31="","",VLOOKUP($A31,JOURNAL!$C$5:$I$1115,3,0))
A32: =IF(A31="","",IF(ISNA(VLOOKUP($A$1&" / "&$A$26,INDIRECT(ADDRESS(A31+5,2,1,,"JOURNAL")&":G700"),2,0)),"",VLOOKUP($A$1&" / "&$A$26,INDIRECT(ADDRESS(A31+5,2,1,,"JOURNAL")&":G700"),2,0))) | B32: =IF($A32="","",VLOOKUP($A32,JOURNAL!$C$5:$I$1115,5,0)) | C32: =IF($A32="","",VLOOKUP($A32,JOURNAL!$C$5:$I$1115,2,0)) | D32: =IF($A32="","",VLOOKUP($A32,JOURNAL!$C$5:$I$1115,4,0)) | E32: =IF($A32="","",VLOOKUP($A32,JOURNAL!$C$5:$I$1115,3,0))
A33: =IF(A32="","",IF(ISNA(VLOOKUP($A$1&" / "&$A$26,INDIRECT(ADDRESS(A32+5,2,1,,"JOURNAL")&":G700"),2,0)),"",VLOOKUP($A$1&" / "&$A$26,INDIRECT(ADDRESS(A32+5,2,1,,"JOURNAL")&":G700"),2,0))) | B33: =IF($A33="","",VLOOKUP($A33,JOURNAL!$C$5:$I$1115,5,0)) | C33: =IF($A33="","",VLOOKUP($A33,JOURNAL!$C$5:$I$1115,2,0)) | D33: =IF($A33="","",VLOOKUP($A33,JOURNAL!$C$5:$I$1115,4,0)) | E33: =IF($A33="","",VLOOKUP($A33,JOURNAL!$C$5:$I$1115,3,0))
A34: {=IF(A33="","",IF(ISNA(VLOOKUP($A$1&" / "&$A$26,INDIRECT(ADDRESS(A33+5,2,1,,"JOURNAL")&":G500"),2,0)),"",VLOOKUP($A$1&" / "&$A$26,INDIRECT(ADDRESS(A33+5,2,1,,"JOURNAL")&":G500"),2,0)))} | B34: =IF($A34="","",VLOOKUP($A34,JOURNAL!$C$5:$I$1115,5,0)) | C34: =IF($A34="","",VLOOKUP($A34,JOURNAL!$C$5:$I$1115,2,0)) | D34: =IF($A34="","",VLOOKUP($A34,JOURNAL!$C$5:$I$1115,4,0)) | E34: =IF($A34="","",VLOOKUP($A34,JOURNAL!$C$5:$I$1115,3,0))
A35: Total | E35: =SUM(E28:E34) -> 1117.35
A36: Produits
A37: N° | B37: Libellé | C37: Date | D37: En faveur de | E37: Montant
A38: =IF(ISNA(VLOOKUP($A$1&" / "&$A$36,JOURNAL!$B$5:$I$1115,2,0)),"",VLOOKUP($A$1&" / "&$A$36,JOURNAL!$B$5:$I$1115,2,0)) -> 203 | B38: =IF($A38="","",VLOOKUP($A38,JOURNAL!$C$5:$I$1115,5,0)) -> Vente billets | C38: =IF($A38="","",VLOOKUP($A38,JOURNAL!$C$5:$I$1115,2,0)) -> 46090 | D38: =IF($A38="","",VLOOKUP($A38,JOURNAL!$C$5:$I$1115,4,0)) -> BLV | E38: =IF($A38="","",VLOOKUP($A38,JOURNAL!$C$5:$I$1115,3,0)) -> 702.75
A39: {=IF(A38="","",IF(ISNA(VLOOKUP($A$1&" / "&$A$36,INDIRECT(ADDRESS(A38+5,2,1,,"JOURNAL")&":G700"),2,0)),"",VLOOKUP($A$1&" / "&$A$36,INDIRECT(ADDRESS(A38+5,2,1,,"JOURNAL")&":G700"),2,0)))} | B39: =IF($A39="","",VLOOKUP($A39,JOURNAL!$C$5:$I$1115,5,0)) | C39: =IF($A39="","",VLOOKUP($A39,JOURNAL!$C$5:$I$1115,2,0)) | D39: =IF($A39="","",VLOOKUP($A39,JOURNAL!$C$5:$I$1115,4,0)) | E39: =IF($A39="","",VLOOKUP($A39,JOURNAL!$C$5:$I$1115,3,0))
A40: =IF(A39="","",IF(ISNA(VLOOKUP($A$1&" / "&$A$36,INDIRECT(ADDRESS(A39+5,2,1,,"JOURNAL")&":G500"),2,0)),"",VLOOKUP($A$1&" / "&$A$36,INDIRECT(ADDRESS(A39+5,2,1,,"JOURNAL")&":G500"),2,0))) | B40: =IF($A40="","",VLOOKUP($A40,JOURNAL!$C$5:$I$1115,5,0)) | C40: =IF($A40="","",VLOOKUP($A40,JOURNAL!$C$5:$I$1115,2,0)) | D40: =IF($A40="","",VLOOKUP($A40,JOURNAL!$C$5:$I$1115,4,0)) | E40: =IF($A40="","",VLOOKUP($A40,JOURNAL!$C$5:$I$1115,3,0))
A41: =IF(A40="","",IF(ISNA(VLOOKUP($A$1&" / "&$A$36,INDIRECT(ADDRESS(A40+5,2,1,,"JOURNAL")&":G500"),2,0)),"",VLOOKUP($A$1&" / "&$A$36,INDIRECT(ADDRESS(A40+5,2,1,,"JOURNAL")&":G500"),2,0))) | B41: =IF($A41="","",VLOOKUP($A41,JOURNAL!$C$5:$I$1115,5,0)) | C41: =IF($A41="","",VLOOKUP($A41,JOURNAL!$C$5:$I$1115,2,0)) | D41: =IF($A41="","",VLOOKUP($A41,JOURNAL!$C$5:$I$1115,4,0)) | E41: =IF($A41="","",VLOOKUP($A41,JOURNAL!$C$5:$I$1115,3,0))
A42: =IF(A41="","",IF(ISNA(VLOOKUP($A$1&" / "&$A$36,INDIRECT(ADDRESS(A41+5,2,1,,"JOURNAL")&":G500"),2,0)),"",VLOOKUP($A$1&" / "&$A$36,INDIRECT(ADDRESS(A41+5,2,1,,"JOURNAL")&":G500"),2,0))) | B42: =IF($A42="","",VLOOKUP($A42,JOURNAL!$C$5:$I$1115,5,0)) | C42: =IF($A42="","",VLOOKUP($A42,JOURNAL!$C$5:$I$1115,2,0)) | D42: =IF($A42="","",VLOOKUP($A42,JOURNAL!$C$5:$I$1115,4,0)) | E42: =IF($A42="","",VLOOKUP($A42,JOURNAL!$C$5:$I$1115,3,0))
A43: =IF(A42="","",IF(ISNA(VLOOKUP($A$1&" / "&$A$36,INDIRECT(ADDRESS(A42+5,2,1,,"JOURNAL")&":G500"),2,0)),"",VLOOKUP($A$1&" / "&$A$36,INDIRECT(ADDRESS(A42+5,2,1,,"JOURNAL")&":G500"),2,0))) | B43: =IF($A43="","",VLOOKUP($A43,JOURNAL!$C$5:$I$1115,5,0)) | C43: =IF($A43="","",VLOOKUP($A43,JOURNAL!$C$5:$I$1115,2,0)) | D43: =IF($A43="","",VLOOKUP($A43,JOURNAL!$C$5:$I$1115,4,0)) | E43: =IF($A43="","",VLOOKUP($A43,JOURNAL!$C$5:$I$1115,3,0))
A44: =IF(A43="","",IF(ISNA(VLOOKUP($A$1&" / "&$A$36,INDIRECT(ADDRESS(A43+5,2,1,,"JOURNAL")&":G500"),2,0)),"",VLOOKUP($A$1&" / "&$A$36,INDIRECT(ADDRESS(A43+5,2,1,,"JOURNAL")&":G500"),2,0))) | B44: =IF($A44="","",VLOOKUP($A44,JOURNAL!$C$5:$I$1115,5,0)) | C44: =IF($A44="","",VLOOKUP($A44,JOURNAL!$C$5:$I$1115,2,0)) | D44: =IF($A44="","",VLOOKUP($A44,JOURNAL!$C$5:$I$1115,4,0)) | E44: =IF($A44="","",VLOOKUP($A44,JOURNAL!$C$5:$I$1115,3,0))
A45: =IF(A44="","",IF(ISNA(VLOOKUP($A$1&" / "&$A$36,INDIRECT(ADDRESS(A44+5,2,1,,"JOURNAL")&":G500"),2,0)),"",VLOOKUP($A$1&" / "&$A$36,INDIRECT(ADDRESS(A44+5,2,1,,"JOURNAL")&":G500"),2,0))) | B45: =IF($A45="","",VLOOKUP($A45,JOURNAL!$C$5:$I$1115,5,0)) | C45: =IF($A45="","",VLOOKUP($A45,JOURNAL!$C$5:$I$1115,2,0)) | D45: =IF($A45="","",VLOOKUP($A45,JOURNAL!$C$5:$I$1115,4,0)) | E45: =IF($A45="","",VLOOKUP($A45,JOURNAL!$C$5:$I$1115,3,0))
A46: =IF(A45="","",IF(ISNA(VLOOKUP($A$1&" / "&$A$36,INDIRECT(ADDRESS(A45+5,2,1,,"JOURNAL")&":G500"),2,0)),"",VLOOKUP($A$1&" / "&$A$36,INDIRECT(ADDRESS(A45+5,2,1,,"JOURNAL")&":G500"),2,0))) | B46: =IF($A46="","",VLOOKUP($A46,JOURNAL!$C$5:$I$1115,5,0)) | C46: =IF($A46="","",VLOOKUP($A46,JOURNAL!$C$5:$I$1115,2,0)) | D46: =IF($A46="","",VLOOKUP($A46,JOURNAL!$C$5:$I$1115,4,0)) | E46: =IF($A46="","",VLOOKUP($A46,JOURNAL!$C$5:$I$1115,3,0))
A47: =IF(A46="","",IF(ISNA(VLOOKUP($A$1&" / "&$A$36,INDIRECT(ADDRESS(A46+5,2,1,,"JOURNAL")&":G500"),2,0)),"",VLOOKUP($A$1&" / "&$A$36,INDIRECT(ADDRESS(A46+5,2,1,,"JOURNAL")&":G500"),2,0))) | B47: =IF($A47="","",VLOOKUP($A47,JOURNAL!$C$5:$I$1115,5,0)) | C47: =IF($A47="","",VLOOKUP($A47,JOURNAL!$C$5:$I$1115,2,0)) | D47: =IF($A47="","",VLOOKUP($A47,JOURNAL!$C$5:$I$1115,4,0)) | E47: =IF($A47="","",VLOOKUP($A47,JOURNAL!$C$5:$I$1115,3,0))
A48: =IF(A47="","",IF(ISNA(VLOOKUP($A$1&" / "&$A$36,INDIRECT(ADDRESS(A47+5,2,1,,"JOURNAL")&":G500"),2,0)),"",VLOOKUP($A$1&" / "&$A$36,INDIRECT(ADDRESS(A47+5,2,1,,"JOURNAL")&":G500"),2,0))) | B48: =IF($A48="","",VLOOKUP($A48,JOURNAL!$C$5:$I$1115,5,0)) | C48: =IF($A48="","",VLOOKUP($A48,JOURNAL!$C$5:$I$1115,2,0)) | D48: =IF($A48="","",VLOOKUP($A48,JOURNAL!$C$5:$I$1115,4,0)) | E48: =IF($A48="","",VLOOKUP($A48,JOURNAL!$C$5:$I$1115,3,0))
A49: =IF(A48="","",IF(ISNA(VLOOKUP($A$1&" / "&$A$36,INDIRECT(ADDRESS(A48+5,2,1,,"JOURNAL")&":G500"),2,0)),"",VLOOKUP($A$1&" / "&$A$36,INDIRECT(ADDRESS(A48+5,2,1,,"JOURNAL")&":G500"),2,0))) | B49: =IF($A49="","",VLOOKUP($A49,JOURNAL!$C$5:$I$1115,5,0)) | C49: =IF($A49="","",VLOOKUP($A49,JOURNAL!$C$5:$I$1115,2,0)) | D49: =IF($A49="","",VLOOKUP($A49,JOURNAL!$C$5:$I$1115,4,0)) | E49: =IF($A49="","",VLOOKUP($A49,JOURNAL!$C$5:$I$1115,3,0))
A50: =IF(A49="","",IF(ISNA(VLOOKUP($A$1&" / "&$A$36,INDIRECT(ADDRESS(A49+5,2,1,,"JOURNAL")&":G500"),2,0)),"",VLOOKUP($A$1&" / "&$A$36,INDIRECT(ADDRESS(A49+5,2,1,,"JOURNAL")&":G500"),2,0))) | B50: =IF($A50="","",VLOOKUP($A50,JOURNAL!$C$5:$I$1115,5,0)) | C50: =IF($A50="","",VLOOKUP($A50,JOURNAL!$C$5:$I$1115,2,0)) | D50: =IF($A50="","",VLOOKUP($A50,JOURNAL!$C$5:$I$1115,4,0)) | E50: =IF($A50="","",VLOOKUP($A50,JOURNAL!$C$5:$I$1115,3,0))
A51: =IF(A50="","",IF(ISNA(VLOOKUP($A$1&" / "&$A$36,INDIRECT(ADDRESS(A50+5,2,1,,"JOURNAL")&":G500"),2,0)),"",VLOOKUP($A$1&" / "&$A$36,INDIRECT(ADDRESS(A50+5,2,1,,"JOURNAL")&":G500"),2,0))) | B51: =IF($A51="","",VLOOKUP($A51,JOURNAL!$C$5:$I$1115,5,0)) | C51: =IF($A51="","",VLOOKUP($A51,JOURNAL!$C$5:$I$1115,2,0)) | D51: =IF($A51="","",VLOOKUP($A51,JOURNAL!$C$5:$I$1115,4,0)) | E51: =IF($A51="","",VLOOKUP($A51,JOURNAL!$C$5:$I$1115,3,0))
A52: =IF(A51="","",IF(ISNA(VLOOKUP($A$1&" / "&$A$36,INDIRECT(ADDRESS(A51+5,2,1,,"JOURNAL")&":G500"),2,0)),"",VLOOKUP($A$1&" / "&$A$36,INDIRECT(ADDRESS(A51+5,2,1,,"JOURNAL")&":G500"),2,0))) | B52: =IF($A52="","",VLOOKUP($A52,JOURNAL!$C$5:$I$1115,5,0)) | C52: =IF($A52="","",VLOOKUP($A52,JOURNAL!$C$5:$I$1115,2,0)) | D52: =IF($A52="","",VLOOKUP($A52,JOURNAL!$C$5:$I$1115,4,0)) | E52: =IF($A52="","",VLOOKUP($A52,JOURNAL!$C$5:$I$1115,3,0))
A53: =IF(A52="","",IF(ISNA(VLOOKUP($A$1&" / "&$A$36,INDIRECT(ADDRESS(A52+5,2,1,,"JOURNAL")&":G500"),2,0)),"",VLOOKUP($A$1&" / "&$A$36,INDIRECT(ADDRESS(A52+5,2,1,,"JOURNAL")&":G500"),2,0))) | B53: =IF($A53="","",VLOOKUP($A53,JOURNAL!$C$5:$I$1115,5,0)) | C53: =IF($A53="","",VLOOKUP($A53,JOURNAL!$C$5:$I$1115,2,0)) | D53: =IF($A53="","",VLOOKUP($A53,JOURNAL!$C$5:$I$1115,4,0)) | E53: =IF($A53="","",VLOOKUP($A53,JOURNAL!$C$5:$I$1115,3,0)) | G53: =SUM(E47,E53,E45,E39,E42) -> 0
A54: =IF(A53="","",IF(ISNA(VLOOKUP($A$1&" / "&$A$36,INDIRECT(ADDRESS(A53+5,2,1,,"JOURNAL")&":G500"),2,0)),"",VLOOKUP($A$1&" / "&$A$36,INDIRECT(ADDRESS(A53+5,2,1,,"JOURNAL")&":G500"),2,0))) | B54: =IF($A54="","",VLOOKUP($A54,JOURNAL!$C$5:$I$1115,5,0)) | C54: =IF($A54="","",VLOOKUP($A54,JOURNAL!$C$5:$I$1115,2,0)) | D54: =IF($A54="","",VLOOKUP($A54,JOURNAL!$C$5:$I$1115,4,0)) | E54: =IF($A54="","",VLOOKUP($A54,JOURNAL!$C$5:$I$1115,3,0))
A55: =IF(A54="","",IF(ISNA(VLOOKUP($A$1&" / "&$A$36,INDIRECT(ADDRESS(A54+5,2,1,,"JOURNAL")&":G500"),2,0)),"",VLOOKUP($A$1&" / "&$A$36,INDIRECT(ADDRESS(A54+5,2,1,,"JOURNAL")&":G500"),2,0))) | B55: =IF($A55="","",VLOOKUP($A55,JOURNAL!$C$5:$I$1115,5,0)) | C55: =IF($A55="","",VLOOKUP($A55,JOURNAL!$C$5:$I$1115,2,0)) | D55: =IF($A55="","",VLOOKUP($A55,JOURNAL!$C$5:$I$1115,4,0)) | E55: =IF($A55="","",VLOOKUP($A55,JOURNAL!$C$5:$I$1115,3,0))
A56: =IF(A55="","",IF(ISNA(VLOOKUP($A$1&" / "&$A$36,INDIRECT(ADDRESS(A55+5,2,1,,"JOURNAL")&":G500"),2,0)),"",VLOOKUP($A$1&" / "&$A$36,INDIRECT(ADDRESS(A55+5,2,1,,"JOURNAL")&":G500"),2,0))) | B56: =IF($A56="","",VLOOKUP($A56,JOURNAL!$C$5:$I$1115,5,0)) | C56: =IF($A56="","",VLOOKUP($A56,JOURNAL!$C$5:$I$1115,2,0)) | D56: =IF($A56="","",VLOOKUP($A56,JOURNAL!$C$5:$I$1115,4,0)) | E56: =IF($A56="","",VLOOKUP($A56,JOURNAL!$C$5:$I$1115,3,0))
A57: =IF(A56="","",IF(ISNA(VLOOKUP($A$1&" / "&$A$36,INDIRECT(ADDRESS(A56+5,2,1,,"JOURNAL")&":G500"),2,0)),"",VLOOKUP($A$1&" / "&$A$36,INDIRECT(ADDRESS(A56+5,2,1,,"JOURNAL")&":G500"),2,0))) | B57: =IF($A57="","",VLOOKUP($A57,JOURNAL!$C$5:$I$1115,5,0)) | C57: =IF($A57="","",VLOOKUP($A57,JOURNAL!$C$5:$I$1115,2,0)) | D57: =IF($A57="","",VLOOKUP($A57,JOURNAL!$C$5:$I$1115,4,0)) | E57: =IF($A57="","",VLOOKUP($A57,JOURNAL!$C$5:$I$1115,3,0))
A58: =IF(A57="","",IF(ISNA(VLOOKUP($A$1&" / "&$A$36,INDIRECT(ADDRESS(A57+5,2,1,,"JOURNAL")&":G500"),2,0)),"",VLOOKUP($A$1&" / "&$A$36,INDIRECT(ADDRESS(A57+5,2,1,,"JOURNAL")&":G500"),2,0))) | B58: =IF($A58="","",VLOOKUP($A58,JOURNAL!$C$5:$I$1115,5,0)) | C58: =IF($A58="","",VLOOKUP($A58,JOURNAL!$C$5:$I$1115,2,0)) | D58: =IF($A58="","",VLOOKUP($A58,JOURNAL!$C$5:$I$1115,4,0)) | E58: =IF($A58="","",VLOOKUP($A58,JOURNAL!$C$5:$I$1115,3,0))
A59: =IF(A58="","",IF(ISNA(VLOOKUP($A$1&" / "&$A$36,INDIRECT(ADDRESS(A58+5,2,1,,"JOURNAL")&":G500"),2,0)),"",VLOOKUP($A$1&" / "&$A$36,INDIRECT(ADDRESS(A58+5,2,1,,"JOURNAL")&":G500"),2,0))) | B59: =IF($A59="","",VLOOKUP($A59,JOURNAL!$C$5:$I$1115,5,0)) | C59: =IF($A59="","",VLOOKUP($A59,JOURNAL!$C$5:$I$1115,2,0)) | D59: =IF($A59="","",VLOOKUP($A59,JOURNAL!$C$5:$I$1115,4,0)) | E59: =IF($A59="","",VLOOKUP($A59,JOURNAL!$C$5:$I$1115,3,0))
A60: =IF(A59="","",IF(ISNA(VLOOKUP($A$1&" / "&$A$36,INDIRECT(ADDRESS(A59+5,2,1,,"JOURNAL")&":G500"),2,0)),"",VLOOKUP($A$1&" / "&$A$36,INDIRECT(ADDRESS(A59+5,2,1,,"JOURNAL")&":G500"),2,0))) | B60: =IF($A60="","",VLOOKUP($A60,JOURNAL!$C$5:$I$1115,5,0)) | C60: =IF($A60="","",VLOOKUP($A60,JOURNAL!$C$5:$I$1115,2,0)) | D60: =IF($A60="","",VLOOKUP($A60,JOURNAL!$C$5:$I$1115,4,0)) | E60: =IF($A60="","",VLOOKUP($A60,JOURNAL!$C$5:$I$1115,3,0))
A61: =IF(A60="","",IF(ISNA(VLOOKUP($A$1&" / "&$A$36,INDIRECT(ADDRESS(A60+5,2,1,,"JOURNAL")&":G500"),2,0)),"",VLOOKUP($A$1&" / "&$A$36,INDIRECT(ADDRESS(A60+5,2,1,,"JOURNAL")&":G500"),2,0))) | B61: =IF($A61="","",VLOOKUP($A61,JOURNAL!$C$5:$I$1115,5,0)) | C61: =IF($A61="","",VLOOKUP($A61,JOURNAL!$C$5:$I$1115,2,0)) | D61: =IF($A61="","",VLOOKUP($A61,JOURNAL!$C$5:$I$1115,4,0)) | E61: =IF($A61="","",VLOOKUP($A61,JOURNAL!$C$5:$I$1115,3,0))
A62: =IF(A61="","",IF(ISNA(VLOOKUP($A$1&" / "&$A$36,INDIRECT(ADDRESS(A61+5,2,1,,"JOURNAL")&":G500"),2,0)),"",VLOOKUP($A$1&" / "&$A$36,INDIRECT(ADDRESS(A61+5,2,1,,"JOURNAL")&":G500"),2,0))) | B62: =IF($A62="","",VLOOKUP($A62,JOURNAL!$C$5:$I$1115,5,0)) | C62: =IF($A62="","",VLOOKUP($A62,JOURNAL!$C$5:$I$1115,2,0)) | D62: =IF($A62="","",VLOOKUP($A62,JOURNAL!$C$5:$I$1115,4,0)) | E62: =IF($A62="","",VLOOKUP($A62,JOURNAL!$C$5:$I$1115,3,0))
A63: =IF(A62="","",IF(ISNA(VLOOKUP($A$1&" / "&$A$36,INDIRECT(ADDRESS(A62+5,2,1,,"JOURNAL")&":G500"),2,0)),"",VLOOKUP($A$1&" / "&$A$36,INDIRECT(ADDRESS(A62+5,2,1,,"JOURNAL")&":G500"),2,0))) | B63: =IF($A63="","",VLOOKUP($A63,JOURNAL!$C$5:$I$1115,5,0)) | C63: =IF($A63="","",VLOOKUP($A63,JOURNAL!$C$5:$I$1115,2,0)) | D63: =IF($A63="","",VLOOKUP($A63,JOURNAL!$C$5:$I$1115,4,0)) | E63: =IF($A63="","",VLOOKUP($A63,JOURNAL!$C$5:$I$1115,3,0))
A64: =IF(A63="","",IF(ISNA(VLOOKUP($A$1&" / "&$A$36,INDIRECT(ADDRESS(A63+5,2,1,,"JOURNAL")&":G500"),2,0)),"",VLOOKUP($A$1&" / "&$A$36,INDIRECT(ADDRESS(A63+5,2,1,,"JOURNAL")&":G500"),2,0))) | B64: =IF($A64="","",VLOOKUP($A64,JOURNAL!$C$5:$I$1115,5,0)) | C64: =IF($A64="","",VLOOKUP($A64,JOURNAL!$C$5:$I$1115,2,0)) | D64: =IF($A64="","",VLOOKUP($A64,JOURNAL!$C$5:$I$1115,4,0)) | E64: =IF($A64="","",VLOOKUP($A64,JOURNAL!$C$5:$I$1115,3,0))
A65: =IF(A64="","",IF(ISNA(VLOOKUP($A$1&" / "&$A$36,INDIRECT(ADDRESS(A64+5,2,1,,"JOURNAL")&":G500"),2,0)),"",VLOOKUP($A$1&" / "&$A$36,INDIRECT(ADDRESS(A64+5,2,1,,"JOURNAL")&":G500"),2,0))) | B65: =IF($A65="","",VLOOKUP($A65,JOURNAL!$C$5:$I$1115,5,0)) | C65: =IF($A65="","",VLOOKUP($A65,JOURNAL!$C$5:$I$1115,2,0)) | D65: =IF($A65="","",VLOOKUP($A65,JOURNAL!$C$5:$I$1115,4,0)) | E65: =IF($A65="","",VLOOKUP($A65,JOURNAL!$C$5:$I$1115,3,0))
A66: =IF(A65="","",IF(ISNA(VLOOKUP($A$1&" / "&$A$36,INDIRECT(ADDRESS(A65+5,2,1,,"JOURNAL")&":G500"),2,0)),"",VLOOKUP($A$1&" / "&$A$36,INDIRECT(ADDRESS(A65+5,2,1,,"JOURNAL")&":G500"),2,0))) | B66: =IF($A66="","",VLOOKUP($A66,JOURNAL!$C$5:$I$1115,5,0)) | C66: =IF($A66="","",VLOOKUP($A66,JOURNAL!$C$5:$I$1115,2,0)) | D66: =IF($A66="","",VLOOKUP($A66,JOURNAL!$C$5:$I$1115,4,0)) | E66: =IF($A66="","",VLOOKUP($A66,JOURNAL!$C$5:$I$1115,3,0))
A67: =IF(A66="","",IF(ISNA(VLOOKUP($A$1&" / "&$A$36,INDIRECT(ADDRESS(A66+5,2,1,,"JOURNAL")&":G700"),2,0)),"",VLOOKUP($A$1&" / "&$A$36,INDIRECT(ADDRESS(A66+5,2,1,,"JOURNAL")&":G700"),2,0))) | B67: =IF($A67="","",VLOOKUP($A67,JOURNAL!$C$5:$I$1115,5,0)) | C67: =IF($A67="","",VLOOKUP($A67,JOURNAL!$C$5:$I$1115,2,0)) | D67: =IF($A67="","",VLOOKUP($A67,JOURNAL!$C$5:$I$1115,4,0)) | E67: =IF($A67="","",VLOOKUP($A67,JOURNAL!$C$5:$I$1115,3,0))
A68: =IF(A67="","",IF(ISNA(VLOOKUP($A$1&" / "&$A$36,INDIRECT(ADDRESS(A67+5,2,1,,"JOURNAL")&":G700"),2,0)),"",VLOOKUP($A$1&" / "&$A$36,INDIRECT(ADDRESS(A67+5,2,1,,"JOURNAL")&":G700"),2,0))) | B68: =IF($A68="","",VLOOKUP($A68,JOURNAL!$C$5:$I$1115,5,0)) | C68: =IF($A68="","",VLOOKUP($A68,JOURNAL!$C$5:$I$1115,2,0)) | D68: =IF($A68="","",VLOOKUP($A68,JOURNAL!$C$5:$I$1115,4,0)) | E68: =IF($A68="","",VLOOKUP($A68,JOURNAL!$C$5:$I$1115,3,0))
A69: =IF(A68="","",IF(ISNA(VLOOKUP($A$1&" / "&$A$36,INDIRECT(ADDRESS(A68+5,2,1,,"JOURNAL")&":G700"),2,0)),"",VLOOKUP($A$1&" / "&$A$36,INDIRECT(ADDRESS(A68+5,2,1,,"JOURNAL")&":G700"),2,0))) | B69: =IF($A69="","",VLOOKUP($A69,JOURNAL!$C$5:$I$1115,5,0)) | C69: =IF($A69="","",VLOOKUP($A69,JOURNAL!$C$5:$I$1115,2,0)) | D69: =IF($A69="","",VLOOKUP($A69,JOURNAL!$C$5:$I$1115,4,0)) | E69: =IF($A69="","",VLOOKUP($A69,JOURNAL!$C$5:$I$1115,3,0))
A70: =IF(A69="","",IF(ISNA(VLOOKUP($A$1&" / "&$A$36,INDIRECT(ADDRESS(A69+5,2,1,,"JOURNAL")&":G700"),2,0)),"",VLOOKUP($A$1&" / "&$A$36,INDIRECT(ADDRESS(A69+5,2,1,,"JOURNAL")&":G700"),2,0))) | B70: =IF($A70="","",VLOOKUP($A70,JOURNAL!$C$5:$I$1115,5,0)) | C70: =IF($A70="","",VLOOKUP($A70,JOURNAL!$C$5:$I$1115,2,0)) | D70: =IF($A70="","",VLOOKUP($A70,JOURNAL!$C$5:$I$1115,4,0)) | E70: =IF($A70="","",VLOOKUP($A70,JOURNAL!$C$5:$I$1115,3,0))
A71: =IF(A70="","",IF(ISNA(VLOOKUP($A$1&" / "&$A$36,INDIRECT(ADDRESS(A70+5,2,1,,"JOURNAL")&":G700"),2,0)),"",VLOOKUP($A$1&" / "&$A$36,INDIRECT(ADDRESS(A70+5,2,1,,"JOURNAL")&":G700"),2,0))) | B71: =IF($A71="","",VLOOKUP($A71,JOURNAL!$C$5:$I$1115,5,0)) | C71: =IF($A71="","",VLOOKUP($A71,JOURNAL!$C$5:$I$1115,2,0)) | D71: =IF($A71="","",VLOOKUP($A71,JOURNAL!$C$5:$I$1115,4,0)) | E71: =IF($A71="","",VLOOKUP($A71,JOURNAL!$C$5:$I$1115,3,0))
A72: =IF(A71="","",IF(ISNA(VLOOKUP($A$1&" / "&$A$36,INDIRECT(ADDRESS(A71+5,2,1,,"JOURNAL")&":G700"),2,0)),"",VLOOKUP($A$1&" / "&$A$36,INDIRECT(ADDRESS(A71+5,2,1,,"JOURNAL")&":G700"),2,0))) | B72: =IF($A72="","",VLOOKUP($A72,JOURNAL!$C$5:$I$1115,5,0)) | C72: =IF($A72="","",VLOOKUP($A72,JOURNAL!$C$5:$I$1115,2,0)) | D72: =IF($A72="","",VLOOKUP($A72,JOURNAL!$C$5:$I$1115,4,0)) | E72: =IF($A72="","",VLOOKUP($A72,JOURNAL!$C$5:$I$1115,3,0))
A73: =IF(A72="","",IF(ISNA(VLOOKUP($A$1&" / "&$A$36,INDIRECT(ADDRESS(A72+5,2,1,,"JOURNAL")&":G700"),2,0)),"",VLOOKUP($A$1&" / "&$A$36,INDIRECT(ADDRESS(A72+5,2,1,,"JOURNAL")&":G700"),2,0))) | B73: =IF($A73="","",VLOOKUP($A73,JOURNAL!$C$5:$I$1115,5,0)) | C73: =IF($A73="","",VLOOKUP($A73,JOURNAL!$C$5:$I$1115,2,0)) | D73: =IF($A73="","",VLOOKUP($A73,JOURNAL!$C$5:$I$1115,4,0)) | E73: =IF($A73="","",VLOOKUP($A73,JOURNAL!$C$5:$I$1115,3,0))
A74: =IF(A73="","",IF(ISNA(VLOOKUP($A$1&" / "&$A$36,INDIRECT(ADDRESS(A73+5,2,1,,"JOURNAL")&":G700"),2,0)),"",VLOOKUP($A$1&" / "&$A$36,INDIRECT(ADDRESS(A73+5,2,1,,"JOURNAL")&":G700"),2,0))) | B74: =IF($A74="","",VLOOKUP($A74,JOURNAL!$C$5:$I$1115,5,0)) | C74: =IF($A74="","",VLOOKUP($A74,JOURNAL!$C$5:$I$1115,2,0)) | D74: =IF($A74="","",VLOOKUP($A74,JOURNAL!$C$5:$I$1115,4,0)) | E74: =IF($A74="","",VLOOKUP($A74,JOURNAL!$C$5:$I$1115,3,0))
A75: =IF(A74="","",IF(ISNA(VLOOKUP($A$1&" / "&$A$36,INDIRECT(ADDRESS(A74+5,2,1,,"JOURNAL")&":G700"),2,0)),"",VLOOKUP($A$1&" / "&$A$36,INDIRECT(ADDRESS(A74+5,2,1,,"JOURNAL")&":G700"),2,0))) | B75: =IF($A75="","",VLOOKUP($A75,JOURNAL!$C$5:$I$1115,5,0)) | C75: =IF($A75="","",VLOOKUP($A75,JOURNAL!$C$5:$I$1115,2,0)) | D75: =IF($A75="","",VLOOKUP($A75,JOURNAL!$C$5:$I$1115,4,0)) | E75: =IF($A75="","",VLOOKUP($A75,JOURNAL!$C$5:$I$1115,3,0))
A76: =IF(A75="","",IF(ISNA(VLOOKUP($A$1&" / "&$A$36,INDIRECT(ADDRESS(A75+5,2,1,,"JOURNAL")&":G700"),2,0)),"",VLOOKUP($A$1&" / "&$A$36,INDIRECT(ADDRESS(A75+5,2,1,,"JOURNAL")&":G700"),2,0))) | B76: =IF($A76="","",VLOOKUP($A76,JOURNAL!$C$5:$I$1115,5,0)) | C76: =IF($A76="","",VLOOKUP($A76,JOURNAL!$C$5:$I$1115,2,0)) | D76: =IF($A76="","",VLOOKUP($A76,JOURNAL!$C$5:$I$1115,4,0)) | E76: =IF($A76="","",VLOOKUP($A76,JOURNAL!$C$5:$I$1115,3,0))
A77: =IF(A76="","",IF(ISNA(VLOOKUP($A$1&" / "&$A$36,INDIRECT(ADDRESS(A76+5,2,1,,"JOURNAL")&":G700"),2,0)),"",VLOOKUP($A$1&" / "&$A$36,INDIRECT(ADDRESS(A76+5,2,1,,"JOURNAL")&":G700"),2,0))) | B77: =IF($A77="","",VLOOKUP($A77,JOURNAL!$C$5:$I$1115,5,0)) | C77: =IF($A77="","",VLOOKUP($A77,JOURNAL!$C$5:$I$1115,2,0)) | D77: =IF($A77="","",VLOOKUP($A77,JOURNAL!$C$5:$I$1115,4,0)) | E77: =IF($A77="","",VLOOKUP($A77,JOURNAL!$C$5:$I$1115,3,0))
A78: =IF(A77="","",IF(ISNA(VLOOKUP($A$1&" / "&$A$36,INDIRECT(ADDRESS(A77+5,2,1,,"JOURNAL")&":G700"),2,0)),"",VLOOKUP($A$1&" / "&$A$36,INDIRECT(ADDRESS(A77+5,2,1,,"JOURNAL")&":G700"),2,0))) | B78: =IF($A78="","",VLOOKUP($A78,JOURNAL!$C$5:$I$1115,5,0)) | C78: =IF($A78="","",VLOOKUP($A78,JOURNAL!$C$5:$I$1115,2,0)) | D78: =IF($A78="","",VLOOKUP($A78,JOURNAL!$C$5:$I$1115,4,0)) | E78: =IF($A78="","",VLOOKUP($A78,JOURNAL!$C$5:$I$1115,3,0))
... A98: =IF(A97="","",IF(ISNA(VLOOKUP($A$1&" / "&$A$36,INDIRECT(ADDRESS(A97+5,2,1,,"JOURNAL")&":G700"),2,0)),"",VLOOKUP($A$1&" / "&$A$36,INDIRECT(ADDRESS(A97+5,2,1,,"JOURNAL")&":G700"),2,0))) | B98: =IF($A98="","",VLOOKUP($A98,JOURNAL!$C$5:$I$1115,5,0)) | C98: =IF($A98="","",VLOOKUP($A98,JOURNAL!$C$5:$I$1115,2,0)) | D98: =IF($A98="","",VLOOKUP($A98,JOURNAL!$C$5:$I$1115,4,0)) | E98: =IF($A98="","",VLOOKUP($A98,JOURNAL!$C$5:$I$1115,3,0))
A99: Total | E99: =SUM(E38:E98) -> 702.75

Sheet EVENTS
A1: EVENTS
A3: BUDGET
A4: Charges
A5: Mois de facturation | B5: Libellé | C5: Date | D5: En faveur de | E5: Montant
A6: Septembre | B6: Journée d'accueil | E6: 54
A7: Septembre | B7: Semaine Grillades 1 (rentrée) | E7: 1075
B8: Semaine de vin chaud | E8: 1700
B9: Semaine Grillades 2 (montage) | E9: 1000
B10: Grosse Murge GM | E10: 600
B11: Raclette inter-asso | E11: 500
B12: Vestiaire Amalgame | E12: 100
B13: After | E13: 800
B14: Tremplin | E14: 800
B15: Apéro de soutien | E15: 300
B16: CRUNCH | E16: 750
B17: Baleiski | D17: (600 de bouffe) | E17: 1800
B18: local baleinev | E18: 1000
B19: Passation pouvoir | E19: 400
B20: Marché de Noel | E20: 5300 | F20: peut-être moins au vu des reserves à la cave
A21: Total | E21: =SUM(E6:E20) -> 16179
A22: Produits
A23: Mois de facturation | B23: Libellé | C23: Date | D23: En faveur de | E23: Montant
B24: Journée d'accueil | E24: 155
B25: Nourriture GM + participation | E25: 500
B26: raclette inter-asso | E26: 200
B27: Semaine Grillades 1 (rentrée) | E27: 1902
B28: semaine de vin chaud | E28: 7000
B29: Semaine Grillades 2 (montage) | E29: 1800 | F29: compliqué
B30: Vestiaire Amalgame | E30: 800
B31: local baleinev | E31: 1000
B32: Semaine montage | E32: 5000 | F32: compliqué
B33: Tremplin | E33: 2500
B34: Apéro de soutien | E34: 1600
B35: CRUNCH | E35: 2000
B36: After | E36: 3000
B37: Baleiski participation | E37: 1250
B38: Marché de Noel | E38: 10000
A39: Total | E39: =SUM(E25:E38) -> 38552
A41: COMPTABILITE
A42: Charges
A43: N° | B43: Libellé | C43: Date | D43: En faveur de | E43: Montant
A44: =IF(ISNA(VLOOKUP($A$1&" / "&$A$42,JOURNAL!$B$5:$I$1115,2,0)),"",VLOOKUP($A$1&" / "&$A$42,JOURNAL!$B$5:$I$116,2,0)) -> 2 | B44: =IF($A44="","",VLOOKUP($A44,JOURNAL!$C$5:$I$1115,5,0)) -> JA : Charbon | C44: =IF($A44="","",VLOOKUP($A44,JOURNAL!$C$5:$I$1115,2,0)) -> 45912 | D44: =IF($A44="","",VLOOKUP($A44,JOURNAL!$C$5:$I$1115,4,0)) -> Landi | E44: =IF($A44="","",VLOOKUP($A44,JOURNAL!$C$5:$I$1115,3,0)) -> 54
A45: =IF(A44="","",IF(ISNA(VLOOKUP($A$1&" / "&$A$42,INDIRECT(ADDRESS(A44+5,2,1,,"JOURNAL")&":G500"),2,0)),"",VLOOKUP($A$1&" / "&$A$42,INDIRECT(ADDRESS(A44+5,2,1,,"JOURNAL")&":G500"),2,0))) -> 3 | B45: =IF($A45="","",VLOOKUP($A45,JOURNAL!$C$5:$I$1115,5,0)) -> SG1 : Charbon | C45: =IF($A45="","",VLOOKUP($A45,JOURNAL!$C$5:$I$1115,2,0)) -> 46279 | D45: =IF($A45="","",VLOOKUP($A45,JOURNAL!$C$5:$I$1115,4,0)) -> Landi | E45: =IF($A45="","",VLOOKUP($A45,JOURNAL!$C$5:$I$1115,3,0)) -> 175.5
A46: =IF(A45="","",IF(ISNA(VLOOKUP($A$1&" / "&$A$42,INDIRECT(ADDRESS(A45+5,2,1,,"JOURNAL")&":G500"),2,0)),"",VLOOKUP($A$1&" / "&$A$42,INDIRECT(ADDRESS(A45+5,2,1,,"JOURNAL")&":G500"),2,0))) -> 21 | B46: =IF($A46="","",VLOOKUP($A46,JOURNAL!$C$5:$I$1115,5,0)) -> JA : Bonbons | C46: =IF($A46="","",VLOOKUP($A46,JOURNAL!$C$5:$I$1115,2,0)) -> 45911 | D46: =IF($A46="","",VLOOKUP($A46,JOURNAL!$C$5:$I$1115,4,0)) -> Denner | E46: =IF($A46="","",VLOOKUP($A46,JOURNAL!$C$5:$I$1115,3,0)) -> 10.5
A47: =IF(A46="","",IF(ISNA(VLOOKUP($A$1&" / "&$A$42,INDIRECT(ADDRESS(A46+5,2,1,,"JOURNAL")&":G500"),2,0)),"",VLOOKUP($A$1&" / "&$A$42,INDIRECT(ADDRESS(A46+5,2,1,,"JOURNAL")&":G500"),2,0))) -> 22 | B47: =IF($A47="","",VLOOKUP($A47,JOURNAL!$C$5:$I$1115,5,0)) -> JA : Softs | C47: =IF($A47="","",VLOOKUP($A47,JOURNAL!$C$5:$I$1115,2,0)) -> 45911 | D47: =IF($A47="","",VLOOKUP($A47,JOURNAL!$C$5:$I$1115,4,0)) -> Landi | E47: =IF($A47="","",VLOOKUP($A47,JOURNAL!$C$5:$I$1115,3,0)) -> 15
A48: =IF(A47="","",IF(ISNA(VLOOKUP($A$1&" / "&$A$42,INDIRECT(ADDRESS(A47+5,2,1,,"JOURNAL")&":G500"),2,0)),"",VLOOKUP($A$1&" / "&$A$42,INDIRECT(ADDRESS(A47+5,2,1,,"JOURNAL")&":G500"),2,0))) -> 24 | B48: =IF($A48="","",VLOOKUP($A48,JOURNAL!$C$5:$I$1115,5,0)) -> Caution GM | C48: =IF($A48="","",VLOOKUP($A48,JOURNAL!$C$5:$I$1115,2,0)) -> 45917 | D48: =IF($A48="","",VLOOKUP($A48,JOURNAL!$C$5:$I$1115,4,0)) -> Commune de Cheseaux | E48: =IF($A48="","",VLOOKUP($A48,JOURNAL!$C$5:$I$1115,3,0)) -> 500
A49: =IF(A48="","",IF(ISNA(VLOOKUP($A$1&" / "&$A$42,INDIRECT(ADDRESS(A48+5,2,1,,"JOURNAL")&":G500"),2,0)),"",VLOOKUP($A$1&" / "&$A$42,INDIRECT(ADDRESS(A48+5,2,1,,"JOURNAL")&":G500"),2,0))) -> 25 | B49: =IF($A49="","",VLOOKUP($A49,JOURNAL!$C$5:$I$1115,5,0)) -> SG1 : Courses Hot Dogs | C49: =IF($A49="","",VLOOKUP($A49,JOURNAL!$C$5:$I$1115,2,0)) -> 45918 | D49: =IF($A49="","",VLOOKUP($A49,JOURNAL!$C$5:$I$1115,4,0)) -> Thomas Brêchet | E49: =IF($A49="","",VLOOKUP($A49,JOURNAL!$C$5:$I$1115,3,0)) -> 20.5
A50: =IF(A49="","",IF(ISNA(VLOOKUP($A$1&" / "&$A$42,INDIRECT(ADDRESS(A49+5,2,1,,"JOURNAL")&":G500"),2,0)),"",VLOOKUP($A$1&" / "&$A$42,INDIRECT(ADDRESS(A49+5,2,1,,"JOURNAL")&":G500"),2,0))) -> 26 | B50: =IF($A50="","",VLOOKUP($A50,JOURNAL!$C$5:$I$1115,5,0)) -> SG1 : Courses Hot Dogs | C50: =IF($A50="","",VLOOKUP($A50,JOURNAL!$C$5:$I$1115,2,0)) -> 45918 | D50: =IF($A50="","",VLOOKUP($A50,JOURNAL!$C$5:$I$1115,4,0)) -> Thomas Brêchet | E50: =IF($A50="","",VLOOKUP($A50,JOURNAL!$C$5:$I$1115,3,0)) -> 47.25
A51: =IF(A50="","",IF(ISNA(VLOOKUP($A$1&" / "&$A$42,INDIRECT(ADDRESS(A50+5,2,1,,"JOURNAL")&":G500"),2,0)),"",VLOOKUP($A$1&" / "&$A$42,INDIRECT(ADDRESS(A50+5,2,1,,"JOURNAL")&":G500"),2,0))) -> 27 | B51: =IF($A51="","",VLOOKUP($A51,JOURNAL!$C$5:$I$1115,5,0)) -> SG1 : Courses after (softs) | C51: =IF($A51="","",VLOOKUP($A51,JOURNAL!$C$5:$I$1115,2,0)) -> 45919 | D51: =IF($A51="","",VLOOKUP($A51,JOURNAL!$C$5:$I$1115,4,0)) -> Landi | E51: =IF($A51="","",VLOOKUP($A51,JOURNAL!$C$5:$I$1115,3,0)) -> 21.6
A52: =IF(A51="","",IF(ISNA(VLOOKUP($A$1&" / "&$A$42,INDIRECT(ADDRESS(A51+5,2,1,,"JOURNAL")&":G500"),2,0)),"",VLOOKUP($A$1&" / "&$A$42,INDIRECT(ADDRESS(A51+5,2,1,,"JOURNAL")&":G500"),2,0))) -> 33 | B52: =IF($A52="","",VLOOKUP($A52,JOURNAL!$C$5:$I$1115,5,0)) -> DrawOnMe : croques monsieur | C52: =IF($A52="","",VLOOKUP($A52,JOURNAL!$C$5:$I$1115,2,0)) -> 45938 | D52: =IF($A52="","",VLOOKUP($A52,JOURNAL!$C$5:$I$1115,4,0)) -> Thomas Brêchet | E52: =IF($A52="","",VLOOKUP($A52,JOURNAL!$C$5:$I$1115,3,0)) -> 47.05
A53: =IF(A52="","",IF(ISNA(VLOOKUP($A$1&" / "&$A$42,INDIRECT(ADDRESS(A52+5,2,1,,"JOURNAL")&":G500"),2,0)),"",VLOOKUP($A$1&" / "&$A$42,INDIRECT(ADDRESS(A52+5,2,1,,"JOURNAL")&":G500"),2,0))) -> 34 | B53: =IF($A53="","",VLOOKUP($A53,JOURNAL!$C$5:$I$1115,5,0)) -> Courses GM - 26.85 possiblement pas remboursé | C53: =IF($A53="","",VLOOKUP($A53,JOURNAL!$C$5:$I$1115,2,0)) -> 45933 | D53: =IF($A53="","",VLOOKUP($A53,JOURNAL!$C$5:$I$1115,4,0)) -> Maxime Magnenat | E53: =IF($A53="","",VLOOKUP($A53,JOURNAL!$C$5:$I$1115,3,0)) -> 0
A54: =IF(A53="","",IF(ISNA(VLOOKUP($A$1&" / "&$A$42,INDIRECT(ADDRESS(A53+5,2,1,,"JOURNAL")&":G500"),2,0)),"",VLOOKUP($A$1&" / "&$A$42,INDIRECT(ADDRESS(A53+5,2,1,,"JOURNAL")&":G500"),2,0))) -> 36 | B54: =IF($A54="","",VLOOKUP($A54,JOURNAL!$C$5:$I$1115,5,0)) -> Fromage GM | C54: =IF($A54="","",VLOOKUP($A54,JOURNAL!$C$5:$I$1115,2,0)) -> 45935 | D54: =IF($A54="","",VLOOKUP($A54,JOURNAL!$C$5:$I$1115,4,0)) -> Laiterie du Chateau | E54: =IF($A54="","",VLOOKUP($A54,JOURNAL!$C$5:$I$1115,3,0)) -> 150
A55: =IF(A54="","",IF(ISNA(VLOOKUP($A$1&" / "&$A$42,INDIRECT(ADDRESS(A54+5,2,1,,"JOURNAL")&":G500"),2,0)),"",VLOOKUP($A$1&" / "&$A$42,INDIRECT(ADDRESS(A54+5,2,1,,"JOURNAL")&":G500"),2,0))) -> 37 | B55: =IF($A55="","",VLOOKUP($A55,JOURNAL!$C$5:$I$1115,5,0)) -> Pain GM | C55: =IF($A55="","",VLOOKUP($A55,JOURNAL!$C$5:$I$1115,2,0)) -> 45935 | D55: =IF($A55="","",VLOOKUP($A55,JOURNAL!$C$5:$I$1115,4,0)) -> Boulangerie du Chateau | E55: =IF($A55="","",VLOOKUP($A55,JOURNAL!$C$5:$I$1115,3,0)) -> 91.8
A56: =IF(A55="","",IF(ISNA(VLOOKUP($A$1&" / "&$A$42,INDIRECT(ADDRESS(A55+5,2,1,,"JOURNAL")&":G500"),2,0)),"",VLOOKUP($A$1&" / "&$A$42,INDIRECT(ADDRESS(A55+5,2,1,,"JOURNAL")&":G500"),2,0))) -> 38 | B56: =IF($A56="","",VLOOKUP($A56,JOURNAL!$C$5:$I$1115,5,0)) -> Bières SG1 et JACC | C56: =IF($A56="","",VLOOKUP($A56,JOURNAL!$C$5:$I$1115,2,0)) -> 45943 | D56: =IF($A56="","",VLOOKUP($A56,JOURNAL!$C$5:$I$1115,4,0)) -> Chopfab Boxer | E56: =IF($A56="","",VLOOKUP($A56,JOURNAL!$C$5:$I$1115,3,0)) -> 968.48
... A120: =IF(A119="","",IF(ISNA(VLOOKUP($A$1&" / "&$A$42,INDIRECT(ADDRESS(A119+5,2,1,,"JOURNAL")&":G500"),2,0)),"",VLOOKUP($A$1&" / "&$A$42,INDIRECT(ADDRESS(A119+5,2,1,,"JOURNAL")&":G500"),2,0))) | B120: =IF($A120="","",VLOOKUP($A120,JOURNAL!$C$5:$I$1115,5,0)) | C120: =IF($A120="","",VLOOKUP($A120,JOURNAL!$C$5:$I$1115,2,0)) | D120: =IF($A120="","",VLOOKUP($A120,JOURNAL!$C$5:$I$1115,4,0)) | E120: =IF($A120="","",VLOOKUP($A120,JOURNAL!$C$5:$I$1115,3,0))
A121: =IF(A120="","",IF(ISNA(VLOOKUP($A$1&" / "&$A$42,INDIRECT(ADDRESS(A120+5,2,1,,"JOURNAL")&":G700"),2,0)),"",VLOOKUP($A$1&" / "&$A$42,INDIRECT(ADDRESS(A120+5,2,1,,"JOURNAL")&":G700"),2,0))) | B121: =IF($A121="","",VLOOKUP($A121,JOURNAL!$C$5:$I$1115,5,0)) | C121: =IF($A121="","",VLOOKUP($A121,JOURNAL!$C$5:$I$1115,2,0)) | D121: =IF($A121="","",VLOOKUP($A121,JOURNAL!$C$5:$I$1115,4,0)) | E121: =IF($A121="","",VLOOKUP($A121,JOURNAL!$C$5:$I$1115,3,0))
A122: =IF(A121="","",IF(ISNA(VLOOKUP($A$1&" / "&$A$42,INDIRECT(ADDRESS(A121+5,2,1,,"JOURNAL")&":G700"),2,0)),"",VLOOKUP($A$1&" / "&$A$42,INDIRECT(ADDRESS(A121+5,2,1,,"JOURNAL")&":G700"),2,0))) | B122: =IF($A122="","",VLOOKUP($A122,JOURNAL!$C$5:$I$1115,5,0)) | C122: =IF($A122="","",VLOOKUP($A122,JOURNAL!$C$5:$I$1115,2,0)) | D122: =IF($A122="","",VLOOKUP($A122,JOURNAL!$C$5:$I$1115,4,0)) | E122: =IF($A122="","",VLOOKUP($A122,JOURNAL!$C$5:$I$1115,3,0))
A123: =IF(A122="","",IF(ISNA(VLOOKUP($A$1&" / "&$A$42,INDIRECT(ADDRESS(A122+5,2,1,,"JOURNAL")&":G700"),2,0)),"",VLOOKUP($A$1&" / "&$A$42,INDIRECT(ADDRESS(A122+5,2,1,,"JOURNAL")&":G700"),2,0))) | B123: =IF($A123="","",VLOOKUP($A123,JOURNAL!$C$5:$I$1115,5,0)) | C123: =IF($A123="","",VLOOKUP($A123,JOURNAL!$C$5:$I$1115,2,0)) | D123: =IF($A123="","",VLOOKUP($A123,JOURNAL!$C$5:$I$1115,4,0)) | E123: =IF($A123="","",VLOOKUP($A123,JOURNAL!$C$5:$I$1115,3,0))
